Workbook
Name Anchor: Config!$B$8
Name CostEq: Config!$B$4
Name CostFI: Config!$B$5
Name EdgeEq: Config!$B$6
Name EdgeFI: Config!$B$7
Name ExDivFlag: Config!$B$10
Name SessionLeft: Feed!$R$2
Name StaleMin: Config!$B$9

Sheet Dashboard
A1: 09:00 market closed
A2: Ticker | B2: Signal | C2: β / Wt | D2: Last | E2: Bid | F2: Ask | G2: Bid Sz | H2: Ask Sz | I2: Spread bps | J2: Chg % | K2: Volume | L2: Avg Vol | M2: Rel Vol | N2: σ 1D | O2: Move σ | P2: P>1σ | Q2: P>2σ | R2: P>3σ | S2: NAV T-1 | T2: Prem T-1 bps | U2: Und Move | V2: Fair Value | W2: vs FV bps | X2: Sell Edge | Y2: Buy Edge | Z2: Resid Z | AA2: Yield | AB2: Time
A3: SPY | B3: =IF(NOT(ISNUMBER(V3)),"",IF((NOW()-N(AB3))*1440>StaleMin,"STALE",IF(AND($AF3="EQUITY",ABS(N(T3))>ExDivFlag),"EX-DIV?",IF(X3>IF($AF3="FI",EdgeFI,EdgeEq),"SELL ETF / BUY "&UPPER($A$4),IF(Y3>IF($AF3="FI",EdgeFI,EdgeEq),"BUY ETF / SELL "&UPPER($A$4),""))))) -> STALE | C3: =IFERROR(IF(INDEX(Feed!$N:$N,$AG3)="","",INDEX(Feed!$N:$N,$AG3)),"") -> 1 | D3: =IFERROR(IF(INDEX(Feed!$B:$B,$AG3)="","",INDEX(Feed!$B:$B,$AG3)),"") -> 773.6197 | E3: =IFERROR(IF(INDEX(Feed!$C:$C,$AG3)="","",INDEX(Feed!$C:$C,$AG3)),"") -> 773.61 | F3: =IFERROR(IF(INDEX(Feed!$D:$D,$AG3)="","",INDEX(Feed!$D:$D,$AG3)),"") -> 773.66 | G3: =IFERROR(IF(INDEX(Feed!$E:$E,$AG3)="","",INDEX(Feed!$E:$E,$AG3)),"") -> 246 | H3: =IFERROR(IF(INDEX(Feed!$F:$F,$AG3)="","",INDEX(Feed!$F:$F,$AG3)),"") -> 1620 | I3: =IF(AND(N(E3)>0,N(F3)>0),(F3-E3)/((F3+E3)/2)*10000,"") -> 0.64629961 | J3: =IF(N(D3)>0,IFERROR(D3/INDEX(Feed!$G:$G,$AG3)-1,""),"") -> 0.015662146 | K3: =IFERROR(IF(INDEX(Feed!$H:$H,$AG3)="","",INDEX(Feed!$H:$H,$AG3)),"") -> 50486686 | L3: =IFERROR(IF(INDEX(Feed!$I:$I,$AG3)="","",INDEX(Feed!$I:$I,$AG3)),"") | M3: =IF(AND(N(K3)>0,N(L3)>0),K3/L3,"") | N3: =IFERROR(IF(INDEX(Feed!$L:$L,$AG3)="","",INDEX(Feed!$L:$L,$AG3)),"") -> 0.0073762093 | O3: =IF(AND(ISNUMBER(J3),N(N3)>0),J3/N3,"") -> 2.1233326 | P3: =IF(ISNUMBER(O3),IF(SessionLeft<=0,--(ABS(O3)>1),_xlfn.NORM.S.DIST((-1-O3)/SQRT(SessionLeft),TRUE)+1-_xlfn.NORM.S.DIST((1-O3)/SQRT(SessionLeft),TRUE)),"") -> 1 | Q3: =IF(ISNUMBER(O3),IF(SessionLeft<=0,--(ABS(O3)>2),_xlfn.NORM.S.DIST((-2-O3)/SQRT(SessionLeft),TRUE)+1-_xlfn.NORM.S.DIST((2-O3)/SQRT(SessionLeft),TRUE)),"") -> 1 | R3: =IF(ISNUMBER(O3),IF(SessionLeft<=0,--(ABS(O3)>3),_xlfn.NORM.S.DIST((-3-O3)/SQRT(SessionLeft),TRUE)+1-_xlfn.NORM.S.DIST((3-O3)/SQRT(SessionLeft),TRUE)),"") -> 0 | S3: =IFERROR(IF(INDEX(Feed!$J:$J,$AG3)="","",INDEX(Feed!$J:$J,$AG3)),"") -> 762.0114 | T3: =IFERROR(IF(N(S3)>0,(INDEX(Feed!$G:$G,$AG3)/S3-1)*10000,""),"") -> -4.2177847 | U3: =IFERROR(C3*$J$4,"") -> 0.015108122 | V3: =IF(ISNUMBER(U3),IF(AND(Anchor="NAV",N(S3)>0),S3,INDEX(Feed!$G:$G,$AG3))*(1+U3),"") -> 773.19771 | W3: =IF(ISNUMBER(V3),(IF(AND(N(E3)>0,N(F3)>0),(E3+F3)/2,D3)/V3-1)*10000,"") -> 5.655662 | X3: =IF(ISNUMBER(V3),(IF(N(E3)>0,E3,D3)/V3-1)*10000-IF($AF3="FI",CostFI,CostEq),"") -> 2.3323295 | Y3: =IF(ISNUMBER(V3),(1-IF(N(F3)>0,F3,D3)/V3)*10000-IF($AF3="FI",CostFI,CostEq),"") -> -8.9789946 | Z3: =IFERROR((J3-U3-INDEX(Feed!$O:$O,$AG3))/INDEX(Feed!$P:$P,$AG3),"") -> 0.53567994 | AA3: =IFERROR(IF(INDEX(Feed!$K:$K,$AG3)="","",INDEX(Feed!$K:$K,$AG3)),"") -> 0.0098 | AB3: =IFERROR(IF(INDEX(Feed!$M:$M,$AG3)="","",INDEX(Feed!$M:$M,$AG3)),"") -> 46287.672 | AD3: SPY | AE3: ETF | AF3: EQUITY | AG3: =IFERROR(MATCH($AD3,Feed!$A:$A,0),"") -> 2
A4: Basket | C4: =IFERROR(SUMIFS(Holdings!$G:$G,Holdings!$A:$A,$A$3)/SUMIFS(Holdings!$D:$D,Holdings!$A:$A,$A$3),"") -> 0.8010182 | J4: =IFERROR(SUMIFS(Holdings!$F:$F,Holdings!$A:$A,$A$3)/SUMIFS(Holdings!$G:$G,Holdings!$A:$A,$A$3),"") -> 0.015108122 | N4: =IFERROR(IF(INDEX(Feed!$L:$L,$AG4)="","",INDEX(Feed!$L:$L,$AG4)),"") -> 0.0072114745 | O4: =IF(AND(ISNUMBER(J4),N(N4)>0),J4/N4,"") -> 2.0950115 | P4: =IF(ISNUMBER(O4),IF(SessionLeft<=0,--(ABS(O4)>1),_xlfn.NORM.S.DIST((-1-O4)/SQRT(SessionLeft),TRUE)+1-_xlfn.NORM.S.DIST((1-O4)/SQRT(SessionLeft),TRUE)),"") -> 1 | Q4: =IF(ISNUMBER(O4),IF(SessionLeft<=0,--(ABS(O4)>2),_xlfn.NORM.S.DIST((-2-O4)/SQRT(SessionLeft),TRUE)+1-_xlfn.NORM.S.DIST((2-O4)/SQRT(SessionLeft),TRUE)),"") -> 1 | R4: =IF(ISNUMBER(O4),IF(SessionLeft<=0,--(ABS(O4)>3),_xlfn.NORM.S.DIST((-3-O4)/SQRT(SessionLeft),TRUE)+1-_xlfn.NORM.S.DIST((3-O4)/SQRT(SessionLeft),TRUE)),"") -> 0 | AD4: SPY BASKET | AE4: Basket | AF4: EQUITY | AG4: =IFERROR(MATCH($AD4,Feed!$A:$A,0),"") -> 559
A5: NVDA | C5: =SUMIFS(Holdings!$D:$D,Holdings!$A:$A,$A$3,Holdings!$B:$B,A5) -> 0.08276795 | D5: =IFERROR(IF(INDEX(Feed!$B:$B,$AG5)="","",INDEX(Feed!$B:$B,$AG5)),"") -> 228.3882 | E5: =IFERROR(IF(INDEX(Feed!$C:$C,$AG5)="","",INDEX(Feed!$C:$C,$AG5)),"") | F5: =IFERROR(IF(INDEX(Feed!$D:$D,$AG5)="","",INDEX(Feed!$D:$D,$AG5)),"") | G5: =IFERROR(IF(INDEX(Feed!$E:$E,$AG5)="","",INDEX(Feed!$E:$E,$AG5)),"") | H5: =IFERROR(IF(INDEX(Feed!$F:$F,$AG5)="","",INDEX(Feed!$F:$F,$AG5)),"") | I5: =IF(AND(N(E5)>0,N(F5)>0),(F5-E5)/((F5+E5)/2)*10000,"") | J5: =IF(N(D5)>0,IFERROR(D5/INDEX(Feed!$G:$G,$AG5)-1,""),"") -> 0.027525982 | K5: =IFERROR(IF(INDEX(Feed!$H:$H,$AG5)="","",INDEX(Feed!$H:$H,$AG5)),"") -> 109980196 | L5: =IFERROR(IF(INDEX(Feed!$I:$I,$AG5)="","",INDEX(Feed!$I:$I,$AG5)),"") | M5: =IF(AND(N(K5)>0,N(L5)>0),K5/L5,"") | N5: =IFERROR(IF(INDEX(Feed!$L:$L,$AG5)="","",INDEX(Feed!$L:$L,$AG5)),"") -> 0.025073562 | O5: =IF(AND(ISNUMBER(J5),N(N5)>0),J5/N5,"") -> 1.097809 | P5: =IF(ISNUMBER(O5),IF(SessionLeft<=0,--(ABS(O5)>1),_xlfn.NORM.S.DIST((-1-O5)/SQRT(SessionLeft),TRUE)+1-_xlfn.NORM.S.DIST((1-O5)/SQRT(SessionLeft),TRUE)),"") -> 1 | Q5: =IF(ISNUMBER(O5),IF(SessionLeft<=0,--(ABS(O5)>2),_xlfn.NORM.S.DIST((-2-O5)/SQRT(SessionLeft),TRUE)+1-_xlfn.NORM.S.DIST((2-O5)/SQRT(SessionLeft),TRUE)),"") -> 0 | R5: =IF(ISNUMBER(O5),IF(SessionLeft<=0,--(ABS(O5)>3),_xlfn.NORM.S.DIST((-3-O5)/SQRT(SessionLeft),TRUE)+1-_xlfn.NORM.S.DIST((3-O5)/SQRT(SessionLeft),TRUE)),"") -> 0 | AB5: =IFERROR(IF(INDEX(Feed!$M:$M,$AG5)="","",INDEX(Feed!$M:$M,$AG5)),"") -> 46287.671 | AD5: NVDA | AE5: Holding | AF5: EQUITY | AG5: =IFERROR(MATCH($AD5,Feed!$A:$A,0),"") -> 373
A6: AAPL | C6: =SUMIFS(Holdings!$D:$D,Holdings!$A:$A,$A$3,Holdings!$B:$B,A6) -> 0.07409622 | D6: =IFERROR(IF(INDEX(Feed!$B:$B,$AG6)="","",INDEX(Feed!$B:$B,$AG6)),"") | E6: =IFERROR(IF(INDEX(Feed!$C:$C,$AG6)="","",INDEX(Feed!$C:$C,$AG6)),"") | F6: =IFERROR(IF(INDEX(Feed!$D:$D,$AG6)="","",INDEX(Feed!$D:$D,$AG6)),"") | G6: =IFERROR(IF(INDEX(Feed!$E:$E,$AG6)="","",INDEX(Feed!$E:$E,$AG6)),"") | H6: =IFERROR(IF(INDEX(Feed!$F:$F,$AG6)="","",INDEX(Feed!$F:$F,$AG6)),"") | I6: =IF(AND(N(E6)>0,N(F6)>0),(F6-E6)/((F6+E6)/2)*10000,"") | J6: =IF(N(D6)>0,IFERROR(D6/INDEX(Feed!$G:$G,$AG6)-1,""),"") | K6: =IFERROR(IF(INDEX(Feed!$H:$H,$AG6)="","",INDEX(Feed!$H:$H,$AG6)),"") | L6: =IFERROR(IF(INDEX(Feed!$I:$I,$AG6)="","",INDEX(Feed!$I:$I,$AG6)),"") | M6: =IF(AND(N(K6)>0,N(L6)>0),K6/L6,"") | N6: =IFERROR(IF(INDEX(Feed!$L:$L,$AG6)="","",INDEX(Feed!$L:$L,$AG6)),"") -> 0.018439339 | O6: =IF(AND(ISNUMBER(J6),N(N6)>0),J6/N6,"") | P6: =IF(ISNUMBER(O6),IF(SessionLeft<=0,--(ABS(O6)>1),_xlfn.NORM.S.DIST((-1-O6)/SQRT(SessionLeft),TRUE)+1-_xlfn.NORM.S.DIST((1-O6)/SQRT(SessionLeft),TRUE)),"") | Q6: =IF(ISNUMBER(O6),IF(SessionLeft<=0,--(ABS(O6)>2),_xlfn.NORM.S.DIST((-2-O6)/SQRT(SessionLeft),TRUE)+1-_xlfn.NORM.S.DIST((2-O6)/SQRT(SessionLeft),TRUE)),"") | R6: =IF(ISNUMBER(O6),IF(SessionLeft<=0,--(ABS(O6)>3),_xlfn.NORM.S.DIST((-3-O6)/SQRT(SessionLeft),TRUE)+1-_xlfn.NORM.S.DIST((3-O6)/SQRT(SessionLeft),TRUE)),"") | AB6: =IFERROR(IF(INDEX(Feed!$M:$M,$AG6)="","",INDEX(Feed!$M:$M,$AG6)),"") | AD6: AAPL | AE6: Holding | AF6: EQUITY | AG6: =IFERROR(MATCH($AD6,Feed!$A:$A,0),"") -> 20
A7: MSFT | C7: =SUMIFS(Holdings!$D:$D,Holdings!$A:$A,$A$3,Holdings!$B:$B,A7) -> 0.05525998 | D7: =IFERROR(IF(INDEX(Feed!$B:$B,$AG7)="","",INDEX(Feed!$B:$B,$AG7)),"") -> 497.8325 | E7: =IFERROR(IF(INDEX(Feed!$C:$C,$AG7)="","",INDEX(Feed!$C:$C,$AG7)),"") | F7: =IFERROR(IF(INDEX(Feed!$D:$D,$AG7)="","",INDEX(Feed!$D:$D,$AG7)),"") | G7: =IFERROR(IF(INDEX(Feed!$E:$E,$AG7)="","",INDEX(Feed!$E:$E,$AG7)),"") | H7: =IFERROR(IF(INDEX(Feed!$F:$F,$AG7)="","",INDEX(Feed!$F:$F,$AG7)),"") | I7: =IF(AND(N(E7)>0,N(F7)>0),(F7-E7)/((F7+E7)/2)*10000,"") | J7: =IF(N(D7)>0,IFERROR(D7/INDEX(Feed!$G:$G,$AG7)-1,""),"") -> -0.007530751 | K7: =IFERROR(IF(INDEX(Feed!$H:$H,$AG7)="","",INDEX(Feed!$H:$H,$AG7)),"") -> 16019410 | L7: =IFERROR(IF(INDEX(Feed!$I:$I,$AG7)="","",INDEX(Feed!$I:$I,$AG7)),"") | M7: =IF(AND(N(K7)>0,N(L7)>0),K7/L7,"") | N7: =IFERROR(IF(INDEX(Feed!$L:$L,$AG7)="","",INDEX(Feed!$L:$L,$AG7)),"") -> 0.026179693 | O7: =IF(AND(ISNUMBER(J7),N(N7)>0),J7/N7,"") -> -0.2876562 | P7: =IF(ISNUMBER(O7),IF(SessionLeft<=0,--(ABS(O7)>1),_xlfn.NORM.S.DIST((-1-O7)/SQRT(SessionLeft),TRUE)+1-_xlfn.NORM.S.DIST((1-O7)/SQRT(SessionLeft),TRUE)),"") -> 0 | Q7: =IF(ISNUMBER(O7),IF(SessionLeft<=0,--(ABS(O7)>2),_xlfn.NORM.S.DIST((-2-O7)/SQRT(SessionLeft),TRUE)+1-_xlfn.NORM.S.DIST((2-O7)/SQRT(SessionLeft),TRUE)),"") -> 0 | R7: =IF(ISNUMBER(O7),IF(SessionLeft<=0,--(ABS(O7)>3),_xlfn.NORM.S.DIST((-3-O7)/SQRT(SessionLeft),TRUE)+1-_xlfn.NORM.S.DIST((3-O7)/SQRT(SessionLeft),TRUE)),"") -> 0 | AB7: =IFERROR(IF(INDEX(Feed!$M:$M,$AG7)="","",INDEX(Feed!$M:$M,$AG7)),"") -> 46287.671 | AD7: MSFT | AE7: Holding | AF7: EQUITY | AG7: =IFERROR(MATCH($AD7,Feed!$A:$A,0),"") -> 351
A8: QQQ | B8: =IF(NOT(ISNUMBER(V8)),"",IF((NOW()-N(AB8))*1440>StaleMin,"STALE",IF(AND($AF8="EQUITY",ABS(N(T8))>ExDivFlag),"EX-DIV?",IF(X8>IF($AF8="FI",EdgeFI,EdgeEq),"SELL ETF / BUY "&UPPER($A$9),IF(Y8>IF($AF8="FI",EdgeFI,EdgeEq),"BUY ETF / SELL "&UPPER($A$9),""))))) -> STALE | C8: =IFERROR(IF(INDEX(Feed!$N:$N,$AG8)="","",INDEX(Feed!$N:$N,$AG8)),"") -> 1 | D8: =IFERROR(IF(INDEX(Feed!$B:$B,$AG8)="","",INDEX(Feed!$B:$B,$AG8)),"") -> 747.45 | E8: =IFERROR(IF(INDEX(Feed!$C:$C,$AG8)="","",INDEX(Feed!$C:$C,$AG8)),"") -> 747.45 | F8: =IFERROR(IF(INDEX(Feed!$D:$D,$AG8)="","",INDEX(Feed!$D:$D,$AG8)),"") -> 747.48 | G8: =IFERROR(IF(INDEX(Feed!$E:$E,$AG8)="","",INDEX(Feed!$E:$E,$AG8)),"") -> 180 | H8: =IFERROR(IF(INDEX(Feed!$F:$F,$AG8)="","",INDEX(Feed!$F:$F,$AG8)),"") -> 100 | I8: =IF(AND(N(E8)>0,N(F8)>0),(F8-E8)/((F8+E8)/2)*10000,"") -> 0.40135659 | J8: =IF(N(D8)>0,IFERROR(D8/INDEX(Feed!$G:$G,$AG8)-1,""),"") -> 0.037118707 | K8: =IFERROR(IF(INDEX(Feed!$H:$H,$AG8)="","",INDEX(Feed!$H:$H,$AG8)),"") -> 46731300 | L8: =IFERROR(IF(INDEX(Feed!$I:$I,$AG8)="","",INDEX(Feed!$I:$I,$AG8)),"") | M8: =IF(AND(N(K8)>0,N(L8)>0),K8/L8,"") | N8: =IFERROR(IF(INDEX(Feed!$L:$L,$AG8)="","",INDEX(Feed!$L:$L,$AG8)),"") -> 0.01324884 | O8: =IF(AND(ISNUMBER(J8),N(N8)>0),J8/N8,"") -> 2.8016571 | P8: =IF(ISNUMBER(O8),IF(SessionLeft<=0,--(ABS(O8)>1),_xlfn.NORM.S.DIST((-1-O8)/SQRT(SessionLeft),TRUE)+1-_xlfn.NORM.S.DIST((1-O8)/SQRT(SessionLeft),TRUE)),"") -> 1 | Q8: =IF(ISNUMBER(O8),IF(SessionLeft<=0,--(ABS(O8)>2),_xlfn.NORM.S.DIST((-2-O8)/SQRT(SessionLeft),TRUE)+1-_xlfn.NORM.S.DIST((2-O8)/SQRT(SessionLeft),TRUE)),"") -> 1 | R8: =IF(ISNUMBER(O8),IF(SessionLeft<=0,--(ABS(O8)>3),_xlfn.NORM.S.DIST((-3-O8)/SQRT(SessionLeft),TRUE)+1-_xlfn.NORM.S.DIST((3-O8)/SQRT(SessionLeft),TRUE)),"") -> 0 | S8: =IFERROR(IF(INDEX(Feed!$J:$J,$AG8)="","",INDEX(Feed!$J:$J,$AG8)),"") -> 721.72 | T8: =IFERROR(IF(N(S8)>0,(INDEX(Feed!$G:$G,$AG8)/S8-1)*10000,""),"") -> -14.152303 | U8: =IFERROR(C8*$J$9,"") -> 0.035298946 | V8: =IF(ISNUMBER(U8),IF(AND(Anchor="NAV",N(S8)>0),S8,INDEX(Feed!$G:$G,$AG8))*(1+U8),"") -> 746.1385 | W8: =IF(ISNUMBER(V8),(IF(AND(N(E8)>0,N(F8)>0),(E8+F8)/2,D8)/V8-1)*10000,"") -> 17.778188 | X8: =IF(ISNUMBER(V8),(IF(N(E8)>0,E8,D8)/V8-1)*10000-IF($AF8="FI",CostFI,CostEq),"") -> 14.577153 | Y8: =IF(ISNUMBER(V8),(1-IF(N(F8)>0,F8,D8)/V8)*10000-IF($AF8="FI",CostFI,CostEq),"") -> -20.979223 | Z8: =IFERROR((J8-U8-INDEX(Feed!$O:$O,$AG8))/INDEX(Feed!$P:$P,$AG8),"") -> 2.0779963 | AA8: =IFERROR(IF(INDEX(Feed!$K:$K,$AG8)="","",INDEX(Feed!$K:$K,$AG8)),"") -> 0.0042 | AB8: =IFERROR(IF(INDEX(Feed!$M:$M,$AG8)="","",INDEX(Feed!$M:$M,$AG8)),"") -> 46287.672 | AD8: QQQ | AE8: ETF | AF8: EQUITY | AG8: =IFERROR(MATCH($AD8,Feed!$A:$A,0),"") -> 3
A9: Basket | C9: =IFERROR(SUMIFS(Holdings!$G:$G,Holdings!$A:$A,$A$8)/SUMIFS(Holdings!$D:$D,Holdings!$A:$A,$A$8),"") -> 0.80563984 | J9: =IFERROR(SUMIFS(Holdings!$F:$F,Holdings!$A:$A,$A$8)/SUMIFS(Holdings!$G:$G,Holdings!$A:$A,$A$8),"") -> 0.035298946 | N9: =IFERROR(IF(INDEX(Feed!$L:$L,$AG9)="","",INDEX(Feed!$L:$L,$AG9)),"") -> 0.01338235 | O9: =IF(AND(ISNUMBER(J9),N(N9)>0),J9/N9,"") -> 2.6377241 | P9: =IF(ISNUMBER(O9),IF(SessionLeft<=0,--(ABS(O9)>1),_xlfn.NORM.S.DIST((-1-O9)/SQRT(SessionLeft),TRUE)+1-_xlfn.NORM.S.DIST((1-O9)/SQRT(SessionLeft),TRUE)),"") -> 1 | Q9: =IF(ISNUMBER(O9),IF(SessionLeft<=0,--(ABS(O9)>2),_xlfn.NORM.S.DIST((-2-O9)/SQRT(SessionLeft),TRUE)+1-_xlfn.NORM.S.DIST((2-O9)/SQRT(SessionLeft),TRUE)),"") -> 1 | R9: =IF(ISNUMBER(O9),IF(SessionLeft<=0,--(ABS(O9)>3),_xlfn.NORM.S.DIST((-3-O9)/SQRT(SessionLeft),TRUE)+1-_xlfn.NORM.S.DIST((3-O9)/SQRT(SessionLeft),TRUE)),"") -> 0 | AD9: QQQ BASKET | AE9: Basket | AF9: EQUITY | AG9: =IFERROR(MATCH($AD9,Feed!$A:$A,0),"") -> 560
A10: NVDA | C10: =SUMIFS(Holdings!$D:$D,Holdings!$A:$A,$A$8,Holdings!$B:$B,A10) -> 0.08277194 | D10: =IFERROR(IF(INDEX(Feed!$B:$B,$AG10)="","",INDEX(Feed!$B:$B,$AG10)),"") -> 228.3882 | E10: =IFERROR(IF(INDEX(Feed!$C:$C,$AG10)="","",INDEX(Feed!$C:$C,$AG10)),"") | F10: =IFERROR(IF(INDEX(Feed!$D:$D,$AG10)="","",INDEX(Feed!$D:$D,$AG10)),"") | G10: =IFERROR(IF(INDEX(Feed!$E:$E,$AG10)="","",INDEX(Feed!$E:$E,$AG10)),"") | H10: =IFERROR(IF(INDEX(Feed!$F:$F,$AG10)="","",INDEX(Feed!$F:$F,$AG10)),"") | I10: =IF(AND(N(E10)>0,N(F10)>0),(F10-E10)/((F10+E10)/2)*10000,"") | J10: =IF(N(D10)>0,IFERROR(D10/INDEX(Feed!$G:$G,$AG10)-1,""),"") -> 0.027525982 | K10: =IFERROR(IF(INDEX(Feed!$H:$H,$AG10)="","",INDEX(Feed!$H:$H,$AG10)),"") -> 109980196 | L10: =IFERROR(IF(INDEX(Feed!$I:$I,$AG10)="","",INDEX(Feed!$I:$I,$AG10)),"") | M10: =IF(AND(N(K10)>0,N(L10)>0),K10/L10,"") | N10: =IFERROR(IF(INDEX(Feed!$L:$L,$AG10)="","",INDEX(Feed!$L:$L,$AG10)),"") -> 0.025073562 | O10: =IF(AND(ISNUMBER(J10),N(N10)>0),J10/N10,"") -> 1.097809 | P10: =IF(ISNUMBER(O10),IF(SessionLeft<=0,--(ABS(O10)>1),_xlfn.NORM.S.DIST((-1-O10)/SQRT(SessionLeft),TRUE)+1-_xlfn.NORM.S.DIST((1-O10)/SQRT(SessionLeft),TRUE)),"") -> 1 | Q10: =IF(ISNUMBER(O10),IF(SessionLeft<=0,--(ABS(O10)>2),_xlfn.NORM.S.DIST((-2-O10)/SQRT(SessionLeft),TRUE)+1-_xlfn.NORM.S.DIST((2-O10)/SQRT(SessionLeft),TRUE)),"") -> 0 | R10: =IF(ISNUMBER(O10),IF(SessionLeft<=0,--(ABS(O10)>3),_xlfn.NORM.S.DIST((-3-O10)/SQRT(SessionLeft),TRUE)+1-_xlfn.NORM.S.DIST((3-O10)/SQRT(SessionLeft),TRUE)),"") -> 0 | AB10: =IFERROR(IF(INDEX(Feed!$M:$M,$AG10)="","",INDEX(Feed!$M:$M,$AG10)),"") -> 46287.671 | AD10: NVDA | AE10: Holding | AF10: EQUITY | AG10: =IFERROR(MATCH($AD10,Feed!$A:$A,0),"") -> 373
A11: AAPL | C11: =SUMIFS(Holdings!$D:$D,Holdings!$A:$A,$A$8,Holdings!$B:$B,A11) -> 0.07432348 | D11: =IFERROR(IF(INDEX(Feed!$B:$B,$AG11)="","",INDEX(Feed!$B:$B,$AG11)),"") | E11: =IFERROR(IF(INDEX(Feed!$C:$C,$AG11)="","",INDEX(Feed!$C:$C,$AG11)),"") | F11: =IFERROR(IF(INDEX(Feed!$D:$D,$AG11)="","",INDEX(Feed!$D:$D,$AG11)),"") | G11: =IFERROR(IF(INDEX(Feed!$E:$E,$AG11)="","",INDEX(Feed!$E:$E,$AG11)),"") | H11: =IFERROR(IF(INDEX(Feed!$F:$F,$AG11)="","",INDEX(Feed!$F:$F,$AG11)),"") | I11: =IF(AND(N(E11)>0,N(F11)>0),(F11-E11)/((F11+E11)/2)*10000,"") | J11: =IF(N(D11)>0,IFERROR(D11/INDEX(Feed!$G:$G,$AG11)-1,""),"") | K11: =IFERROR(IF(INDEX(Feed!$H:$H,$AG11)="","",INDEX(Feed!$H:$H,$AG11)),"") | L11: =IFERROR(IF(INDEX(Feed!$I:$I,$AG11)="","",INDEX(Feed!$I:$I,$AG11)),"") | M11: =IF(AND(N(K11)>0,N(L11)>0),K11/L11,"") | N11: =IFERROR(IF(INDEX(Feed!$L:$L,$AG11)="","",INDEX(Feed!$L:$L,$AG11)),"") -> 0.018439339 | O11: =IF(AND(ISNUMBER(J11),N(N11)>0),J11/N11,"") | P11: =IF(ISNUMBER(O11),IF(SessionLeft<=0,--(ABS(O11)>1),_xlfn.NORM.S.DIST((-1-O11)/SQRT(SessionLeft),TRUE)+1-_xlfn.NORM.S.DIST((1-O11)/SQRT(SessionLeft),TRUE)),"") | Q11: =IF(ISNUMBER(O11),IF(SessionLeft<=0,--(ABS(O11)>2),_xlfn.NORM.S.DIST((-2-O11)/SQRT(SessionLeft),TRUE)+1-_xlfn.NORM.S.DIST((2-O11)/SQRT(SessionLeft),TRUE)),"") | R11: =IF(ISNUMBER(O11),IF(SessionLeft<=0,--(ABS(O11)>3),_xlfn.NORM.S.DIST((-3-O11)/SQRT(SessionLeft),TRUE)+1-_xlfn.NORM.S.DIST((3-O11)/SQRT(SessionLeft),TRUE)),"") | AB11: =IFERROR(IF(INDEX(Feed!$M:$M,$AG11)="","",INDEX(Feed!$M:$M,$AG11)),"") | AD11: AAPL | AE11: Holding | AF11: EQUITY | AG11: =IFERROR(MATCH($AD11,Feed!$A:$A,0),"") -> 20
A12: MSFT | C12: =SUMIFS(Holdings!$D:$D,Holdings!$A:$A,$A$8,Holdings!$B:$B,A12) -> 0.05542997 | D12: =IFERROR(IF(INDEX(Feed!$B:$B,$AG12)="","",INDEX(Feed!$B:$B,$AG12)),"") -> 497.8325 | E12: =IFERROR(IF(INDEX(Feed!$C:$C,$AG12)="","",INDEX(Feed!$C:$C,$AG12)),"") | F12: =IFERROR(IF(INDEX(Feed!$D:$D,$AG12)="","",INDEX(Feed!$D:$D,$AG12)),"") | G12: =IFERROR(IF(INDEX(Feed!$E:$E,$AG12)="","",INDEX(Feed!$E:$E,$AG12)),"") | H12: =IFERROR(IF(INDEX(Feed!$F:$F,$AG12)="","",INDEX(Feed!$F:$F,$AG12)),"") | I12: =IF(AND(N(E12)>0,N(F12)>0),(F12-E12)/((F12+E12)/2)*10000,"") | J12: =IF(N(D12)>0,IFERROR(D12/INDEX(Feed!$G:$G,$AG12)-1,""),"") -> -0.007530751 | K12: =IFERROR(IF(INDEX(Feed!$H:$H,$AG12)="","",INDEX(Feed!$H:$H,$AG12)),"") -> 16019410 | L12: =IFERROR(IF(INDEX(Feed!$I:$I,$AG12)="","",INDEX(Feed!$I:$I,$AG12)),"") | M12: =IF(AND(N(K12)>0,N(L12)>0),K12/L12,"") | N12: =IFERROR(IF(INDEX(Feed!$L:$L,$AG12)="","",INDEX(Feed!$L:$L,$AG12)),"") -> 0.026179693 | O12: =IF(AND(ISNUMBER(J12),N(N12)>0),J12/N12,"") -> -0.2876562 | P12: =IF(ISNUMBER(O12),IF(SessionLeft<=0,--(ABS(O12)>1),_xlfn.NORM.S.DIST((-1-O12)/SQRT(SessionLeft),TRUE)+1-_xlfn.NORM.S.DIST((1-O12)/SQRT(SessionLeft),TRUE)),"") -> 0 | Q12: =IF(ISNUMBER(O12),IF(SessionLeft<=0,--(ABS(O12)>2),_xlfn.NORM.S.DIST((-2-O12)/SQRT(SessionLeft),TRUE)+1-_xlfn.NORM.S.DIST((2-O12)/SQRT(SessionLeft),TRUE)),"") -> 0 | R12: =IF(ISNUMBER(O12),IF(SessionLeft<=0,--(ABS(O12)>3),_xlfn.NORM.S.DIST((-3-O12)/SQRT(SessionLeft),TRUE)+1-_xlfn.NORM.S.DIST((3-O12)/SQRT(SessionLeft),TRUE)),"") -> 0 | AB12: =IFERROR(IF(INDEX(Feed!$M:$M,$AG12)="","",INDEX(Feed!$M:$M,$AG12)),"") -> 46287.671 | AD12: MSFT | AE12: Holding | AF12: EQUITY | AG12: =IFERROR(MATCH($AD12,Feed!$A:$A,0),"") -> 351
A13: XLK | B13: =IF(NOT(ISNUMBER(V13)),"",IF((NOW()-N(AB13))*1440>StaleMin,"STALE",IF(AND($AF13="EQUITY",ABS(N(T13))>ExDivFlag),"EX-DIV?",IF(X13>IF($AF13="FI",EdgeFI,EdgeEq),"SELL ETF / BUY "&UPPER($A$14),IF(Y13>IF($AF13="FI",EdgeFI,EdgeEq),"BUY ETF / SELL "&UPPER($A$14),""))))) -> STALE | C13: =IFERROR(IF(INDEX(Feed!$N:$N,$AG13)="","",INDEX(Feed!$N:$N,$AG13)),"") -> 1 | D13: =IFERROR(IF(INDEX(Feed!$B:$B,$AG13)="","",INDEX(Feed!$B:$B,$AG13)),"") -> 196.229 | E13: =IFERROR(IF(INDEX(Feed!$C:$C,$AG13)="","",INDEX(Feed!$C:$C,$AG13)),"") -> 195.6 | F13: =IFERROR(IF(INDEX(Feed!$D:$D,$AG13)="","",INDEX(Feed!$D:$D,$AG13)),"") -> 196.24 | G13: =IFERROR(IF(INDEX(Feed!$E:$E,$AG13)="","",INDEX(Feed!$E:$E,$AG13)),"") -> 400 | H13: =IFERROR(IF(INDEX(Feed!$F:$F,$AG13)="","",INDEX(Feed!$F:$F,$AG13)),"") -> 100 | I13: =IF(AND(N(E13)>0,N(F13)>0),(F13-E13)/((F13+E13)/2)*10000,"") -> 32.666394 | J13: =IF(N(D13)>0,IFERROR(D13/INDEX(Feed!$G:$G,$AG13)-1,""),"") -> 0.03496308 | K13: =IFERROR(IF(INDEX(Feed!$H:$H,$AG13)="","",INDEX(Feed!$H:$H,$AG13)),"") -> 9047360 | L13: =IFERROR(IF(INDEX(Feed!$I:$I,$AG13)="","",INDEX(Feed!$I:$I,$AG13)),"") | M13: =IF(AND(N(K13)>0,N(L13)>0),K13/L13,"") | N13: =IFERROR(IF(INDEX(Feed!$L:$L,$AG13)="","",INDEX(Feed!$L:$L,$AG13)),"") -> 0.018249068 | O13: =IF(AND(ISNUMBER(J13),N(N13)>0),J13/N13,"") -> 1.9158831 | P13: =IF(ISNUMBER(O13),IF(SessionLeft<=0,--(ABS(O13)>1),_xlfn.NORM.S.DIST((-1-O13)/SQRT(SessionLeft),TRUE)+1-_xlfn.NORM.S.DIST((1-O13)/SQRT(SessionLeft),TRUE)),"") -> 1 | Q13: =IF(ISNUMBER(O13),IF(SessionLeft<=0,--(ABS(O13)>2),_xlfn.NORM.S.DIST((-2-O13)/SQRT(SessionLeft),TRUE)+1-_xlfn.NORM.S.DIST((2-O13)/SQRT(SessionLeft),TRUE)),"") -> 0 | R13: =IF(ISNUMBER(O13),IF(SessionLeft<=0,--(ABS(O13)>3),_xlfn.NORM.S.DIST((-3-O13)/SQRT(SessionLeft),TRUE)+1-_xlfn.NORM.S.DIST((3-O13)/SQRT(SessionLeft),TRUE)),"") -> 0 | S13: =IFERROR(IF(INDEX(Feed!$J:$J,$AG13)="","",INDEX(Feed!$J:$J,$AG13)),"") -> 189.69778 | T13: =IFERROR(IF(N(S13)>0,(INDEX(Feed!$G:$G,$AG13)/S13-1)*10000,""),"") -> -5.1545147 | U13: =IFERROR(C13*$J$14,"") -> 0.031931105 | V13: =IF(ISNUMBER(U13),IF(AND(Anchor="NAV",N(S13)>0),S13,INDEX(Feed!$G:$G,$AG13))*(1+U13),"") -> 195.65414 | W13: =IF(ISNUMBER(V13),(IF(AND(N(E13)>0,N(F13)>0),(E13+F13)/2,D13)/V13-1)*10000,"") -> 13.588395 | X13: =IF(ISNUMBER(V13),(IF(N(E13)>0,E13,D13)/V13-1)*10000-IF($AF13="FI",CostFI,CostEq),"") -> -5.7669969 | Y13: =IF(ISNUMBER(V13),(1-IF(N(F13)>0,F13,D13)/V13)*10000-IF($AF13="FI",CostFI,CostEq),"") -> -32.943786 | Z13: =IFERROR((J13-U13-INDEX(Feed!$O:$O,$AG13))/INDEX(Feed!$P:$P,$AG13),"") -> 3.8391935 | AA13: =IFERROR(IF(INDEX(Feed!$K:$K,$AG13)="","",INDEX(Feed!$K:$K,$AG13)),"") -> 0.0043 | AB13: =IFERROR(IF(INDEX(Feed!$M:$M,$AG13)="","",INDEX(Feed!$M:$M,$AG13)),"") -> 46287.673 | AD13: XLK | AE13: ETF | AF13: EQUITY | AG13: =IFERROR(MATCH($AD13,Feed!$A:$A,0),"") -> 4
A14: Basket | C14: =IFERROR(SUMIFS(Holdings!$G:$G,Holdings!$A:$A,$A$13)/SUMIFS(Holdings!$D:$D,Holdings!$A:$A,$A$13),"") -> 0.79367953 | J14: =IFERROR(SUMIFS(Holdings!$F:$F,Holdings!$A:$A,$A$13)/SUMIFS(Holdings!$G:$G,Holdings!$A:$A,$A$13),"") -> 0.031931105 | N14: =IFERROR(IF(INDEX(Feed!$L:$L,$AG14)="","",INDEX(Feed!$L:$L,$AG14)),"") -> 0.017895276 | O14: =IF(AND(ISNUMBER(J14),N(N14)>0),J14/N14,"") -> 1.7843315 | P14: =IF(ISNUMBER(O14),IF(SessionLeft<=0,--(ABS(O14)>1),_xlfn.NORM.S.DIST((-1-O14)/SQRT(SessionLeft),TRUE)+1-_xlfn.NORM.S.DIST((1-O14)/SQRT(SessionLeft),TRUE)),"") -> 1 | Q14: =IF(ISNUMBER(O14),IF(SessionLeft<=0,--(ABS(O14)>2),_xlfn.NORM.S.DIST((-2-O14)/SQRT(SessionLeft),TRUE)+1-_xlfn.NORM.S.DIST((2-O14)/SQRT(SessionLeft),TRUE)),"") -> 0 | R14: =IF(ISNUMBER(O14),IF(SessionLeft<=0,--(ABS(O14)>3),_xlfn.NORM.S.DIST((-3-O14)/SQRT(SessionLeft),TRUE)+1-_xlfn.NORM.S.DIST((3-O14)/SQRT(SessionLeft),TRUE)),"") -> 0 | AD14: XLK BASKET | AE14: Basket | AF14: EQUITY | AG14: =IFERROR(MATCH($AD14,Feed!$A:$A,0),"") -> 561
A15: NVDA | C15: =SUMIFS(Holdings!$D:$D,Holdings!$A:$A,$A$13,Holdings!$B:$B,A15) -> 0.15457152 | D15: =IFERROR(IF(INDEX(Feed!$B:$B,$AG15)="","",INDEX(Feed!$B:$B,$AG15)),"") -> 228.3882 | E15: =IFERROR(IF(INDEX(Feed!$C:$C,$AG15)="","",INDEX(Feed!$C:$C,$AG15)),"") | F15: =IFERROR(IF(INDEX(Feed!$D:$D,$AG15)="","",INDEX(Feed!$D:$D,$AG15)),"") | G15: =IFERROR(IF(INDEX(Feed!$E:$E,$AG15)="","",INDEX(Feed!$E:$E,$AG15)),"") | H15: =IFERROR(IF(INDEX(Feed!$F:$F,$AG15)="","",INDEX(Feed!$F:$F,$AG15)),"") | I15: =IF(AND(N(E15)>0,N(F15)>0),(F15-E15)/((F15+E15)/2)*10000,"") | J15: =IF(N(D15)>0,IFERROR(D15/INDEX(Feed!$G:$G,$AG15)-1,""),"") -> 0.027525982 | K15: =IFERROR(IF(INDEX(Feed!$H:$H,$AG15)="","",INDEX(Feed!$H:$H,$AG15)),"") -> 109980196 | L15: =IFERROR(IF(INDEX(Feed!$I:$I,$AG15)="","",INDEX(Feed!$I:$I,$AG15)),"") | M15: =IF(AND(N(K15)>0,N(L15)>0),K15/L15,"") | N15: =IFERROR(IF(INDEX(Feed!$L:$L,$AG15)="","",INDEX(Feed!$L:$L,$AG15)),"") -> 0.025073562 | O15: =IF(AND(ISNUMBER(J15),N(N15)>0),J15/N15,"") -> 1.097809 | P15: =IF(ISNUMBER(O15),IF(SessionLeft<=0,--(ABS(O15)>1),_xlfn.NORM.S.DIST((-1-O15)/SQRT(SessionLeft),TRUE)+1-_xlfn.NORM.S.DIST((1-O15)/SQRT(SessionLeft),TRUE)),"") -> 1 | Q15: =IF(ISNUMBER(O15),IF(SessionLeft<=0,--(ABS(O15)>2),_xlfn.NORM.S.DIST((-2-O15)/SQRT(SessionLeft),TRUE)+1-_xlfn.NORM.S.DIST((2-O15)/SQRT(SessionLeft),TRUE)),"") -> 0 | R15: =IF(ISNUMBER(O15),IF(SessionLeft<=0,--(ABS(O15)>3),_xlfn.NORM.S.DIST((-3-O15)/SQRT(SessionLeft),TRUE)+1-_xlfn.NORM.S.DIST((3-O15)/SQRT(SessionLeft),TRUE)),"") -> 0 | AB15: =IFERROR(IF(INDEX(Feed!$M:$M,$AG15)="","",INDEX(Feed!$M:$M,$AG15)),"") -> 46287.671 | AD15: NVDA | AE15: Holding | AF15: EQUITY | AG15: =IFERROR(MATCH($AD15,Feed!$A:$A,0),"") -> 373
A16: AAPL | C16: =SUMIFS(Holdings!$D:$D,Holdings!$A:$A,$A$13,Holdings!$B:$B,A16) -> 0.13837713 | D16: =IFERROR(IF(INDEX(Feed!$B:$B,$AG16)="","",INDEX(Feed!$B:$B,$AG16)),"") | E16: =IFERROR(IF(INDEX(Feed!$C:$C,$AG16)="","",INDEX(Feed!$C:$C,$AG16)),"") | F16: =IFERROR(IF(INDEX(Feed!$D:$D,$AG16)="","",INDEX(Feed!$D:$D,$AG16)),"") | G16: =IFERROR(IF(INDEX(Feed!$E:$E,$AG16)="","",INDEX(Feed!$E:$E,$AG16)),"") | H16: =IFERROR(IF(INDEX(Feed!$F:$F,$AG16)="","",INDEX(Feed!$F:$F,$AG16)),"") | I16: =IF(AND(N(E16)>0,N(F16)>0),(F16-E16)/((F16+E16)/2)*10000,"") | J16: =IF(N(D16)>0,IFERROR(D16/INDEX(Feed!$G:$G,$AG16)-1,""),"") | K16: =IFERROR(IF(INDEX(Feed!$H:$H,$AG16)="","",INDEX(Feed!$H:$H,$AG16)),"") | L16: =IFERROR(IF(INDEX(Feed!$I:$I,$AG16)="","",INDEX(Feed!$I:$I,$AG16)),"") | M16: =IF(AND(N(K16)>0,N(L16)>0),K16/L16,"") | N16: =IFERROR(IF(INDEX(Feed!$L:$L,$AG16)="","",INDEX(Feed!$L:$L,$AG16)),"") -> 0.018439339 | O16: =IF(AND(ISNUMBER(J16),N(N16)>0),J16/N16,"") | P16: =IF(ISNUMBER(O16),IF(SessionLeft<=0,--(ABS(O16)>1),_xlfn.NORM.S.DIST((-1-O16)/SQRT(SessionLeft),TRUE)+1-_xlfn.NORM.S.DIST((1-O16)/SQRT(SessionLeft),TRUE)),"") | Q16: =IF(ISNUMBER(O16),IF(SessionLeft<=0,--(ABS(O16)>2),_xlfn.NORM.S.DIST((-2-O16)/SQRT(SessionLeft),TRUE)+1-_xlfn.NORM.S.DIST((2-O16)/SQRT(SessionLeft),TRUE)),"") | R16: =IF(ISNUMBER(O16),IF(SessionLeft<=0,--(ABS(O16)>3),_xlfn.NORM.S.DIST((-3-O16)/SQRT(SessionLeft),TRUE)+1-_xlfn.NORM.S.DIST((3-O16)/SQRT(SessionLeft),TRUE)),"") | AB16: =IFERROR(IF(INDEX(Feed!$M:$M,$AG16)="","",INDEX(Feed!$M:$M,$AG16)),"") | AD16: AAPL | AE16: Holding | AF16: EQUITY | AG16: =IFERROR(MATCH($AD16,Feed!$A:$A,0),"") -> 20
A17: MSFT | C17: =SUMIFS(Holdings!$D:$D,Holdings!$A:$A,$A$13,Holdings!$B:$B,A17) -> 0.10320077 | D17: =IFERROR(IF(INDEX(Feed!$B:$B,$AG17)="","",INDEX(Feed!$B:$B,$AG17)),"") -> 497.8325 | E17: =IFERROR(IF(INDEX(Feed!$C:$C,$AG17)="","",INDEX(Feed!$C:$C,$AG17)),"") | F17: =IFERROR(IF(INDEX(Feed!$D:$D,$AG17)="","",INDEX(Feed!$D:$D,$AG17)),"") | G17: =IFERROR(IF(INDEX(Feed!$E:$E,$AG17)="","",INDEX(Feed!$E:$E,$AG17)),"") | H17: =IFERROR(IF(INDEX(Feed!$F:$F,$AG17)="","",INDEX(Feed!$F:$F,$AG17)),"") | I17: =IF(AND(N(E17)>0,N(F17)>0),(F17-E17)/((F17+E17)/2)*10000,"") | J17: =IF(N(D17)>0,IFERROR(D17/INDEX(Feed!$G:$G,$AG17)-1,""),"") -> -0.007530751 | K17: =IFERROR(IF(INDEX(Feed!$H:$H,$AG17)="","",INDEX(Feed!$H:$H,$AG17)),"") -> 16019410 | L17: =IFERROR(IF(INDEX(Feed!$I:$I,$AG17)="","",INDEX(Feed!$I:$I,$AG17)),"") | M17: =IF(AND(N(K17)>0,N(L17)>0),K17/L17,"") | N17: =IFERROR(IF(INDEX(Feed!$L:$L,$AG17)="","",INDEX(Feed!$L:$L,$AG17)),"") -> 0.026179693 | O17: =IF(AND(ISNUMBER(J17),N(N17)>0),J17/N17,"") -> -0.2876562 | P17: =IF(ISNUMBER(O17),IF(SessionLeft<=0,--(ABS(O17)>1),_xlfn.NORM.S.DIST((-1-O17)/SQRT(SessionLeft),TRUE)+1-_xlfn.NORM.S.DIST((1-O17)/SQRT(SessionLeft),TRUE)),"") -> 0 | Q17: =IF(ISNUMBER(O17),IF(SessionLeft<=0,--(ABS(O17)>2),_xlfn.NORM.S.DIST((-2-O17)/SQRT(SessionLeft),TRUE)+1-_xlfn.NORM.S.DIST((2-O17)/SQRT(SessionLeft),TRUE)),"") -> 0 | R17: =IF(ISNUMBER(O17),IF(SessionLeft<=0,--(ABS(O17)>3),_xlfn.NORM.S.DIST((-3-O17)/SQRT(SessionLeft),TRUE)+1-_xlfn.NORM.S.DIST((3-O17)/SQRT(SessionLeft),TRUE)),"") -> 0 | AB17: =IFERROR(IF(INDEX(Feed!$M:$M,$AG17)="","",INDEX(Feed!$M:$M,$AG17)),"") -> 46287.671 | AD17: MSFT | AE17: Holding | AF17: EQUITY | AG17: =IFERROR(MATCH($AD17,Feed!$A:$A,0),"") -> 351
A18: XLF | B18: =IF(NOT(ISNUMBER(V18)),"",IF((NOW()-N(AB18))*1440>StaleMin,"STALE",IF(AND($AF18="EQUITY",ABS(N(T18))>ExDivFlag),"EX-DIV?",IF(X18>IF($AF18="FI",EdgeFI,EdgeEq),"SELL ETF / BUY "&UPPER($A$19),IF(Y18>IF($AF18="FI",EdgeFI,EdgeEq),"BUY ETF / SELL "&UPPER($A$19),""))))) -> STALE | C18: =IFERROR(IF(INDEX(Feed!$N:$N,$AG18)="","",INDEX(Feed!$N:$N,$AG18)),"") -> 1 | D18: =IFERROR(IF(INDEX(Feed!$B:$B,$AG18)="","",INDEX(Feed!$B:$B,$AG18)),"") -> 54.8 | E18: =IFERROR(IF(INDEX(Feed!$C:$C,$AG18)="","",INDEX(Feed!$C:$C,$AG18)),"") | F18: =IFERROR(IF(INDEX(Feed!$D:$D,$AG18)="","",INDEX(Feed!$D:$D,$AG18)),"") | G18: =IFERROR(IF(INDEX(Feed!$E:$E,$AG18)="","",INDEX(Feed!$E:$E,$AG18)),"") | H18: =IFERROR(IF(INDEX(Feed!$F:$F,$AG18)="","",INDEX(Feed!$F:$F,$AG18)),"") | I18: =IF(AND(N(E18)>0,N(F18)>0),(F18-E18)/((F18+E18)/2)*10000,"") | J18: =IF(N(D18)>0,IFERROR(D18/INDEX(Feed!$G:$G,$AG18)-1,""),"") -> -0.018976011 | K18: =IFERROR(IF(INDEX(Feed!$H:$H,$AG18)="","",INDEX(Feed!$H:$H,$AG18)),"") -> 30640768 | L18: =IFERROR(IF(INDEX(Feed!$I:$I,$AG18)="","",INDEX(Feed!$I:$I,$AG18)),"") | M18: =IF(AND(N(K18)>0,N(L18)>0),K18/L18,"") | N18: =IFERROR(IF(INDEX(Feed!$L:$L,$AG18)="","",INDEX(Feed!$L:$L,$AG18)),"") -> 0.00816815 | O18: =IF(AND(ISNUMBER(J18),N(N18)>0),J18/N18,"") -> -2.3231713 | P18: =IF(ISNUMBER(O18),IF(SessionLeft<=0,--(ABS(O18)>1),_xlfn.NORM.S.DIST((-1-O18)/SQRT(SessionLeft),TRUE)+1-_xlfn.NORM.S.DIST((1-O18)/SQRT(SessionLeft),TRUE)),"") -> 1 | Q18: =IF(ISNUMBER(O18),IF(SessionLeft<=0,--(ABS(O18)>2),_xlfn.NORM.S.DIST((-2-O18)/SQRT(SessionLeft),TRUE)+1-_xlfn.NORM.S.DIST((2-O18)/SQRT(SessionLeft),TRUE)),"") -> 1 | R18: =IF(ISNUMBER(O18),IF(SessionLeft<=0,--(ABS(O18)>3),_xlfn.NORM.S.DIST((-3-O18)/SQRT(SessionLeft),TRUE)+1-_xlfn.NORM.S.DIST((3-O18)/SQRT(SessionLeft),TRUE)),"") -> 0 | S18: =IFERROR(IF(INDEX(Feed!$J:$J,$AG18)="","",INDEX(Feed!$J:$J,$AG18)),"") -> 55.90363 | T18: =IFERROR(IF(N(S18)>0,(INDEX(Feed!$G:$G,$AG18)/S18-1)*10000,""),"") -> -7.8045021 | U18: =IFERROR(C18*$J$19,"") -> -0.01540494 | V18: =IF(ISNUMBER(U18),IF(AND(Anchor="NAV",N(S18)>0),S18,INDEX(Feed!$G:$G,$AG18))*(1+U18),"") -> 54.99948 | W18: =IF(ISNUMBER(V18),(IF(AND(N(E18)>0,N(F18)>0),(E18+F18)/2,D18)/V18-1)*10000,"") -> -36.269447 | X18: =IF(ISNUMBER(V18),(IF(N(E18)>0,E18,D18)/V18-1)*10000-IF($AF18="FI",CostFI,CostEq),"") -> -39.269447 | Y18: =IF(ISNUMBER(V18),(1-IF(N(F18)>0,F18,D18)/V18)*10000-IF($AF18="FI",CostFI,CostEq),"") -> 33.269447 | Z18: =IFERROR((J18-U18-INDEX(Feed!$O:$O,$AG18))/INDEX(Feed!$P:$P,$AG18),"") -> -7.0802113 | AA18: =IFERROR(IF(INDEX(Feed!$K:$K,$AG18)="","",INDEX(Feed!$K:$K,$AG18)),"") -> 0.014 | AB18: =IFERROR(IF(INDEX(Feed!$M:$M,$AG18)="","",INDEX(Feed!$M:$M,$AG18)),"") -> 46287.671 | AD18: XLF | AE18: ETF | AF18: EQUITY | AG18: =IFERROR(MATCH($AD18,Feed!$A:$A,0),"") -> 5
A19: Basket | C19: =IFERROR(SUMIFS(Holdings!$G:$G,Holdings!$A:$A,$A$18)/SUMIFS(Holdings!$D:$D,Holdings!$A:$A,$A$18),"") -> 0.82881439 | J19: =IFERROR(SUMIFS(Holdings!$F:$F,Holdings!$A:$A,$A$18)/SUMIFS(Holdings!$G:$G,Holdings!$A:$A,$A$18),"") -> -0.01540494 | N19: =IFERROR(IF(INDEX(Feed!$L:$L,$AG19)="","",INDEX(Feed!$L:$L,$AG19)),"") -> 0.0081074333 | O19: =IF(AND(ISNUMBER(J19),N(N19)>0),J19/N19,"") -> -1.9001007 | P19: =IF(ISNUMBER(O19),IF(SessionLeft<=0,--(ABS(O19)>1),_xlfn.NORM.S.DIST((-1-O19)/SQRT(SessionLeft),TRUE)+1-_xlfn.NORM.S.DIST((1-O19)/SQRT(SessionLeft),TRUE)),"") -> 1 | Q19: =IF(ISNUMBER(O19),IF(SessionLeft<=0,--(ABS(O19)>2),_xlfn.NORM.S.DIST((-2-O19)/SQRT(SessionLeft),TRUE)+1-_xlfn.NORM.S.DIST((2-O19)/SQRT(SessionLeft),TRUE)),"") -> 0 | R19: =IF(ISNUMBER(O19),IF(SessionLeft<=0,--(ABS(O19)>3),_xlfn.NORM.S.DIST((-3-O19)/SQRT(SessionLeft),TRUE)+1-_xlfn.NORM.S.DIST((3-O19)/SQRT(SessionLeft),TRUE)),"") -> 0 | AD19: XLF BASKET | AE19: Basket | AF19: EQUITY | AG19: =IFERROR(MATCH($AD19,Feed!$A:$A,0),"") -> 562
A20: JPM | C20: =SUMIFS(Holdings!$D:$D,Holdings!$A:$A,$A$18,Holdings!$B:$B,A20) -> 0.11694535 | D20: =IFERROR(IF(INDEX(Feed!$B:$B,$AG20)="","",INDEX(Feed!$B:$B,$AG20)),"") -> 340.19 | E20: =IFERROR(IF(INDEX(Feed!$C:$C,$AG20)="","",INDEX(Feed!$C:$C,$AG20)),"") | F20: =IFERROR(IF(INDEX(Feed!$D:$D,$AG20)="","",INDEX(Feed!$D:$D,$AG20)),"") | G20: =IFERROR(IF(INDEX(Feed!$E:$E,$AG20)="","",INDEX(Feed!$E:$E,$AG20)),"") | H20: =IFERROR(IF(INDEX(Feed!$F:$F,$AG20)="","",INDEX(Feed!$F:$F,$AG20)),"") | I20: =IF(AND(N(E20)>0,N(F20)>0),(F20-E20)/((F20+E20)/2)*10000,"") | J20: =IF(N(D20)>0,IFERROR(D20/INDEX(Feed!$G:$G,$AG20)-1,""),"") -> -0.027111276 | K20: =IFERROR(IF(INDEX(Feed!$H:$H,$AG20)="","",INDEX(Feed!$H:$H,$AG20)),"") -> 6414696 | L20: =IFERROR(IF(INDEX(Feed!$I:$I,$AG20)="","",INDEX(Feed!$I:$I,$AG20)),"") | M20: =IF(AND(N(K20)>0,N(L20)>0),K20/L20,"") | N20: =IFERROR(IF(INDEX(Feed!$L:$L,$AG20)="","",INDEX(Feed!$L:$L,$AG20)),"") -> 0.011337588 | O20: =IF(AND(ISNUMBER(J20),N(N20)>0),J20/N20,"") -> -2.3912738 | P20: =IF(ISNUMBER(O20),IF(SessionLeft<=0,--(ABS(O20)>1),_xlfn.NORM.S.DIST((-1-O20)/SQRT(SessionLeft),TRUE)+1-_xlfn.NORM.S.DIST((1-O20)/SQRT(SessionLeft),TRUE)),"") -> 1 | Q20: =IF(ISNUMBER(O20),IF(SessionLeft<=0,--(ABS(O20)>2),_xlfn.NORM.S.DIST((-2-O20)/SQRT(SessionLeft),TRUE)+1-_xlfn.NORM.S.DIST((2-O20)/SQRT(SessionLeft),TRUE)),"") -> 1 | R20: =IF(ISNUMBER(O20),IF(SessionLeft<=0,--(ABS(O20)>3),_xlfn.NORM.S.DIST((-3-O20)/SQRT(SessionLeft),TRUE)+1-_xlfn.NORM.S.DIST((3-O20)/SQRT(SessionLeft),TRUE)),"") -> 0 | AB20: =IFERROR(IF(INDEX(Feed!$M:$M,$AG20)="","",INDEX(Feed!$M:$M,$AG20)),"") -> 46287.671 | AD20: JPM | AE20: Holding | AF20: EQUITY | AG20: =IFERROR(MATCH($AD20,Feed!$A:$A,0),"") -> 292
A21: BRK-B | C21: =SUMIFS(Holdings!$D:$D,Holdings!$A:$A,$A$18,Holdings!$B:$B,A21) -> 0.12133901 | D21: =IFERROR(IF(INDEX(Feed!$B:$B,$AG21)="","",INDEX(Feed!$B:$B,$AG21)),"") -> 503.57 | E21: =IFERROR(IF(INDEX(Feed!$C:$C,$AG21)="","",INDEX(Feed!$C:$C,$AG21)),"") | F21: =IFERROR(IF(INDEX(Feed!$D:$D,$AG21)="","",INDEX(Feed!$D:$D,$AG21)),"") | G21: =IFERROR(IF(INDEX(Feed!$E:$E,$AG21)="","",INDEX(Feed!$E:$E,$AG21)),"") | H21: =IFERROR(IF(INDEX(Feed!$F:$F,$AG21)="","",INDEX(Feed!$F:$F,$AG21)),"") | I21: =IF(AND(N(E21)>0,N(F21)>0),(F21-E21)/((F21+E21)/2)*10000,"") | J21: =IF(N(D21)>0,IFERROR(D21/INDEX(Feed!$G:$G,$AG21)-1,""),"") -> -0.012162348 | K21: =IFERROR(IF(INDEX(Feed!$H:$H,$AG21)="","",INDEX(Feed!$H:$H,$AG21)),"") -> 4807459 | L21: =IFERROR(IF(INDEX(Feed!$I:$I,$AG21)="","",INDEX(Feed!$I:$I,$AG21)),"") | M21: =IF(AND(N(K21)>0,N(L21)>0),K21/L21,"") | N21: =IFERROR(IF(INDEX(Feed!$L:$L,$AG21)="","",INDEX(Feed!$L:$L,$AG21)),"") -> 0.0096126656 | O21: =IF(AND(ISNUMBER(J21),N(N21)>0),J21/N21,"") -> -1.265242 | P21: =IF(ISNUMBER(O21),IF(SessionLeft<=0,--(ABS(O21)>1),_xlfn.NORM.S.DIST((-1-O21)/SQRT(SessionLeft),TRUE)+1-_xlfn.NORM.S.DIST((1-O21)/SQRT(SessionLeft),TRUE)),"") -> 1 | Q21: =IF(ISNUMBER(O21),IF(SessionLeft<=0,--(ABS(O21)>2),_xlfn.NORM.S.DIST((-2-O21)/SQRT(SessionLeft),TRUE)+1-_xlfn.NORM.S.DIST((2-O21)/SQRT(SessionLeft),TRUE)),"") -> 0 | R21: =IF(ISNUMBER(O21),IF(SessionLeft<=0,--(ABS(O21)>3),_xlfn.NORM.S.DIST((-3-O21)/SQRT(SessionLeft),TRUE)+1-_xlfn.NORM.S.DIST((3-O21)/SQRT(SessionLeft),TRUE)),"") -> 0 | AB21: =IFERROR(IF(INDEX(Feed!$M:$M,$AG21)="","",INDEX(Feed!$M:$M,$AG21)),"") -> 46287.671 | AD21: BRK-B | AE21: Holding | AF21: EQUITY | AG21: =IFERROR(MATCH($AD21,Feed!$A:$A,0),"") -> 91
A22: V | C22: =SUMIFS(Holdings!$D:$D,Holdings!$A:$A,$A$18,Holdings!$B:$B,A22) -> 0.07983334 | D22: =IFERROR(IF(INDEX(Feed!$B:$B,$AG22)="","",INDEX(Feed!$B:$B,$AG22)),"") | E22: =IFERROR(IF(INDEX(Feed!$C:$C,$AG22)="","",INDEX(Feed!$C:$C,$AG22)),"") | F22: =IFERROR(IF(INDEX(Feed!$D:$D,$AG22)="","",INDEX(Feed!$D:$D,$AG22)),"") | G22: =IFERROR(IF(INDEX(Feed!$E:$E,$AG22)="","",INDEX(Feed!$E:$E,$AG22)),"") | H22: =IFERROR(IF(INDEX(Feed!$F:$F,$AG22)="","",INDEX(Feed!$F:$F,$AG22)),"") | I22: =IF(AND(N(E22)>0,N(F22)>0),(F22-E22)/((F22+E22)/2)*10000,"") | J22: =IF(N(D22)>0,IFERROR(D22/INDEX(Feed!$G:$G,$AG22)-1,""),"") | K22: =IFERROR(IF(INDEX(Feed!$H:$H,$AG22)="","",INDEX(Feed!$H:$H,$AG22)),"") | L22: =IFERROR(IF(INDEX(Feed!$I:$I,$AG22)="","",INDEX(Feed!$I:$I,$AG22)),"") | M22: =IF(AND(N(K22)>0,N(L22)>0),K22/L22,"") | N22: =IFERROR(IF(INDEX(Feed!$L:$L,$AG22)="","",INDEX(Feed!$L:$L,$AG22)),"") -> 0.012657042 | O22: =IF(AND(ISNUMBER(J22),N(N22)>0),J22/N22,"") | P22: =IF(ISNUMBER(O22),IF(SessionLeft<=0,--(ABS(O22)>1),_xlfn.NORM.S.DIST((-1-O22)/SQRT(SessionLeft),TRUE)+1-_xlfn.NORM.S.DIST((1-O22)/SQRT(SessionLeft),TRUE)),"") | Q22: =IF(ISNUMBER(O22),IF(SessionLeft<=0,--(ABS(O22)>2),_xlfn.NORM.S.DIST((-2-O22)/SQRT(SessionLeft),TRUE)+1-_xlfn.NORM.S.DIST((2-O22)/SQRT(SessionLeft),TRUE)),"") | R22: =IF(ISNUMBER(O22),IF(SessionLeft<=0,--(ABS(O22)>3),_xlfn.NORM.S.DIST((-3-O22)/SQRT(SessionLeft),TRUE)+1-_xlfn.NORM.S.DIST((3-O22)/SQRT(SessionLeft),TRUE)),"") | AB22: =IFERROR(IF(INDEX(Feed!$M:$M,$AG22)="","",INDEX(Feed!$M:$M,$AG22)),"") | AD22: V | AE22: Holding | AF22: EQUITY | AG22: =IFERROR(MATCH($AD22,Feed!$A:$A,0),"") -> 509
A23: XLE | B23: =IF(NOT(ISNUMBER(V23)),"",IF((NOW()-N(AB23))*1440>StaleMin,"STALE",IF(AND($AF23="EQUITY",ABS(N(T23))>ExDivFlag),"EX-DIV?",IF(X23>IF($AF23="FI",EdgeFI,EdgeEq),"SELL ETF / BUY "&UPPER($A$24),IF(Y23>IF($AF23="FI",EdgeFI,EdgeEq),"BUY ETF / SELL "&UPPER($A$24),""))))) -> STALE | C23: =IFERROR(IF(INDEX(Feed!$N:$N,$AG23)="","",INDEX(Feed!$N:$N,$AG23)),"") -> 1 | D23: =IFERROR(IF(INDEX(Feed!$B:$B,$AG23)="","",INDEX(Feed!$B:$B,$AG23)),"") -> 61.78 | E23: =IFERROR(IF(INDEX(Feed!$C:$C,$AG23)="","",INDEX(Feed!$C:$C,$AG23)),"") | F23: =IFERROR(IF(INDEX(Feed!$D:$D,$AG23)="","",INDEX(Feed!$D:$D,$AG23)),"") | G23: =IFERROR(IF(INDEX(Feed!$E:$E,$AG23)="","",INDEX(Feed!$E:$E,$AG23)),"") | H23: =IFERROR(IF(INDEX(Feed!$F:$F,$AG23)="","",INDEX(Feed!$F:$F,$AG23)),"") | I23: =IF(AND(N(E23)>0,N(F23)>0),(F23-E23)/((F23+E23)/2)*10000,"") | J23: =IF(N(D23)>0,IFERROR(D23/INDEX(Feed!$G:$G,$AG23)-1,""),"") -> -0.039340694 | K23: =IFERROR(IF(INDEX(Feed!$H:$H,$AG23)="","",INDEX(Feed!$H:$H,$AG23)),"") -> 36482216 | L23: =IFERROR(IF(INDEX(Feed!$I:$I,$AG23)="","",INDEX(Feed!$I:$I,$AG23)),"") | M23: =IF(AND(N(K23)>0,N(L23)>0),K23/L23,"") | N23: =IFERROR(IF(INDEX(Feed!$L:$L,$AG23)="","",INDEX(Feed!$L:$L,$AG23)),"") -> 0.013677719 | O23: =IF(AND(ISNUMBER(J23),N(N23)>0),J23/N23,"") -> -2.8762613 | P23: =IF(ISNUMBER(O23),IF(SessionLeft<=0,--(ABS(O23)>1),_xlfn.NORM.S.DIST((-1-O23)/SQRT(SessionLeft),TRUE)+1-_xlfn.NORM.S.DIST((1-O23)/SQRT(SessionLeft),TRUE)),"") -> 1 | Q23: =IF(ISNUMBER(O23),IF(SessionLeft<=0,--(ABS(O23)>2),_xlfn.NORM.S.DIST((-2-O23)/SQRT(SessionLeft),TRUE)+1-_xlfn.NORM.S.DIST((2-O23)/SQRT(SessionLeft),TRUE)),"") -> 1 | R23: =IF(ISNUMBER(O23),IF(SessionLeft<=0,--(ABS(O23)>3),_xlfn.NORM.S.DIST((-3-O23)/SQRT(SessionLeft),TRUE)+1-_xlfn.NORM.S.DIST((3-O23)/SQRT(SessionLeft),TRUE)),"") -> 0 | S23: =IFERROR(IF(INDEX(Feed!$J:$J,$AG23)="","",INDEX(Feed!$J:$J,$AG23)),"") -> 64.3543 | T23: =IFERROR(IF(N(S23)>0,(INDEX(Feed!$G:$G,$AG23)/S23-1)*10000,""),"") -> -6.8837669 | U23: =IFERROR(C23*$J$24,"") -> -0.031958605 | V23: =IF(ISNUMBER(U23),IF(AND(Anchor="NAV",N(S23)>0),S23,INDEX(Feed!$G:$G,$AG23))*(1+U23),"") -> 62.254742 | W23: =IF(ISNUMBER(V23),(IF(AND(N(E23)>0,N(F23)>0),(E23+F23)/2,D23)/V23-1)*10000,"") -> -76.257988 | X23: =IF(ISNUMBER(V23),(IF(N(E23)>0,E23,D23)/V23-1)*10000-IF($AF23="FI",CostFI,CostEq),"") -> -79.257988 | Y23: =IF(ISNUMBER(V23),(1-IF(N(F23)>0,F23,D23)/V23)*10000-IF($AF23="FI",CostFI,CostEq),"") -> 73.257988 | Z23: =IFERROR((J23-U23-INDEX(Feed!$O:$O,$AG23))/INDEX(Feed!$P:$P,$AG23),"") -> -8.2694726 | AA23: =IFERROR(IF(INDEX(Feed!$K:$K,$AG23)="","",INDEX(Feed!$K:$K,$AG23)),"") -> 0.023699999 | AB23: =IFERROR(IF(INDEX(Feed!$M:$M,$AG23)="","",INDEX(Feed!$M:$M,$AG23)),"") -> 46287.671 | AD23: XLE | AE23: ETF | AF23: EQUITY | AG23: =IFERROR(MATCH($AD23,Feed!$A:$A,0),"") -> 6
A24: Basket | C24: =IFERROR(SUMIFS(Holdings!$G:$G,Holdings!$A:$A,$A$23)/SUMIFS(Holdings!$D:$D,Holdings!$A:$A,$A$23),"") -> 0.5851916 | J24: =IFERROR(SUMIFS(Holdings!$F:$F,Holdings!$A:$A,$A$23)/SUMIFS(Holdings!$G:$G,Holdings!$A:$A,$A$23),"") -> -0.031958605 | N24: =IFERROR(IF(INDEX(Feed!$L:$L,$AG24)="","",INDEX(Feed!$L:$L,$AG24)),"") -> 0.013826421 | O24: =IF(AND(ISNUMBER(J24),N(N24)>0),J24/N24,"") -> -2.3114155 | P24: =IF(ISNUMBER(O24),IF(SessionLeft<=0,--(ABS(O24)>1),_xlfn.NORM.S.DIST((-1-O24)/SQRT(SessionLeft),TRUE)+1-_xlfn.NORM.S.DIST((1-O24)/SQRT(SessionLeft),TRUE)),"") -> 1 | Q24: =IF(ISNUMBER(O24),IF(SessionLeft<=0,--(ABS(O24)>2),_xlfn.NORM.S.DIST((-2-O24)/SQRT(SessionLeft),TRUE)+1-_xlfn.NORM.S.DIST((2-O24)/SQRT(SessionLeft),TRUE)),"") -> 1 | R24: =IF(ISNUMBER(O24),IF(SessionLeft<=0,--(ABS(O24)>3),_xlfn.NORM.S.DIST((-3-O24)/SQRT(SessionLeft),TRUE)+1-_xlfn.NORM.S.DIST((3-O24)/SQRT(SessionLeft),TRUE)),"") -> 0 | AD24: XLE BASKET | AE24: Basket | AF24: EQUITY | AG24: =IFERROR(MATCH($AD24,Feed!$A:$A,0),"") -> 563
A25: XOM | C25: =SUMIFS(Holdings!$D:$D,Holdings!$A:$A,$A$23,Holdings!$B:$B,A25) -> 0.23363762 | D25: =IFERROR(IF(INDEX(Feed!$B:$B,$AG25)="","",INDEX(Feed!$B:$B,$AG25)),"") | E25: =IFERROR(IF(INDEX(Feed!$C:$C,$AG25)="","",INDEX(Feed!$C:$C,$AG25)),"") | F25: =IFERROR(IF(INDEX(Feed!$D:$D,$AG25)="","",INDEX(Feed!$D:$D,$AG25)),"") | G25: =IFERROR(IF(INDEX(Feed!$E:$E,$AG25)="","",INDEX(Feed!$E:$E,$AG25)),"") | H25: =IFERROR(IF(INDEX(Feed!$F:$F,$AG25)="","",INDEX(Feed!$F:$F,$AG25)),"") | I25: =IF(AND(N(E25)>0,N(F25)>0),(F25-E25)/((F25+E25)/2)*10000,"") | J25: =IF(N(D25)>0,IFERROR(D25/INDEX(Feed!$G:$G,$AG25)-1,""),"") | K25: =IFERROR(IF(INDEX(Feed!$H:$H,$AG25)="","",INDEX(Feed!$H:$H,$AG25)),"") | L25: =IFERROR(IF(INDEX(Feed!$I:$I,$AG25)="","",INDEX(Feed!$I:$I,$AG25)),"") | M25: =IF(AND(N(K25)>0,N(L25)>0),K25/L25,"") | N25: =IFERROR(IF(INDEX(Feed!$L:$L,$AG25)="","",INDEX(Feed!$L:$L,$AG25)),"") -> 0.016503579 | O25: =IF(AND(ISNUMBER(J25),N(N25)>0),J25/N25,"") | P25: =IF(ISNUMBER(O25),IF(SessionLeft<=0,--(ABS(O25)>1),_xlfn.NORM.S.DIST((-1-O25)/SQRT(SessionLeft),TRUE)+1-_xlfn.NORM.S.DIST((1-O25)/SQRT(SessionLeft),TRUE)),"") | Q25: =IF(ISNUMBER(O25),IF(SessionLeft<=0,--(ABS(O25)>2),_xlfn.NORM.S.DIST((-2-O25)/SQRT(SessionLeft),TRUE)+1-_xlfn.NORM.S.DIST((2-O25)/SQRT(SessionLeft),TRUE)),"") | R25: =IF(ISNUMBER(O25),IF(SessionLeft<=0,--(ABS(O25)>3),_xlfn.NORM.S.DIST((-3-O25)/SQRT(SessionLeft),TRUE)+1-_xlfn.NORM.S.DIST((3-O25)/SQRT(SessionLeft),TRUE)),"") | AB25: =IFERROR(IF(INDEX(Feed!$M:$M,$AG25)="","",INDEX(Feed!$M:$M,$AG25)),"") | AD25: XOM | AE25: Holding | AF25: EQUITY | AG25: =IFERROR(MATCH($AD25,Feed!$A:$A,0),"") -> 552
A26: CVX | C26: =SUMIFS(Holdings!$D:$D,Holdings!$A:$A,$A$23,Holdings!$B:$B,A26) -> 0.17839262 | D26: =IFERROR(IF(INDEX(Feed!$B:$B,$AG26)="","",INDEX(Feed!$B:$B,$AG26)),"") -> 202.41 | E26: =IFERROR(IF(INDEX(Feed!$C:$C,$AG26)="","",INDEX(Feed!$C:$C,$AG26)),"") | F26: =IFERROR(IF(INDEX(Feed!$D:$D,$AG26)="","",INDEX(Feed!$D:$D,$AG26)),"") | G26: =IFERROR(IF(INDEX(Feed!$E:$E,$AG26)="","",INDEX(Feed!$E:$E,$AG26)),"") | H26: =IFERROR(IF(INDEX(Feed!$F:$F,$AG26)="","",INDEX(Feed!$F:$F,$AG26)),"") | I26: =IF(AND(N(E26)>0,N(F26)>0),(F26-E26)/((F26+E26)/2)*10000,"") | J26: =IF(N(D26)>0,IFERROR(D26/INDEX(Feed!$G:$G,$AG26)-1,""),"") -> -0.033888597 | K26: =IFERROR(IF(INDEX(Feed!$H:$H,$AG26)="","",INDEX(Feed!$H:$H,$AG26)),"") -> 8469759 | L26: =IFERROR(IF(INDEX(Feed!$I:$I,$AG26)="","",INDEX(Feed!$I:$I,$AG26)),"") | M26: =IF(AND(N(K26)>0,N(L26)>0),K26/L26,"") | N26: =IFERROR(IF(INDEX(Feed!$L:$L,$AG26)="","",INDEX(Feed!$L:$L,$AG26)),"") -> 0.015788966 | O26: =IF(AND(ISNUMBER(J26),N(N26)>0),J26/N26,"") -> -2.1463468 | P26: =IF(ISNUMBER(O26),IF(SessionLeft<=0,--(ABS(O26)>1),_xlfn.NORM.S.DIST((-1-O26)/SQRT(SessionLeft),TRUE)+1-_xlfn.NORM.S.DIST((1-O26)/SQRT(SessionLeft),TRUE)),"") -> 1 | Q26: =IF(ISNUMBER(O26),IF(SessionLeft<=0,--(ABS(O26)>2),_xlfn.NORM.S.DIST((-2-O26)/SQRT(SessionLeft),TRUE)+1-_xlfn.NORM.S.DIST((2-O26)/SQRT(SessionLeft),TRUE)),"") -> 1 | R26: =IF(ISNUMBER(O26),IF(SessionLeft<=0,--(ABS(O26)>3),_xlfn.NORM.S.DIST((-3-O26)/SQRT(SessionLeft),TRUE)+1-_xlfn.NORM.S.DIST((3-O26)/SQRT(SessionLeft),TRUE)),"") -> 0 | AB26: =IFERROR(IF(INDEX(Feed!$M:$M,$AG26)="","",INDEX(Feed!$M:$M,$AG26)),"") -> 46287.671 | AD26: CVX | AE26: Holding | AF26: EQUITY | AG26: =IFERROR(MATCH($AD26,Feed!$A:$A,0),"") -> 150
A27: COP | C27: =SUMIFS(Holdings!$D:$D,Holdings!$A:$A,$A$23,Holdings!$B:$B,A27) -> 0.06713039 | D27: =IFERROR(IF(INDEX(Feed!$B:$B,$AG27)="","",INDEX(Feed!$B:$B,$AG27)),"") -> 125.27 | E27: =IFERROR(IF(INDEX(Feed!$C:$C,$AG27)="","",INDEX(Feed!$C:$C,$AG27)),"") | F27: =IFERROR(IF(INDEX(Feed!$D:$D,$AG27)="","",INDEX(Feed!$D:$D,$AG27)),"") | G27: =IFERROR(IF(INDEX(Feed!$E:$E,$AG27)="","",INDEX(Feed!$E:$E,$AG27)),"") | H27: =IFERROR(IF(INDEX(Feed!$F:$F,$AG27)="","",INDEX(Feed!$F:$F,$AG27)),"") | I27: =IF(AND(N(E27)>0,N(F27)>0),(F27-E27)/((F27+E27)/2)*10000,"") | J27: =IF(N(D27)>0,IFERROR(D27/INDEX(Feed!$G:$G,$AG27)-1,""),"") -> -0.049761056 | K27: =IFERROR(IF(INDEX(Feed!$H:$H,$AG27)="","",INDEX(Feed!$H:$H,$AG27)),"") -> 6157054 | L27: =IFERROR(IF(INDEX(Feed!$I:$I,$AG27)="","",INDEX(Feed!$I:$I,$AG27)),"") | M27: =IF(AND(N(K27)>0,N(L27)>0),K27/L27,"") | N27: =IFERROR(IF(INDEX(Feed!$L:$L,$AG27)="","",INDEX(Feed!$L:$L,$AG27)),"") -> 0.01979802 | O27: =IF(AND(ISNUMBER(J27),N(N27)>0),J27/N27,"") -> -2.513436 | P27: =IF(ISNUMBER(O27),IF(SessionLeft<=0,--(ABS(O27)>1),_xlfn.NORM.S.DIST((-1-O27)/SQRT(SessionLeft),TRUE)+1-_xlfn.NORM.S.DIST((1-O27)/SQRT(SessionLeft),TRUE)),"") -> 1 | Q27: =IF(ISNUMBER(O27),IF(SessionLeft<=0,--(ABS(O27)>2),_xlfn.NORM.S.DIST((-2-O27)/SQRT(SessionLeft),TRUE)+1-_xlfn.NORM.S.DIST((2-O27)/SQRT(SessionLeft),TRUE)),"") -> 1 | R27: =IF(ISNUMBER(O27),IF(SessionLeft<=0,--(ABS(O27)>3),_xlfn.NORM.S.DIST((-3-O27)/SQRT(SessionLeft),TRUE)+1-_xlfn.NORM.S.DIST((3-O27)/SQRT(SessionLeft),TRUE)),"") -> 0 | AB27: =IFERROR(IF(INDEX(Feed!$M:$M,$AG27)="","",INDEX(Feed!$M:$M,$AG27)),"") -> 46287.671 | AD27: COP | AE27: Holding | AF27: EQUITY | AG27: =IFERROR(MATCH($AD27,Feed!$A:$A,0),"") -> 131
A28: XLV | B28: =IF(NOT(ISNUMBER(V28)),"",IF((NOW()-N(AB28))*1440>StaleMin,"STALE",IF(AND($AF28="EQUITY",ABS(N(T28))>ExDivFlag),"EX-DIV?",IF(X28>IF($AF28="FI",EdgeFI,EdgeEq),"SELL ETF / BUY "&UPPER($A$29),IF(Y28>IF($AF28="FI",EdgeFI,EdgeEq),"BUY ETF / SELL "&UPPER($A$29),""))))) -> STALE | C28: =IFERROR(IF(INDEX(Feed!$N:$N,$AG28)="","",INDEX(Feed!$N:$N,$AG28)),"") -> 1 | D28: =IFERROR(IF(INDEX(Feed!$B:$B,$AG28)="","",INDEX(Feed!$B:$B,$AG28)),"") -> 170.34 | E28: =IFERROR(IF(INDEX(Feed!$C:$C,$AG28)="","",INDEX(Feed!$C:$C,$AG28)),"") -> 169.55 | F28: =IFERROR(IF(INDEX(Feed!$D:$D,$AG28)="","",INDEX(Feed!$D:$D,$AG28)),"") -> 170.35 | G28: =IFERROR(IF(INDEX(Feed!$E:$E,$AG28)="","",INDEX(Feed!$E:$E,$AG28)),"") -> 100 | H28: =IFERROR(IF(INDEX(Feed!$F:$F,$AG28)="","",INDEX(Feed!$F:$F,$AG28)),"") -> 700 | I28: =IF(AND(N(E28)>0,N(F28)>0),(F28-E28)/((F28+E28)/2)*10000,"") -> 47.072668 | J28: =IF(N(D28)>0,IFERROR(D28/INDEX(Feed!$G:$G,$AG28)-1,""),"") -> 0.01158026 | K28: =IFERROR(IF(INDEX(Feed!$H:$H,$AG28)="","",INDEX(Feed!$H:$H,$AG28)),"") -> 7618319 | L28: =IFERROR(IF(INDEX(Feed!$I:$I,$AG28)="","",INDEX(Feed!$I:$I,$AG28)),"") | M28: =IF(AND(N(K28)>0,N(L28)>0),K28/L28,"") | N28: =IFERROR(IF(INDEX(Feed!$L:$L,$AG28)="","",INDEX(Feed!$L:$L,$AG28)),"") -> 0.012011046 | O28: =IF(AND(ISNUMBER(J28),N(N28)>0),J28/N28,"") -> 0.96413422 | P28: =IF(ISNUMBER(O28),IF(SessionLeft<=0,--(ABS(O28)>1),_xlfn.NORM.S.DIST((-1-O28)/SQRT(SessionLeft),TRUE)+1-_xlfn.NORM.S.DIST((1-O28)/SQRT(SessionLeft),TRUE)),"") -> 0 | Q28: =IF(ISNUMBER(O28),IF(SessionLeft<=0,--(ABS(O28)>2),_xlfn.NORM.S.DIST((-2-O28)/SQRT(SessionLeft),TRUE)+1-_xlfn.NORM.S.DIST((2-O28)/SQRT(SessionLeft),TRUE)),"") -> 0 | R28: =IF(ISNUMBER(O28),IF(SessionLeft<=0,--(ABS(O28)>3),_xlfn.NORM.S.DIST((-3-O28)/SQRT(SessionLeft),TRUE)+1-_xlfn.NORM.S.DIST((3-O28)/SQRT(SessionLeft),TRUE)),"") -> 0 | S28: =IFERROR(IF(INDEX(Feed!$J:$J,$AG28)="","",INDEX(Feed!$J:$J,$AG28)),"") -> 168.47356 | T28: =IFERROR(IF(N(S28)>0,(INDEX(Feed!$G:$G,$AG28)/S28-1)*10000,""),"") -> -4.9598287 | U28: =IFERROR(C28*$J$29,"") -> 0.013971663 | V28: =IF(ISNUMBER(U28),IF(AND(Anchor="NAV",N(S28)>0),S28,INDEX(Feed!$G:$G,$AG28))*(1+U28),"") -> 170.74269 | W28: =IF(ISNUMBER(V28),(IF(AND(N(E28)>0,N(F28)>0),(E28+F28)/2,D28)/V28-1)*10000,"") -> -46.425899 | X28: =IF(ISNUMBER(V28),(IF(N(E28)>0,E28,D28)/V28-1)*10000-IF($AF28="FI",CostFI,CostEq),"") -> -72.852964 | Y28: =IF(ISNUMBER(V28),(1-IF(N(F28)>0,F28,D28)/V28)*10000-IF($AF28="FI",CostFI,CostEq),"") -> 19.998834 | Z28: =IFERROR((J28-U28-INDEX(Feed!$O:$O,$AG28))/INDEX(Feed!$P:$P,$AG28),"") -> -5.0744295 | AA28: =IFERROR(IF(INDEX(Feed!$K:$K,$AG28)="","",INDEX(Feed!$K:$K,$AG28)),"") -> 0.0149 | AB28: =IFERROR(IF(INDEX(Feed!$M:$M,$AG28)="","",INDEX(Feed!$M:$M,$AG28)),"") -> 46287.673 | AD28: XLV | AE28: ETF | AF28: EQUITY | AG28: =IFERROR(MATCH($AD28,Feed!$A:$A,0),"") -> 7
A29: Basket | C29: =IFERROR(SUMIFS(Holdings!$G:$G,Holdings!$A:$A,$A$28)/SUMIFS(Holdings!$D:$D,Holdings!$A:$A,$A$28),"") -> 0.89305529 | J29: =IFERROR(SUMIFS(Holdings!$F:$F,Holdings!$A:$A,$A$28)/SUMIFS(Holdings!$G:$G,Holdings!$A:$A,$A$28),"") -> 0.013971663 | N29: =IFERROR(IF(INDEX(Feed!$L:$L,$AG29)="","",INDEX(Feed!$L:$L,$AG29)),"") -> 0.012162636 | O29: =IF(AND(ISNUMBER(J29),N(N29)>0),J29/N29,"") -> 1.1487364 | P29: =IF(ISNUMBER(O29),IF(SessionLeft<=0,--(ABS(O29)>1),_xlfn.NORM.S.DIST((-1-O29)/SQRT(SessionLeft),TRUE)+1-_xlfn.NORM.S.DIST((1-O29)/SQRT(SessionLeft),TRUE)),"") -> 1 | Q29: =IF(ISNUMBER(O29),IF(SessionLeft<=0,--(ABS(O29)>2),_xlfn.NORM.S.DIST((-2-O29)/SQRT(SessionLeft),TRUE)+1-_xlfn.NORM.S.DIST((2-O29)/SQRT(SessionLeft),TRUE)),"") -> 0 | R29: =IF(ISNUMBER(O29),IF(SessionLeft<=0,--(ABS(O29)>3),_xlfn.NORM.S.DIST((-3-O29)/SQRT(SessionLeft),TRUE)+1-_xlfn.NORM.S.DIST((3-O29)/SQRT(SessionLeft),TRUE)),"") -> 0 | AD29: XLV BASKET | AE29: Basket | AF29: EQUITY | AG29: =IFERROR(MATCH($AD29,Feed!$A:$A,0),"") -> 564
A30: LLY | C30: =SUMIFS(Holdings!$D:$D,Holdings!$A:$A,$A$28,Holdings!$B:$B,A30) -> 0.1516036 | D30: =IFERROR(IF(INDEX(Feed!$B:$B,$AG30)="","",INDEX(Feed!$B:$B,$AG30)),"") -> 1169 | E30: =IFERROR(IF(INDEX(Feed!$C:$C,$AG30)="","",INDEX(Feed!$C:$C,$AG30)),"") | F30: =IFERROR(IF(INDEX(Feed!$D:$D,$AG30)="","",INDEX(Feed!$D:$D,$AG30)),"") | G30: =IFERROR(IF(INDEX(Feed!$E:$E,$AG30)="","",INDEX(Feed!$E:$E,$AG30)),"") | H30: =IFERROR(IF(INDEX(Feed!$F:$F,$AG30)="","",INDEX(Feed!$F:$F,$AG30)),"") | I30: =IF(AND(N(E30)>0,N(F30)>0),(F30-E30)/((F30+E30)/2)*10000,"") | J30: =IF(N(D30)>0,IFERROR(D30/INDEX(Feed!$G:$G,$AG30)-1,""),"") -> 0.0139384 | K30: =IFERROR(IF(INDEX(Feed!$H:$H,$AG30)="","",INDEX(Feed!$H:$H,$AG30)),"") -> 2480210 | L30: =IFERROR(IF(INDEX(Feed!$I:$I,$AG30)="","",INDEX(Feed!$I:$I,$AG30)),"") | M30: =IF(AND(N(K30)>0,N(L30)>0),K30/L30,"") | N30: =IFERROR(IF(INDEX(Feed!$L:$L,$AG30)="","",INDEX(Feed!$L:$L,$AG30)),"") -> 0.021168384 | O30: =IF(AND(ISNUMBER(J30),N(N30)>0),J30/N30,"") -> 0.65845369 | P30: =IF(ISNUMBER(O30),IF(SessionLeft<=0,--(ABS(O30)>1),_xlfn.NORM.S.DIST((-1-O30)/SQRT(SessionLeft),TRUE)+1-_xlfn.NORM.S.DIST((1-O30)/SQRT(SessionLeft),TRUE)),"") -> 0 | Q30: =IF(ISNUMBER(O30),IF(SessionLeft<=0,--(ABS(O30)>2),_xlfn.NORM.S.DIST((-2-O30)/SQRT(SessionLeft),TRUE)+1-_xlfn.NORM.S.DIST((2-O30)/SQRT(SessionLeft),TRUE)),"") -> 0 | R30: =IF(ISNUMBER(O30),IF(SessionLeft<=0,--(ABS(O30)>3),_xlfn.NORM.S.DIST((-3-O30)/SQRT(SessionLeft),TRUE)+1-_xlfn.NORM.S.DIST((3-O30)/SQRT(SessionLeft),TRUE)),"") -> 0 | AB30: =IFERROR(IF(INDEX(Feed!$M:$M,$AG30)="","",INDEX(Feed!$M:$M,$AG30)),"") -> 46287.671 | AD30: LLY | AE30: Holding | AF30: EQUITY | AG30: =IFERROR(MATCH($AD30,Feed!$A:$A,0),"") -> 313
A31: JNJ | C31: =SUMIFS(Holdings!$D:$D,Holdings!$A:$A,$A$28,Holdings!$B:$B,A31) -> 0.10504005 | D31: =IFERROR(IF(INDEX(Feed!$B:$B,$AG31)="","",INDEX(Feed!$B:$B,$AG31)),"") -> 269.19 | E31: =IFERROR(IF(INDEX(Feed!$C:$C,$AG31)="","",INDEX(Feed!$C:$C,$AG31)),"") | F31: =IFERROR(IF(INDEX(Feed!$D:$D,$AG31)="","",INDEX(Feed!$D:$D,$AG31)),"") | G31: =IFERROR(IF(INDEX(Feed!$E:$E,$AG31)="","",INDEX(Feed!$E:$E,$AG31)),"") | H31: =IFERROR(IF(INDEX(Feed!$F:$F,$AG31)="","",INDEX(Feed!$F:$F,$AG31)),"") | I31: =IF(AND(N(E31)>0,N(F31)>0),(F31-E31)/((F31+E31)/2)*10000,"") | J31: =IF(N(D31)>0,IFERROR(D31/INDEX(Feed!$G:$G,$AG31)-1,""),"") -> -0.0029630727 | K31: =IFERROR(IF(INDEX(Feed!$H:$H,$AG31)="","",INDEX(Feed!$H:$H,$AG31)),"") -> 4487741 | L31: =IFERROR(IF(INDEX(Feed!$I:$I,$AG31)="","",INDEX(Feed!$I:$I,$AG31)),"") | M31: =IF(AND(N(K31)>0,N(L31)>0),K31/L31,"") | N31: =IFERROR(IF(INDEX(Feed!$L:$L,$AG31)="","",INDEX(Feed!$L:$L,$AG31)),"") -> 0.015061652 | O31: =IF(AND(ISNUMBER(J31),N(N31)>0),J31/N31,"") -> -0.1967296 | P31: =IF(ISNUMBER(O31),IF(SessionLeft<=0,--(ABS(O31)>1),_xlfn.NORM.S.DIST((-1-O31)/SQRT(SessionLeft),TRUE)+1-_xlfn.NORM.S.DIST((1-O31)/SQRT(SessionLeft),TRUE)),"") -> 0 | Q31: =IF(ISNUMBER(O31),IF(SessionLeft<=0,--(ABS(O31)>2),_xlfn.NORM.S.DIST((-2-O31)/SQRT(SessionLeft),TRUE)+1-_xlfn.NORM.S.DIST((2-O31)/SQRT(SessionLeft),TRUE)),"") -> 0 | R31: =IF(ISNUMBER(O31),IF(SessionLeft<=0,--(ABS(O31)>3),_xlfn.NORM.S.DIST((-3-O31)/SQRT(SessionLeft),TRUE)+1-_xlfn.NORM.S.DIST((3-O31)/SQRT(SessionLeft),TRUE)),"") -> 0 | AB31: =IFERROR(IF(INDEX(Feed!$M:$M,$AG31)="","",INDEX(Feed!$M:$M,$AG31)),"") -> 46287.671 | AD31: JNJ | AE31: Holding | AF31: EQUITY | AG31: =IFERROR(MATCH($AD31,Feed!$A:$A,0),"") -> 290
A32: ABBV | C32: =SUMIFS(Holdings!$D:$D,Holdings!$A:$A,$A$28,Holdings!$B:$B,A32) -> 0.07588456 | D32: =IFERROR(IF(INDEX(Feed!$B:$B,$AG32)="","",INDEX(Feed!$B:$B,$AG32)),"") -> 265.21 | E32: =IFERROR(IF(INDEX(Feed!$C:$C,$AG32)="","",INDEX(Feed!$C:$C,$AG32)),"") | F32: =IFERROR(IF(INDEX(Feed!$D:$D,$AG32)="","",INDEX(Feed!$D:$D,$AG32)),"") | G32: =IFERROR(IF(INDEX(Feed!$E:$E,$AG32)="","",INDEX(Feed!$E:$E,$AG32)),"") | H32: =IFERROR(IF(INDEX(Feed!$F:$F,$AG32)="","",INDEX(Feed!$F:$F,$AG32)),"") | I32: =IF(AND(N(E32)>0,N(F32)>0),(F32-E32)/((F32+E32)/2)*10000,"") | J32: =IF(N(D32)>0,IFERROR(D32/INDEX(Feed!$G:$G,$AG32)-1,""),"") -> 0.004735566 | K32: =IFERROR(IF(INDEX(Feed!$H:$H,$AG32)="","",INDEX(Feed!$H:$H,$AG32)),"") -> 3438160 | L32: =IFERROR(IF(INDEX(Feed!$I:$I,$AG32)="","",INDEX(Feed!$I:$I,$AG32)),"") | M32: =IF(AND(N(K32)>0,N(L32)>0),K32/L32,"") | N32: =IFERROR(IF(INDEX(Feed!$L:$L,$AG32)="","",INDEX(Feed!$L:$L,$AG32)),"") -> 0.015757903 | O32: =IF(AND(ISNUMBER(J32),N(N32)>0),J32/N32,"") -> 0.30052007 | P32: =IF(ISNUMBER(O32),IF(SessionLeft<=0,--(ABS(O32)>1),_xlfn.NORM.S.DIST((-1-O32)/SQRT(SessionLeft),TRUE)+1-_xlfn.NORM.S.DIST((1-O32)/SQRT(SessionLeft),TRUE)),"") -> 0 | Q32: =IF(ISNUMBER(O32),IF(SessionLeft<=0,--(ABS(O32)>2),_xlfn.NORM.S.DIST((-2-O32)/SQRT(SessionLeft),TRUE)+1-_xlfn.NORM.S.DIST((2-O32)/SQRT(SessionLeft),TRUE)),"") -> 0 | R32: =IF(ISNUMBER(O32),IF(SessionLeft<=0,--(ABS(O32)>3),_xlfn.NORM.S.DIST((-3-O32)/SQRT(SessionLeft),TRUE)+1-_xlfn.NORM.S.DIST((3-O32)/SQRT(SessionLeft),TRUE)),"") -> 0 | AB32: =IFERROR(IF(INDEX(Feed!$M:$M,$AG32)="","",INDEX(Feed!$M:$M,$AG32)),"") -> 46287.671 | AD32: ABBV | AE32: Holding | AF32: EQUITY | AG32: =IFERROR(MATCH($AD32,Feed!$A:$A,0),"") -> 21
A33: IWM | B33: =IF(NOT(ISNUMBER(V33)),"",IF((NOW()-N(AB33))*1440>StaleMin,"STALE",IF(AND($AF33="EQUITY",ABS(N(T33))>ExDivFlag),"EX-DIV?",IF(X33>IF($AF33="FI",EdgeFI,EdgeEq),"SELL ETF / BUY "&UPPER($A$34),IF(Y33>IF($AF33="FI",EdgeFI,EdgeEq),"BUY ETF / SELL "&UPPER($A$34),""))))) -> STALE | C33: =IFERROR(IF(INDEX(Feed!$N:$N,$AG33)="","",INDEX(Feed!$N:$N,$AG33)),"") -> 0.99819867 | D33: =IFERROR(IF(INDEX(Feed!$B:$B,$AG33)="","",INDEX(Feed!$B:$B,$AG33)),"") -> 285.4921 | E33: =IFERROR(IF(INDEX(Feed!$C:$C,$AG33)="","",INDEX(Feed!$C:$C,$AG33)),"") | F33: =IFERROR(IF(INDEX(Feed!$D:$D,$AG33)="","",INDEX(Feed!$D:$D,$AG33)),"") | G33: =IFERROR(IF(INDEX(Feed!$E:$E,$AG33)="","",INDEX(Feed!$E:$E,$AG33)),"") | H33: =IFERROR(IF(INDEX(Feed!$F:$F,$AG33)="","",INDEX(Feed!$F:$F,$AG33)),"") | I33: =IF(AND(N(E33)>0,N(F33)>0),(F33-E33)/((F33+E33)/2)*10000,"") | J33: =IF(N(D33)>0,IFERROR(D33/INDEX(Feed!$G:$G,$AG33)-1,""),"") -> 0.0049000352 | K33: =IFERROR(IF(INDEX(Feed!$H:$H,$AG33)="","",INDEX(Feed!$H:$H,$AG33)),"") -> 18968224 | L33: =IFERROR(IF(INDEX(Feed!$I:$I,$AG33)="","",INDEX(Feed!$I:$I,$AG33)),"") | M33: =IF(AND(N(K33)>0,N(L33)>0),K33/L33,"") | N33: =IFERROR(IF(INDEX(Feed!$L:$L,$AG33)="","",INDEX(Feed!$L:$L,$AG33)),"") -> 0.008127509 | O33: =IF(AND(ISNUMBER(J33),N(N33)>0),J33/N33,"") -> 0.60289508 | P33: =IF(ISNUMBER(O33),IF(SessionLeft<=0,--(ABS(O33)>1),_xlfn.NORM.S.DIST((-1-O33)/SQRT(SessionLeft),TRUE)+1-_xlfn.NORM.S.DIST((1-O33)/SQRT(SessionLeft),TRUE)),"") -> 0 | Q33: =IF(ISNUMBER(O33),IF(SessionLeft<=0,--(ABS(O33)>2),_xlfn.NORM.S.DIST((-2-O33)/SQRT(SessionLeft),TRUE)+1-_xlfn.NORM.S.DIST((2-O33)/SQRT(SessionLeft),TRUE)),"") -> 0 | R33: =IF(ISNUMBER(O33),IF(SessionLeft<=0,--(ABS(O33)>3),_xlfn.NORM.S.DIST((-3-O33)/SQRT(SessionLeft),TRUE)+1-_xlfn.NORM.S.DIST((3-O33)/SQRT(SessionLeft),TRUE)),"") -> 0 | S33: =IFERROR(IF(INDEX(Feed!$J:$J,$AG33)="","",INDEX(Feed!$J:$J,$AG33)),"") -> 283.9969 | T33: =IFERROR(IF(N(S33)>0,(INDEX(Feed!$G:$G,$AG33)/S33-1)*10000,""),"") -> 3.6303213 | U33: =IFERROR(C33*$J$34,"") -> 0.0056921831 | V33: =IF(ISNUMBER(U33),IF(AND(Anchor="NAV",N(S33)>0),S33,INDEX(Feed!$G:$G,$AG33))*(1+U33),"") -> 285.71715 | W33: =IF(ISNUMBER(V33),(IF(AND(N(E33)>0,N(F33)>0),(E33+F33)/2,D33)/V33-1)*10000,"") -> -7.8766435 | X33: =IF(ISNUMBER(V33),(IF(N(E33)>0,E33,D33)/V33-1)*10000-IF($AF33="FI",CostFI,CostEq),"") -> -10.876644 | Y33: =IF(ISNUMBER(V33),(1-IF(N(F33)>0,F33,D33)/V33)*10000-IF($AF33="FI",CostFI,CostEq),"") -> 4.8766435 | Z33: =IFERROR((J33-U33-INDEX(Feed!$O:$O,$AG33))/INDEX(Feed!$P:$P,$AG33),"") -> -0.57140361 | AA33: =IFERROR(IF(INDEX(Feed!$K:$K,$AG33)="","",INDEX(Feed!$K:$K,$AG33)),"") -> 0.009 | AB33: =IFERROR(IF(INDEX(Feed!$M:$M,$AG33)="","",INDEX(Feed!$M:$M,$AG33)),"") -> 46287.672 | AD33: IWM | AE33: ETF | AF33: EQUITY | AG33: =IFERROR(MATCH($AD33,Feed!$A:$A,0),"") -> 8
A34: VTWO | D34: =IFERROR(IF(INDEX(Feed!$B:$B,$AG34)="","",INDEX(Feed!$B:$B,$AG34)),"") -> 116.4 | E34: =IFERROR(IF(INDEX(Feed!$C:$C,$AG34)="","",INDEX(Feed!$C:$C,$AG34)),"") -> 116.35 | F34: =IFERROR(IF(INDEX(Feed!$D:$D,$AG34)="","",INDEX(Feed!$D:$D,$AG34)),"") -> 116.38 | G34: =IFERROR(IF(INDEX(Feed!$E:$E,$AG34)="","",INDEX(Feed!$E:$E,$AG34)),"") -> 1300 | H34: =IFERROR(IF(INDEX(Feed!$F:$F,$AG34)="","",INDEX(Feed!$F:$F,$AG34)),"") -> 1300 | I34: =IF(AND(N(E34)>0,N(F34)>0),(F34-E34)/((F34+E34)/2)*10000,"") -> 2.5780948 | J34: =IF(N(D34)>0,IFERROR(D34/INDEX(Feed!$G:$G,$AG34)-1,""),"") -> 0.0057024551 | K34: =IFERROR(IF(INDEX(Feed!$H:$H,$AG34)="","",INDEX(Feed!$H:$H,$AG34)),"") | L34: =IFERROR(IF(INDEX(Feed!$I:$I,$AG34)="","",INDEX(Feed!$I:$I,$AG34)),"") | M34: =IF(AND(N(K34)>0,N(L34)>0),K34/L34,"") | N34: =IFERROR(IF(INDEX(Feed!$L:$L,$AG34)="","",INDEX(Feed!$L:$L,$AG34)),"") -> 0.0080839738 | O34: =IF(AND(ISNUMBER(J34),N(N34)>0),J34/N34,"") -> 0.70540246 | P34: =IF(ISNUMBER(O34),IF(SessionLeft<=0,--(ABS(O34)>1),_xlfn.NORM.S.DIST((-1-O34)/SQRT(SessionLeft),TRUE)+1-_xlfn.NORM.S.DIST((1-O34)/SQRT(SessionLeft),TRUE)),"") -> 0 | Q34: =IF(ISNUMBER(O34),IF(SessionLeft<=0,--(ABS(O34)>2),_xlfn.NORM.S.DIST((-2-O34)/SQRT(SessionLeft),TRUE)+1-_xlfn.NORM.S.DIST((2-O34)/SQRT(SessionLeft),TRUE)),"") -> 0 | R34: =IF(ISNUMBER(O34),IF(SessionLeft<=0,--(ABS(O34)>3),_xlfn.NORM.S.DIST((-3-O34)/SQRT(SessionLeft),TRUE)+1-_xlfn.NORM.S.DIST((3-O34)/SQRT(SessionLeft),TRUE)),"") -> 0 | AB34: =IFERROR(IF(INDEX(Feed!$M:$M,$AG34)="","",INDEX(Feed!$M:$M,$AG34)),"") -> 46287.683 | AD34: VTWO | AE34: Underlying | AF34: EQUITY | AG34: =IFERROR(MATCH($AD34,Feed!$A:$A,0),"") -> 532
A35: AAPU | B35: =IF(NOT(ISNUMBER(V35)),"",IF((NOW()-N(AB35))*1440>StaleMin,"STALE",IF(AND($AF35="EQUITY",ABS(N(T35))>ExDivFlag),"EX-DIV?",IF(X35>IF($AF35="FI",EdgeFI,EdgeEq),"SELL ETF / BUY "&UPPER($A$36),IF(Y35>IF($AF35="FI",EdgeFI,EdgeEq),"BUY ETF / SELL "&UPPER($A$36),""))))) | C35: =IFERROR(IF(INDEX(Feed!$N:$N,$AG35)="","",INDEX(Feed!$N:$N,$AG35)),"") -> 2 | D35: =IFERROR(IF(INDEX(Feed!$B:$B,$AG35)="","",INDEX(Feed!$B:$B,$AG35)),"") -> 46.14 | E35: =IFERROR(IF(INDEX(Feed!$C:$C,$AG35)="","",INDEX(Feed!$C:$C,$AG35)),"") | F35: =IFERROR(IF(INDEX(Feed!$D:$D,$AG35)="","",INDEX(Feed!$D:$D,$AG35)),"") | G35: =IFERROR(IF(INDEX(Feed!$E:$E,$AG35)="","",INDEX(Feed!$E:$E,$AG35)),"") | H35: =IFERROR(IF(INDEX(Feed!$F:$F,$AG35)="","",INDEX(Feed!$F:$F,$AG35)),"") | I35: =IF(AND(N(E35)>0,N(F35)>0),(F35-E35)/((F35+E35)/2)*10000,"") | J35: =IF(N(D35)>0,IFERROR(D35/INDEX(Feed!$G:$G,$AG35)-1,""),"") -> 0.019218025 | K35: =IFERROR(IF(INDEX(Feed!$H:$H,$AG35)="","",INDEX(Feed!$H:$H,$AG35)),"") -> 706522 | L35: =IFERROR(IF(INDEX(Feed!$I:$I,$AG35)="","",INDEX(Feed!$I:$I,$AG35)),"") | M35: =IF(AND(N(K35)>0,N(L35)>0),K35/L35,"") | N35: =IFERROR(IF(INDEX(Feed!$L:$L,$AG35)="","",INDEX(Feed!$L:$L,$AG35)),"") -> 0.036577395 | O35: =IF(AND(ISNUMBER(J35),N(N35)>0),J35/N35,"") -> 0.52540716 | P35: =IF(ISNUMBER(O35),IF(SessionLeft<=0,--(ABS(O35)>1),_xlfn.NORM.S.DIST((-1-O35)/SQRT(SessionLeft),TRUE)+1-_xlfn.NORM.S.DIST((1-O35)/SQRT(SessionLeft),TRUE)),"") -> 0 | Q35: =IF(ISNUMBER(O35),IF(SessionLeft<=0,--(ABS(O35)>2),_xlfn.NORM.S.DIST((-2-O35)/SQRT(SessionLeft),TRUE)+1-_xlfn.NORM.S.DIST((2-O35)/SQRT(SessionLeft),TRUE)),"") -> 0 | R35: =IF(ISNUMBER(O35),IF(SessionLeft<=0,--(ABS(O35)>3),_xlfn.NORM.S.DIST((-3-O35)/SQRT(SessionLeft),TRUE)+1-_xlfn.NORM.S.DIST((3-O35)/SQRT(SessionLeft),TRUE)),"") -> 0 | S35: =IFERROR(IF(INDEX(Feed!$J:$J,$AG35)="","",INDEX(Feed!$J:$J,$AG35)),"") -> 45.386 | T35: =IFERROR(IF(N(S35)>0,(INDEX(Feed!$G:$G,$AG35)/S35-1)*10000,""),"") -> -25.558542 | U35: =IFERROR(C35*$J$36,"") | V35: =IF(ISNUMBER(U35),IF(AND(Anchor="NAV",N(S35)>0),S35,INDEX(Feed!$G:$G,$AG35))*(1+U35),"") | W35: =IF(ISNUMBER(V35),(IF(AND(N(E35)>0,N(F35)>0),(E35+F35)/2,D35)/V35-1)*10000,"") | X35: =IF(ISNUMBER(V35),(IF(N(E35)>0,E35,D35)/V35-1)*10000-IF($AF35="FI",CostFI,CostEq),"") | Y35: =IF(ISNUMBER(V35),(1-IF(N(F35)>0,F35,D35)/V35)*10000-IF($AF35="FI",CostFI,CostEq),"") | Z35: =IFERROR((J35-U35-INDEX(Feed!$O:$O,$AG35))/INDEX(Feed!$P:$P,$AG35),"") | AA35: =IFERROR(IF(INDEX(Feed!$K:$K,$AG35)="","",INDEX(Feed!$K:$K,$AG35)),"") -> 0.0186 | AB35: =IFERROR(IF(INDEX(Feed!$M:$M,$AG35)="","",INDEX(Feed!$M:$M,$AG35)),"") -> 46287.671 | AD35: AAPU | AE35: ETF | AF35: EQUITY | AG35: =IFERROR(MATCH($AD35,Feed!$A:$A,0),"") -> 9
A36: AAPL | D36: =IFERROR(IF(INDEX(Feed!$B:$B,$AG36)="","",INDEX(Feed!$B:$B,$AG36)),"") | E36: =IFERROR(IF(INDEX(Feed!$C:$C,$AG36)="","",INDEX(Feed!$C:$C,$AG36)),"") | F36: =IFERROR(IF(INDEX(Feed!$D:$D,$AG36)="","",INDEX(Feed!$D:$D,$AG36)),"") | G36: =IFERROR(IF(INDEX(Feed!$E:$E,$AG36)="","",INDEX(Feed!$E:$E,$AG36)),"") | H36: =IFERROR(IF(INDEX(Feed!$F:$F,$AG36)="","",INDEX(Feed!$F:$F,$AG36)),"") | I36: =IF(AND(N(E36)>0,N(F36)>0),(F36-E36)/((F36+E36)/2)*10000,"") | J36: =IF(N(D36)>0,IFERROR(D36/INDEX(Feed!$G:$G,$AG36)-1,""),"") | K36: =IFERROR(IF(INDEX(Feed!$H:$H,$AG36)="","",INDEX(Feed!$H:$H,$AG36)),"") | L36: =IFERROR(IF(INDEX(Feed!$I:$I,$AG36)="","",INDEX(Feed!$I:$I,$AG36)),"") | M36: =IF(AND(N(K36)>0,N(L36)>0),K36/L36,"") | N36: =IFERROR(IF(INDEX(Feed!$L:$L,$AG36)="","",INDEX(Feed!$L:$L,$AG36)),"") -> 0.018439339 | O36: =IF(AND(ISNUMBER(J36),N(N36)>0),J36/N36,"") | P36: =IF(ISNUMBER(O36),IF(SessionLeft<=0,--(ABS(O36)>1),_xlfn.NORM.S.DIST((-1-O36)/SQRT(SessionLeft),TRUE)+1-_xlfn.NORM.S.DIST((1-O36)/SQRT(SessionLeft),TRUE)),"") | Q36: =IF(ISNUMBER(O36),IF(SessionLeft<=0,--(ABS(O36)>2),_xlfn.NORM.S.DIST((-2-O36)/SQRT(SessionLeft),TRUE)+1-_xlfn.NORM.S.DIST((2-O36)/SQRT(SessionLeft),TRUE)),"") | R36: =IF(ISNUMBER(O36),IF(SessionLeft<=0,--(ABS(O36)>3),_xlfn.NORM.S.DIST((-3-O36)/SQRT(SessionLeft),TRUE)+1-_xlfn.NORM.S.DIST((3-O36)/SQRT(SessionLeft),TRUE)),"") | AB36: =IFERROR(IF(INDEX(Feed!$M:$M,$AG36)="","",INDEX(Feed!$M:$M,$AG36)),"") | AD36: AAPL | AE36: Underlying | AF36: EQUITY | AG36: =IFERROR(MATCH($AD36,Feed!$A:$A,0),"") -> 20
A38: TLT | B38: =IF(NOT(ISNUMBER(V38)),"",IF((NOW()-N(AB38))*1440>StaleMin,"STALE",IF(AND($AF38="EQUITY",ABS(N(T38))>ExDivFlag),"EX-DIV?",IF(X38>IF($AF38="FI",EdgeFI,EdgeEq),"SELL ETF / BUY "&UPPER($A$39),IF(Y38>IF($AF38="FI",EdgeFI,EdgeEq),"BUY ETF / SELL "&UPPER($A$39),""))))) -> STALE | C38: =IFERROR(IF(INDEX(Feed!$N:$N,$AG38)="","",INDEX(Feed!$N:$N,$AG38)),"") -> 1.0740028 | D38: =IFERROR(IF(INDEX(Feed!$B:$B,$AG38)="","",INDEX(Feed!$B:$B,$AG38)),"") -> 81.69 | E38: =IFERROR(IF(INDEX(Feed!$C:$C,$AG38)="","",INDEX(Feed!$C:$C,$AG38)),"") -> 81.7 | F38: =IFERROR(IF(INDEX(Feed!$D:$D,$AG38)="","",INDEX(Feed!$D:$D,$AG38)),"") -> 81.72 | G38: =IFERROR(IF(INDEX(Feed!$E:$E,$AG38)="","",INDEX(Feed!$E:$E,$AG38)),"") -> 1600 | H38: =IFERROR(IF(INDEX(Feed!$F:$F,$AG38)="","",INDEX(Feed!$F:$F,$AG38)),"") -> 1300 | I38: =IF(AND(N(E38)>0,N(F38)>0),(F38-E38)/((F38+E38)/2)*10000,"") -> 2.4476808 | J38: =IF(N(D38)>0,IFERROR(D38/INDEX(Feed!$G:$G,$AG38)-1,""),"") -> 0.0054153846 | K38: =IFERROR(IF(INDEX(Feed!$H:$H,$AG38)="","",INDEX(Feed!$H:$H,$AG38)),"") -> 26981681 | L38: =IFERROR(IF(INDEX(Feed!$I:$I,$AG38)="","",INDEX(Feed!$I:$I,$AG38)),"") | M38: =IF(AND(N(K38)>0,N(L38)>0),K38/L38,"") | N38: =IFERROR(IF(INDEX(Feed!$L:$L,$AG38)="","",INDEX(Feed!$L:$L,$AG38)),"") -> 0.0059716259 | O38: =IF(AND(ISNUMBER(J38),N(N38)>0),J38/N38,"") -> 0.90685263 | P38: =IF(ISNUMBER(O38),IF(SessionLeft<=0,--(ABS(O38)>1),_xlfn.NORM.S.DIST((-1-O38)/SQRT(SessionLeft),TRUE)+1-_xlfn.NORM.S.DIST((1-O38)/SQRT(SessionLeft),TRUE)),"") -> 0 | Q38: =IF(ISNUMBER(O38),IF(SessionLeft<=0,--(ABS(O38)>2),_xlfn.NORM.S.DIST((-2-O38)/SQRT(SessionLeft),TRUE)+1-_xlfn.NORM.S.DIST((2-O38)/SQRT(SessionLeft),TRUE)),"") -> 0 | R38: =IF(ISNUMBER(O38),IF(SessionLeft<=0,--(ABS(O38)>3),_xlfn.NORM.S.DIST((-3-O38)/SQRT(SessionLeft),TRUE)+1-_xlfn.NORM.S.DIST((3-O38)/SQRT(SessionLeft),TRUE)),"") -> 0 | S38: =IFERROR(IF(INDEX(Feed!$J:$J,$AG38)="","",INDEX(Feed!$J:$J,$AG38)),"") -> 81.15524 | T38: =IFERROR(IF(N(S38)>0,(INDEX(Feed!$G:$G,$AG38)/S38-1)*10000,""),"") -> 11.676387 | U38: =IFERROR(C38*$J$39,"") -> -0.00020484666 | V38: =IF(ISNUMBER(U38),IF(AND(Anchor="NAV",N(S38)>0),S38,INDEX(Feed!$G:$G,$AG38))*(1+U38),"") -> 81.233356 | W38: =IF(ISNUMBER(V38),(IF(AND(N(E38)>0,N(F38)>0),(E38+F38)/2,D38)/V38-1)*10000,"") -> 58.675871 | X38: =IF(ISNUMBER(V38),(IF(N(E38)>0,E38,D38)/V38-1)*10000-IF($AF38="FI",CostFI,CostEq),"") -> 49.444849 | Y38: =IF(ISNUMBER(V38),(1-IF(N(F38)>0,F38,D38)/V38)*10000-IF($AF38="FI",CostFI,CostEq),"") -> -67.906892 | Z38: =IFERROR((J38-U38-INDEX(Feed!$O:$O,$AG38))/INDEX(Feed!$P:$P,$AG38),"") -> 10.893027 | AA38: =IFERROR(IF(INDEX(Feed!$K:$K,$AG38)="","",INDEX(Feed!$K:$K,$AG38)),"") -> 0.0473 | AB38: =IFERROR(IF(INDEX(Feed!$M:$M,$AG38)="","",INDEX(Feed!$M:$M,$AG38)),"") -> 46287.673 | AD38: TLT | AE38: ETF | AF38: FI | AG38: =IFERROR(MATCH($AD38,Feed!$A:$A,0),"") -> 10
A39: VGLT | D39: =IFERROR(IF(INDEX(Feed!$B:$B,$AG39)="","",INDEX(Feed!$B:$B,$AG39)),"") -> 52.41 | E39: =IFERROR(IF(INDEX(Feed!$C:$C,$AG39)="","",INDEX(Feed!$C:$C,$AG39)),"") -> 52.4 | F39: =IFERROR(IF(INDEX(Feed!$D:$D,$AG39)="","",INDEX(Feed!$D:$D,$AG39)),"") -> 52.42 | G39: =IFERROR(IF(INDEX(Feed!$E:$E,$AG39)="","",INDEX(Feed!$E:$E,$AG39)),"") -> 5400 | H39: =IFERROR(IF(INDEX(Feed!$F:$F,$AG39)="","",INDEX(Feed!$F:$F,$AG39)),"") -> 10300 | I39: =IF(AND(N(E39)>0,N(F39)>0),(F39-E39)/((F39+E39)/2)*10000,"") -> 3.8160656 | J39: =IF(N(D39)>0,IFERROR(D39/INDEX(Feed!$G:$G,$AG39)-1,""),"") -> -0.00019073196 | K39: =IFERROR(IF(INDEX(Feed!$H:$H,$AG39)="","",INDEX(Feed!$H:$H,$AG39)),"") | L39: =IFERROR(IF(INDEX(Feed!$I:$I,$AG39)="","",INDEX(Feed!$I:$I,$AG39)),"") | M39: =IF(AND(N(K39)>0,N(L39)>0),K39/L39,"") | N39: =IFERROR(IF(INDEX(Feed!$L:$L,$AG39)="","",INDEX(Feed!$L:$L,$AG39)),"") -> 0.005514854 | O39: =IF(AND(ISNUMBER(J39),N(N39)>0),J39/N39,"") -> -0.034585133 | P39: =IF(ISNUMBER(O39),IF(SessionLeft<=0,--(ABS(O39)>1),_xlfn.NORM.S.DIST((-1-O39)/SQRT(SessionLeft),TRUE)+1-_xlfn.NORM.S.DIST((1-O39)/SQRT(SessionLeft),TRUE)),"") -> 0 | Q39: =IF(ISNUMBER(O39),IF(SessionLeft<=0,--(ABS(O39)>2),_xlfn.NORM.S.DIST((-2-O39)/SQRT(SessionLeft),TRUE)+1-_xlfn.NORM.S.DIST((2-O39)/SQRT(SessionLeft),TRUE)),"") -> 0 | R39: =IF(ISNUMBER(O39),IF(SessionLeft<=0,--(ABS(O39)>3),_xlfn.NORM.S.DIST((-3-O39)/SQRT(SessionLeft),TRUE)+1-_xlfn.NORM.S.DIST((3-O39)/SQRT(SessionLeft),TRUE)),"") -> 0 | AB39: =IFERROR(IF(INDEX(Feed!$M:$M,$AG39)="","",INDEX(Feed!$M:$M,$AG39)),"") -> 46287.683 | AD39: VGLT | AE39: Underlying | AF39: FI | AG39: =IFERROR(MATCH($AD39,Feed!$A:$A,0),"") -> 514
A40: IEF | B40: =IF(NOT(ISNUMBER(V40)),"",IF((NOW()-N(AB40))*1440>StaleMin,"STALE",IF(AND($AF40="EQUITY",ABS(N(T40))>ExDivFlag),"EX-DIV?",IF(X40>IF($AF40="FI",EdgeFI,EdgeEq),"SELL ETF / BUY "&UPPER($A$41),IF(Y40>IF($AF40="FI",EdgeFI,EdgeEq),"BUY ETF / SELL "&UPPER($A$41),""))))) -> STALE | C40: =IFERROR(IF(INDEX(Feed!$N:$N,$AG40)="","",INDEX(Feed!$N:$N,$AG40)),"") -> 1.3887398 | D40: =IFERROR(IF(INDEX(Feed!$B:$B,$AG40)="","",INDEX(Feed!$B:$B,$AG40)),"") -> 91.14 | E40: =IFERROR(IF(INDEX(Feed!$C:$C,$AG40)="","",INDEX(Feed!$C:$C,$AG40)),"") | F40: =IFERROR(IF(INDEX(Feed!$D:$D,$AG40)="","",INDEX(Feed!$D:$D,$AG40)),"") | G40: =IFERROR(IF(INDEX(Feed!$E:$E,$AG40)="","",INDEX(Feed!$E:$E,$AG40)),"") | H40: =IFERROR(IF(INDEX(Feed!$F:$F,$AG40)="","",INDEX(Feed!$F:$F,$AG40)),"") | I40: =IF(AND(N(E40)>0,N(F40)>0),(F40-E40)/((F40+E40)/2)*10000,"") | J40: =IF(N(D40)>0,IFERROR(D40/INDEX(Feed!$G:$G,$AG40)-1,""),"") -> 0.0037444934 | K40: =IFERROR(IF(INDEX(Feed!$H:$H,$AG40)="","",INDEX(Feed!$H:$H,$AG40)),"") -> 8833521 | L40: =IFERROR(IF(INDEX(Feed!$I:$I,$AG40)="","",INDEX(Feed!$I:$I,$AG40)),"") | M40: =IF(AND(N(K40)>0,N(L40)>0),K40/L40,"") | N40: =IFERROR(IF(INDEX(Feed!$L:$L,$AG40)="","",INDEX(Feed!$L:$L,$AG40)),"") -> 0.0029743916 | O40: =IF(AND(ISNUMBER(J40),N(N40)>0),J40/N40,"") -> 1.2589107 | P40: =IF(ISNUMBER(O40),IF(SessionLeft<=0,--(ABS(O40)>1),_xlfn.NORM.S.DIST((-1-O40)/SQRT(SessionLeft),TRUE)+1-_xlfn.NORM.S.DIST((1-O40)/SQRT(SessionLeft),TRUE)),"") -> 1 | Q40: =IF(ISNUMBER(O40),IF(SessionLeft<=0,--(ABS(O40)>2),_xlfn.NORM.S.DIST((-2-O40)/SQRT(SessionLeft),TRUE)+1-_xlfn.NORM.S.DIST((2-O40)/SQRT(SessionLeft),TRUE)),"") -> 0 | R40: =IF(ISNUMBER(O40),IF(SessionLeft<=0,--(ABS(O40)>3),_xlfn.NORM.S.DIST((-3-O40)/SQRT(SessionLeft),TRUE)+1-_xlfn.NORM.S.DIST((3-O40)/SQRT(SessionLeft),TRUE)),"") -> 0 | S40: =IFERROR(IF(INDEX(Feed!$J:$J,$AG40)="","",INDEX(Feed!$J:$J,$AG40)),"") -> 90.75945 | T40: =IFERROR(IF(N(S40)>0,(INDEX(Feed!$G:$G,$AG40)/S40-1)*10000,""),"") -> 4.4678543 | U40: =IFERROR(C40*$J$41,"") -> 0.00024228739 | V40: =IF(ISNUMBER(U40),IF(AND(Anchor="NAV",N(S40)>0),S40,INDEX(Feed!$G:$G,$AG40))*(1+U40),"") -> 90.822 | W40: =IF(ISNUMBER(V40),(IF(AND(N(E40)>0,N(F40)>0),(E40+F40)/2,D40)/V40-1)*10000,"") -> 35.013577 | X40: =IF(ISNUMBER(V40),(IF(N(E40)>0,E40,D40)/V40-1)*10000-IF($AF40="FI",CostFI,CostEq),"") -> 27.013577 | Y40: =IF(ISNUMBER(V40),(1-IF(N(F40)>0,F40,D40)/V40)*10000-IF($AF40="FI",CostFI,CostEq),"") -> -43.013577 | Z40: =IFERROR((J40-U40-INDEX(Feed!$O:$O,$AG40))/INDEX(Feed!$P:$P,$AG40),"") -> 6.4941005 | AA40: =IFERROR(IF(INDEX(Feed!$K:$K,$AG40)="","",INDEX(Feed!$K:$K,$AG40)),"") -> 0.0397 | AB40: =IFERROR(IF(INDEX(Feed!$M:$M,$AG40)="","",INDEX(Feed!$M:$M,$AG40)),"") -> 46287.671 | AD40: IEF | AE40: ETF | AF40: FI | AG40: =IFERROR(MATCH($AD40,Feed!$A:$A,0),"") -> 11
A41: VGIT | D41: =IFERROR(IF(INDEX(Feed!$B:$B,$AG41)="","",INDEX(Feed!$B:$B,$AG41)),"") -> 57.32 | E41: =IFERROR(IF(INDEX(Feed!$C:$C,$AG41)="","",INDEX(Feed!$C:$C,$AG41)),"") -> 57.32 | F41: =IFERROR(IF(INDEX(Feed!$D:$D,$AG41)="","",INDEX(Feed!$D:$D,$AG41)),"") -> 57.33 | G41: =IFERROR(IF(INDEX(Feed!$E:$E,$AG41)="","",INDEX(Feed!$E:$E,$AG41)),"") -> 4200 | H41: =IFERROR(IF(INDEX(Feed!$F:$F,$AG41)="","",INDEX(Feed!$F:$F,$AG41)),"") -> 29600 | I41: =IF(AND(N(E41)>0,N(F41)>0),(F41-E41)/((F41+E41)/2)*10000,"") -> 1.7444396 | J41: =IF(N(D41)>0,IFERROR(D41/INDEX(Feed!$G:$G,$AG41)-1,""),"") -> 0.00017446565 | K41: =IFERROR(IF(INDEX(Feed!$H:$H,$AG41)="","",INDEX(Feed!$H:$H,$AG41)),"") | L41: =IFERROR(IF(INDEX(Feed!$I:$I,$AG41)="","",INDEX(Feed!$I:$I,$AG41)),"") | M41: =IF(AND(N(K41)>0,N(L41)>0),K41/L41,"") | N41: =IFERROR(IF(INDEX(Feed!$L:$L,$AG41)="","",INDEX(Feed!$L:$L,$AG41)),"") -> 0.0020782566 | O41: =IF(AND(ISNUMBER(J41),N(N41)>0),J41/N41,"") -> 0.083948078 | P41: =IF(ISNUMBER(O41),IF(SessionLeft<=0,--(ABS(O41)>1),_xlfn.NORM.S.DIST((-1-O41)/SQRT(SessionLeft),TRUE)+1-_xlfn.NORM.S.DIST((1-O41)/SQRT(SessionLeft),TRUE)),"") -> 0 | Q41: =IF(ISNUMBER(O41),IF(SessionLeft<=0,--(ABS(O41)>2),_xlfn.NORM.S.DIST((-2-O41)/SQRT(SessionLeft),TRUE)+1-_xlfn.NORM.S.DIST((2-O41)/SQRT(SessionLeft),TRUE)),"") -> 0 | R41: =IF(ISNUMBER(O41),IF(SessionLeft<=0,--(ABS(O41)>3),_xlfn.NORM.S.DIST((-3-O41)/SQRT(SessionLeft),TRUE)+1-_xlfn.NORM.S.DIST((3-O41)/SQRT(SessionLeft),TRUE)),"") -> 0 | AB41: =IFERROR(IF(INDEX(Feed!$M:$M,$AG41)="","",INDEX(Feed!$M:$M,$AG41)),"") -> 46287.683 | AD41: VGIT | AE41: Underlying | AF41: FI | AG41: =IFERROR(MATCH($AD41,Feed!$A:$A,0),"") -> 513
A42: SHY | B42: =IF(NOT(ISNUMBER(V42)),"",IF((NOW()-N(AB42))*1440>StaleMin,"STALE",IF(AND($AF42="EQUITY",ABS(N(T42))>ExDivFlag),"EX-DIV?",IF(X42>IF($AF42="FI",EdgeFI,EdgeEq),"SELL ETF / BUY "&UPPER($A$43),IF(Y42>IF($AF42="FI",EdgeFI,EdgeEq),"BUY ETF / SELL "&UPPER($A$43),""))))) -> STALE | C42: =IFERROR(IF(INDEX(Feed!$N:$N,$AG42)="","",INDEX(Feed!$N:$N,$AG42)),"") -> 1.0304722 | D42: =IFERROR(IF(INDEX(Feed!$B:$B,$AG42)="","",INDEX(Feed!$B:$B,$AG42)),"") -> 81.3015 | E42: =IFERROR(IF(INDEX(Feed!$C:$C,$AG42)="","",INDEX(Feed!$C:$C,$AG42)),"") -> 81.3 | F42: =IFERROR(IF(INDEX(Feed!$D:$D,$AG42)="","",INDEX(Feed!$D:$D,$AG42)),"") -> 81.31 | G42: =IFERROR(IF(INDEX(Feed!$E:$E,$AG42)="","",INDEX(Feed!$E:$E,$AG42)),"") -> 116049 | H42: =IFERROR(IF(INDEX(Feed!$F:$F,$AG42)="","",INDEX(Feed!$F:$F,$AG42)),"") -> 6100 | I42: =IF(AND(N(E42)>0,N(F42)>0),(F42-E42)/((F42+E42)/2)*10000,"") -> 1.2299367 | J42: =IF(N(D42)>0,IFERROR(D42/INDEX(Feed!$G:$G,$AG42)-1,""),"") -> 0.00075701625 | K42: =IFERROR(IF(INDEX(Feed!$H:$H,$AG42)="","",INDEX(Feed!$H:$H,$AG42)),"") -> 3973124 | L42: =IFERROR(IF(INDEX(Feed!$I:$I,$AG42)="","",INDEX(Feed!$I:$I,$AG42)),"") | M42: =IF(AND(N(K42)>0,N(L42)>0),K42/L42,"") | N42: =IFERROR(IF(INDEX(Feed!$L:$L,$AG42)="","",INDEX(Feed!$L:$L,$AG42)),"") -> 0.00086285564 | O42: =IF(AND(ISNUMBER(J42),N(N42)>0),J42/N42,"") -> 0.87733824 | P42: =IF(ISNUMBER(O42),IF(SessionLeft<=0,--(ABS(O42)>1),_xlfn.NORM.S.DIST((-1-O42)/SQRT(SessionLeft),TRUE)+1-_xlfn.NORM.S.DIST((1-O42)/SQRT(SessionLeft),TRUE)),"") -> 0 | Q42: =IF(ISNUMBER(O42),IF(SessionLeft<=0,--(ABS(O42)>2),_xlfn.NORM.S.DIST((-2-O42)/SQRT(SessionLeft),TRUE)+1-_xlfn.NORM.S.DIST((2-O42)/SQRT(SessionLeft),TRUE)),"") -> 0 | R42: =IF(ISNUMBER(O42),IF(SessionLeft<=0,--(ABS(O42)>3),_xlfn.NORM.S.DIST((-3-O42)/SQRT(SessionLeft),TRUE)+1-_xlfn.NORM.S.DIST((3-O42)/SQRT(SessionLeft),TRUE)),"") -> 0 | S42: =IFERROR(IF(INDEX(Feed!$J:$J,$AG42)="","",INDEX(Feed!$J:$J,$AG42)),"") -> 81.22375 | T42: =IFERROR(IF(N(S42)>0,(INDEX(Feed!$G:$G,$AG42)/S42-1)*10000,""),"") -> 2.0006464 | U42: =IFERROR(C42*$J$43,"") -> 0.00035759749 | V42: =IF(ISNUMBER(U42),IF(AND(Anchor="NAV",N(S42)>0),S42,INDEX(Feed!$G:$G,$AG42))*(1+U42),"") -> 81.269051 | W42: =IF(ISNUMBER(V42),(IF(AND(N(E42)>0,N(F42)>0),(E42+F42)/2,D42)/V42-1)*10000,"") -> 4.423428 | X42: =IF(ISNUMBER(V42),(IF(N(E42)>0,E42,D42)/V42-1)*10000-IF($AF42="FI",CostFI,CostEq),"") -> -4.1918124 | Y42: =IF(ISNUMBER(V42),(1-IF(N(F42)>0,F42,D42)/V42)*10000-IF($AF42="FI",CostFI,CostEq),"") -> -13.038668 | Z42: =IFERROR((J42-U42-INDEX(Feed!$O:$O,$AG42))/INDEX(Feed!$P:$P,$AG42),"") -> 1.8783256 | AA42: =IFERROR(IF(INDEX(Feed!$K:$K,$AG42)="","",INDEX(Feed!$K:$K,$AG42)),"") -> 0.0363 | AB42: =IFERROR(IF(INDEX(Feed!$M:$M,$AG42)="","",INDEX(Feed!$M:$M,$AG42)),"") -> 46287.673 | AD42: SHY | AE42: ETF | AF42: FI | AG42: =IFERROR(MATCH($AD42,Feed!$A:$A,0),"") -> 12
A43: VGSH | D43: =IFERROR(IF(INDEX(Feed!$B:$B,$AG43)="","",INDEX(Feed!$B:$B,$AG43)),"") -> 57.65 | E43: =IFERROR(IF(INDEX(Feed!$C:$C,$AG43)="","",INDEX(Feed!$C:$C,$AG43)),"") -> 57.64 | F43: =IFERROR(IF(INDEX(Feed!$D:$D,$AG43)="","",INDEX(Feed!$D:$D,$AG43)),"") -> 57.65 | G43: =IFERROR(IF(INDEX(Feed!$E:$E,$AG43)="","",INDEX(Feed!$E:$E,$AG43)),"") -> 91916 | H43: =IFERROR(IF(INDEX(Feed!$F:$F,$AG43)="","",INDEX(Feed!$F:$F,$AG43)),"") -> 70100 | I43: =IF(AND(N(E43)>0,N(F43)>0),(F43-E43)/((F43+E43)/2)*10000,"") -> 1.7347558 | J43: =IF(N(D43)>0,IFERROR(D43/INDEX(Feed!$G:$G,$AG43)-1,""),"") -> 0.00034702293 | K43: =IFERROR(IF(INDEX(Feed!$H:$H,$AG43)="","",INDEX(Feed!$H:$H,$AG43)),"") | L43: =IFERROR(IF(INDEX(Feed!$I:$I,$AG43)="","",INDEX(Feed!$I:$I,$AG43)),"") | M43: =IF(AND(N(K43)>0,N(L43)>0),K43/L43,"") | N43: =IFERROR(IF(INDEX(Feed!$L:$L,$AG43)="","",INDEX(Feed!$L:$L,$AG43)),"") -> 0.00080810013 | O43: =IF(AND(ISNUMBER(J43),N(N43)>0),J43/N43,"") -> 0.42943061 | P43: =IF(ISNUMBER(O43),IF(SessionLeft<=0,--(ABS(O43)>1),_xlfn.NORM.S.DIST((-1-O43)/SQRT(SessionLeft),TRUE)+1-_xlfn.NORM.S.DIST((1-O43)/SQRT(SessionLeft),TRUE)),"") -> 0 | Q43: =IF(ISNUMBER(O43),IF(SessionLeft<=0,--(ABS(O43)>2),_xlfn.NORM.S.DIST((-2-O43)/SQRT(SessionLeft),TRUE)+1-_xlfn.NORM.S.DIST((2-O43)/SQRT(SessionLeft),TRUE)),"") -> 0 | R43: =IF(ISNUMBER(O43),IF(SessionLeft<=0,--(ABS(O43)>3),_xlfn.NORM.S.DIST((-3-O43)/SQRT(SessionLeft),TRUE)+1-_xlfn.NORM.S.DIST((3-O43)/SQRT(SessionLeft),TRUE)),"") -> 0 | AB43: =IFERROR(IF(INDEX(Feed!$M:$M,$AG43)="","",INDEX(Feed!$M:$M,$AG43)),"") -> 46287.683 | AD43: VGSH | AE43: Underlying | AF43: FI | AG43: =IFERROR(MATCH($AD43,Feed!$A:$A,0),"") -> 515
A44: LQD | B44: =IF(NOT(ISNUMBER(V44)),"",IF((NOW()-N(AB44))*1440>StaleMin,"STALE",IF(AND($AF44="EQUITY",ABS(N(T44))>ExDivFlag),"EX-DIV?",IF(X44>IF($AF44="FI",EdgeFI,EdgeEq),"SELL ETF / BUY "&UPPER($A$45),IF(Y44>IF($AF44="FI",EdgeFI,EdgeEq),"BUY ETF / SELL "&UPPER($A$45),""))))) -> STALE | C44: =IFERROR(IF(INDEX(Feed!$N:$N,$AG44)="","",INDEX(Feed!$N:$N,$AG44)),"") -> 1.0508315 | D44: =IFERROR(IF(INDEX(Feed!$B:$B,$AG44)="","",INDEX(Feed!$B:$B,$AG44)),"") -> 105.09 | E44: =IFERROR(IF(INDEX(Feed!$C:$C,$AG44)="","",INDEX(Feed!$C:$C,$AG44)),"") | F44: =IFERROR(IF(INDEX(Feed!$D:$D,$AG44)="","",INDEX(Feed!$D:$D,$AG44)),"") | G44: =IFERROR(IF(INDEX(Feed!$E:$E,$AG44)="","",INDEX(Feed!$E:$E,$AG44)),"") | H44: =IFERROR(IF(INDEX(Feed!$F:$F,$AG44)="","",INDEX(Feed!$F:$F,$AG44)),"") | I44: =IF(AND(N(E44)>0,N(F44)>0),(F44-E44)/((F44+E44)/2)*10000,"") | J44: =IF(N(D44)>0,IFERROR(D44/INDEX(Feed!$G:$G,$AG44)-1,""),"") -> 0.0037249284 | K44: =IFERROR(IF(INDEX(Feed!$H:$H,$AG44)="","",INDEX(Feed!$H:$H,$AG44)),"") -> 23076568 | L44: =IFERROR(IF(INDEX(Feed!$I:$I,$AG44)="","",INDEX(Feed!$I:$I,$AG44)),"") | M44: =IF(AND(N(K44)>0,N(L44)>0),K44/L44,"") | N44: =IFERROR(IF(INDEX(Feed!$L:$L,$AG44)="","",INDEX(Feed!$L:$L,$AG44)),"") -> 0.003448224 | O44: =IF(AND(ISNUMBER(J44),N(N44)>0),J44/N44,"") -> 1.0802455 | P44: =IF(ISNUMBER(O44),IF(SessionLeft<=0,--(ABS(O44)>1),_xlfn.NORM.S.DIST((-1-O44)/SQRT(SessionLeft),TRUE)+1-_xlfn.NORM.S.DIST((1-O44)/SQRT(SessionLeft),TRUE)),"") -> 1 | Q44: =IF(ISNUMBER(O44),IF(SessionLeft<=0,--(ABS(O44)>2),_xlfn.NORM.S.DIST((-2-O44)/SQRT(SessionLeft),TRUE)+1-_xlfn.NORM.S.DIST((2-O44)/SQRT(SessionLeft),TRUE)),"") -> 0 | R44: =IF(ISNUMBER(O44),IF(SessionLeft<=0,--(ABS(O44)>3),_xlfn.NORM.S.DIST((-3-O44)/SQRT(SessionLeft),TRUE)+1-_xlfn.NORM.S.DIST((3-O44)/SQRT(SessionLeft),TRUE)),"") -> 0 | S44: =IFERROR(IF(INDEX(Feed!$J:$J,$AG44)="","",INDEX(Feed!$J:$J,$AG44)),"") -> 104.60595 | T44: =IFERROR(IF(N(S44)>0,(INDEX(Feed!$G:$G,$AG44)/S44-1)*10000,""),"") -> 8.9908844 | U44: =IFERROR(C44*$J$45,"") -> 0.0039348315 | V44: =IF(ISNUMBER(U44),IF(AND(Anchor="NAV",N(S44)>0),S44,INDEX(Feed!$G:$G,$AG44))*(1+U44),"") -> 105.11198 | W44: =IF(ISNUMBER(V44),(IF(AND(N(E44)>0,N(F44)>0),(E44+F44)/2,D44)/V44-1)*10000,"") -> -2.0908045 | X44: =IF(ISNUMBER(V44),(IF(N(E44)>0,E44,D44)/V44-1)*10000-IF($AF44="FI",CostFI,CostEq),"") -> -10.090804 | Y44: =IF(ISNUMBER(V44),(1-IF(N(F44)>0,F44,D44)/V44)*10000-IF($AF44="FI",CostFI,CostEq),"") -> -5.9091955 | Z44: =IFERROR((J44-U44-INDEX(Feed!$O:$O,$AG44))/INDEX(Feed!$P:$P,$AG44),"") -> -0.2109625 | AA44: =IFERROR(IF(INDEX(Feed!$K:$K,$AG44)="","",INDEX(Feed!$K:$K,$AG44)),"") -> 0.0467 | AB44: =IFERROR(IF(INDEX(Feed!$M:$M,$AG44)="","",INDEX(Feed!$M:$M,$AG44)),"") -> 46287.671 | AD44: LQD | AE44: ETF | AF44: FI | AG44: =IFERROR(MATCH($AD44,Feed!$A:$A,0),"") -> 13
A45: IEF | D45: =IFERROR(IF(INDEX(Feed!$B:$B,$AG45)="","",INDEX(Feed!$B:$B,$AG45)),"") -> 91.14 | E45: =IFERROR(IF(INDEX(Feed!$C:$C,$AG45)="","",INDEX(Feed!$C:$C,$AG45)),"") | F45: =IFERROR(IF(INDEX(Feed!$D:$D,$AG45)="","",INDEX(Feed!$D:$D,$AG45)),"") | G45: =IFERROR(IF(INDEX(Feed!$E:$E,$AG45)="","",INDEX(Feed!$E:$E,$AG45)),"") | H45: =IFERROR(IF(INDEX(Feed!$F:$F,$AG45)="","",INDEX(Feed!$F:$F,$AG45)),"") | I45: =IF(AND(N(E45)>0,N(F45)>0),(F45-E45)/((F45+E45)/2)*10000,"") | J45: =IF(N(D45)>0,IFERROR(D45/INDEX(Feed!$G:$G,$AG45)-1,""),"") -> 0.0037444934 | K45: =IFERROR(IF(INDEX(Feed!$H:$H,$AG45)="","",INDEX(Feed!$H:$H,$AG45)),"") -> 8833521 | L45: =IFERROR(IF(INDEX(Feed!$I:$I,$AG45)="","",INDEX(Feed!$I:$I,$AG45)),"") | M45: =IF(AND(N(K45)>0,N(L45)>0),K45/L45,"") | N45: =IFERROR(IF(INDEX(Feed!$L:$L,$AG45)="","",INDEX(Feed!$L:$L,$AG45)),"") -> 0.0029743916 | O45: =IF(AND(ISNUMBER(J45),N(N45)>0),J45/N45,"") -> 1.2589107 | P45: =IF(ISNUMBER(O45),IF(SessionLeft<=0,--(ABS(O45)>1),_xlfn.NORM.S.DIST((-1-O45)/SQRT(SessionLeft),TRUE)+1-_xlfn.NORM.S.DIST((1-O45)/SQRT(SessionLeft),TRUE)),"") -> 1 | Q45: =IF(ISNUMBER(O45),IF(SessionLeft<=0,--(ABS(O45)>2),_xlfn.NORM.S.DIST((-2-O45)/SQRT(SessionLeft),TRUE)+1-_xlfn.NORM.S.DIST((2-O45)/SQRT(SessionLeft),TRUE)),"") -> 0 | R45: =IF(ISNUMBER(O45),IF(SessionLeft<=0,--(ABS(O45)>3),_xlfn.NORM.S.DIST((-3-O45)/SQRT(SessionLeft),TRUE)+1-_xlfn.NORM.S.DIST((3-O45)/SQRT(SessionLeft),TRUE)),"") -> 0 | AB45: =IFERROR(IF(INDEX(Feed!$M:$M,$AG45)="","",INDEX(Feed!$M:$M,$AG45)),"") -> 46287.671 | AD45: IEF | AE45: Underlying | AF45: FI | AG45: =IFERROR(MATCH($AD45,Feed!$A:$A,0),"") -> 11
A46: VCIT | B46: =IF(NOT(ISNUMBER(V46)),"",IF((NOW()-N(AB46))*1440>StaleMin,"STALE",IF(AND($AF46="EQUITY",ABS(N(T46))>ExDivFlag),"EX-DIV?",IF(X46>IF($AF46="FI",EdgeFI,EdgeEq),"SELL ETF / BUY "&UPPER($A$47),IF(Y46>IF($AF46="FI",EdgeFI,EdgeEq),"BUY ETF / SELL "&UPPER($A$47),""))))) -> STALE | C46: =IFERROR(IF(INDEX(Feed!$N:$N,$AG46)="","",INDEX(Feed!$N:$N,$AG46)),"") -> 0.87552298 | D46: =IFERROR(IF(INDEX(Feed!$B:$B,$AG46)="","",INDEX(Feed!$B:$B,$AG46)),"") -> 79.95 | E46: =IFERROR(IF(INDEX(Feed!$C:$C,$AG46)="","",INDEX(Feed!$C:$C,$AG46)),"") -> 79.9 | F46: =IFERROR(IF(INDEX(Feed!$D:$D,$AG46)="","",INDEX(Feed!$D:$D,$AG46)),"") -> 80.35 | G46: =IFERROR(IF(INDEX(Feed!$E:$E,$AG46)="","",INDEX(Feed!$E:$E,$AG46)),"") -> 700 | H46: =IFERROR(IF(INDEX(Feed!$F:$F,$AG46)="","",INDEX(Feed!$F:$F,$AG46)),"") -> 31 | I46: =IF(AND(N(E46)>0,N(F46)>0),(F46-E46)/((F46+E46)/2)*10000,"") -> 56.162246 | J46: =IF(N(D46)>0,IFERROR(D46/INDEX(Feed!$G:$G,$AG46)-1,""),"") -> 0.0032626427 | K46: =IFERROR(IF(INDEX(Feed!$H:$H,$AG46)="","",INDEX(Feed!$H:$H,$AG46)),"") -> 10353336 | L46: =IFERROR(IF(INDEX(Feed!$I:$I,$AG46)="","",INDEX(Feed!$I:$I,$AG46)),"") | M46: =IF(AND(N(K46)>0,N(L46)>0),K46/L46,"") | N46: =IFERROR(IF(INDEX(Feed!$L:$L,$AG46)="","",INDEX(Feed!$L:$L,$AG46)),"") -> 0.0027199828 | O46: =IF(AND(ISNUMBER(J46),N(N46)>0),J46/N46,"") -> 1.1995086 | P46: =IF(ISNUMBER(O46),IF(SessionLeft<=0,--(ABS(O46)>1),_xlfn.NORM.S.DIST((-1-O46)/SQRT(SessionLeft),TRUE)+1-_xlfn.NORM.S.DIST((1-O46)/SQRT(SessionLeft),TRUE)),"") -> 1 | Q46: =IF(ISNUMBER(O46),IF(SessionLeft<=0,--(ABS(O46)>2),_xlfn.NORM.S.DIST((-2-O46)/SQRT(SessionLeft),TRUE)+1-_xlfn.NORM.S.DIST((2-O46)/SQRT(SessionLeft),TRUE)),"") -> 0 | R46: =IF(ISNUMBER(O46),IF(SessionLeft<=0,--(ABS(O46)>3),_xlfn.NORM.S.DIST((-3-O46)/SQRT(SessionLeft),TRUE)+1-_xlfn.NORM.S.DIST((3-O46)/SQRT(SessionLeft),TRUE)),"") -> 0 | S46: =IFERROR(IF(INDEX(Feed!$J:$J,$AG46)="","",INDEX(Feed!$J:$J,$AG46)),"") -> 79.64 | T46: =IFERROR(IF(N(S46)>0,(INDEX(Feed!$G:$G,$AG46)/S46-1)*10000,""),"") -> 6.2782521 | U46: =IFERROR(C46*$J$47,"") -> 0.00327839 | V46: =IF(ISNUMBER(U46),IF(AND(Anchor="NAV",N(S46)>0),S46,INDEX(Feed!$G:$G,$AG46))*(1+U46),"") -> 79.951255 | W46: =IF(ISNUMBER(V46),(IF(AND(N(E46)>0,N(F46)>0),(E46+F46)/2,D46)/V46-1)*10000,"") -> 21.731379 | X46: =IF(ISNUMBER(V46),(IF(N(E46)>0,E46,D46)/V46-1)*10000-IF($AF46="FI",CostFI,CostEq),"") -> -14.410769 | Y46: =IF(ISNUMBER(V46),(1-IF(N(F46)>0,F46,D46)/V46)*10000-IF($AF46="FI",CostFI,CostEq),"") -> -57.873526 | Z46: =IFERROR((J46-U46-INDEX(Feed!$O:$O,$AG46))/INDEX(Feed!$P:$P,$AG46),"") -> -0.087755129 | AA46: =IFERROR(IF(INDEX(Feed!$K:$K,$AG46)="","",INDEX(Feed!$K:$K,$AG46)),"") -> 0.048899997 | AB46: =IFERROR(IF(INDEX(Feed!$M:$M,$AG46)="","",INDEX(Feed!$M:$M,$AG46)),"") -> 46287.673 | AD46: VCIT | AE46: ETF | AF46: FI | AG46: =IFERROR(MATCH($AD46,Feed!$A:$A,0),"") -> 14
A47: IEF | D47: =IFERROR(IF(INDEX(Feed!$B:$B,$AG47)="","",INDEX(Feed!$B:$B,$AG47)),"") -> 91.14 | E47: =IFERROR(IF(INDEX(Feed!$C:$C,$AG47)="","",INDEX(Feed!$C:$C,$AG47)),"") | F47: =IFERROR(IF(INDEX(Feed!$D:$D,$AG47)="","",INDEX(Feed!$D:$D,$AG47)),"") | G47: =IFERROR(IF(INDEX(Feed!$E:$E,$AG47)="","",INDEX(Feed!$E:$E,$AG47)),"") | H47: =IFERROR(IF(INDEX(Feed!$F:$F,$AG47)="","",INDEX(Feed!$F:$F,$AG47)),"") | I47: =IF(AND(N(E47)>0,N(F47)>0),(F47-E47)/((F47+E47)/2)*10000,"") | J47: =IF(N(D47)>0,IFERROR(D47/INDEX(Feed!$G:$G,$AG47)-1,""),"") -> 0.0037444934 | K47: =IFERROR(IF(INDEX(Feed!$H:$H,$AG47)="","",INDEX(Feed!$H:$H,$AG47)),"") -> 8833521 | L47: =IFERROR(IF(INDEX(Feed!$I:$I,$AG47)="","",INDEX(Feed!$I:$I,$AG47)),"") | M47: =IF(AND(N(K47)>0,N(L47)>0),K47/L47,"") | N47: =IFERROR(IF(INDEX(Feed!$L:$L,$AG47)="","",INDEX(Feed!$L:$L,$AG47)),"") -> 0.0029743916 | O47: =IF(AND(ISNUMBER(J47),N(N47)>0),J47/N47,"") -> 1.2589107 | P47: =IF(ISNUMBER(O47),IF(SessionLeft<=0,--(ABS(O47)>1),_xlfn.NORM.S.DIST((-1-O47)/SQRT(SessionLeft),TRUE)+1-_xlfn.NORM.S.DIST((1-O47)/SQRT(SessionLeft),TRUE)),"") -> 1 | Q47: =IF(ISNUMBER(O47),IF(SessionLeft<=0,--(ABS(O47)>2),_xlfn.NORM.S.DIST((-2-O47)/SQRT(SessionLeft),TRUE)+1-_xlfn.NORM.S.DIST((2-O47)/SQRT(SessionLeft),TRUE)),"") -> 0 | R47: =IF(ISNUMBER(O47),IF(SessionLeft<=0,--(ABS(O47)>3),_xlfn.NORM.S.DIST((-3-O47)/SQRT(SessionLeft),TRUE)+1-_xlfn.NORM.S.DIST((3-O47)/SQRT(SessionLeft),TRUE)),"") -> 0 | AB47: =IFERROR(IF(INDEX(Feed!$M:$M,$AG47)="","",INDEX(Feed!$M:$M,$AG47)),"") -> 46287.671 | AD47: IEF | AE47: Underlying | AF47: FI | AG47: =IFERROR(MATCH($AD47,Feed!$A:$A,0),"") -> 11
A48: HYG | B48: =IF(NOT(ISNUMBER(V48)),"",IF((NOW()-N(AB48))*1440>StaleMin,"STALE",IF(AND($AF48="EQUITY",ABS(N(T48))>ExDivFlag),"EX-DIV?",IF(X48>IF($AF48="FI",EdgeFI,EdgeEq),"SELL ETF / BUY "&UPPER($A$49),IF(Y48>IF($AF48="FI",EdgeFI,EdgeEq),"BUY ETF / SELL "&UPPER($A$49),""))))) -> STALE | C48: =IFERROR(IF(INDEX(Feed!$N:$N,$AG48)="","",INDEX(Feed!$N:$N,$AG48)),"") -> 1.014561 | D48: =IFERROR(IF(INDEX(Feed!$B:$B,$AG48)="","",INDEX(Feed!$B:$B,$AG48)),"") -> 78.67 | E48: =IFERROR(IF(INDEX(Feed!$C:$C,$AG48)="","",INDEX(Feed!$C:$C,$AG48)),"") | F48: =IFERROR(IF(INDEX(Feed!$D:$D,$AG48)="","",INDEX(Feed!$D:$D,$AG48)),"") | G48: =IFERROR(IF(INDEX(Feed!$E:$E,$AG48)="","",INDEX(Feed!$E:$E,$AG48)),"") | H48: =IFERROR(IF(INDEX(Feed!$F:$F,$AG48)="","",INDEX(Feed!$F:$F,$AG48)),"") | I48: =IF(AND(N(E48)>0,N(F48)>0),(F48-E48)/((F48+E48)/2)*10000,"") | J48: =IF(N(D48)>0,IFERROR(D48/INDEX(Feed!$G:$G,$AG48)-1,""),"") -> 0.0017827582 | K48: =IFERROR(IF(INDEX(Feed!$H:$H,$AG48)="","",INDEX(Feed!$H:$H,$AG48)),"") -> 44495821 | L48: =IFERROR(IF(INDEX(Feed!$I:$I,$AG48)="","",INDEX(Feed!$I:$I,$AG48)),"") | M48: =IF(AND(N(K48)>0,N(L48)>0),K48/L48,"") | N48: =IFERROR(IF(INDEX(Feed!$L:$L,$AG48)="","",INDEX(Feed!$L:$L,$AG48)),"") -> 0.0017903913 | O48: =IF(AND(ISNUMBER(J48),N(N48)>0),J48/N48,"") -> 0.99573659 | P48: =IF(ISNUMBER(O48),IF(SessionLeft<=0,--(ABS(O48)>1),_xlfn.NORM.S.DIST((-1-O48)/SQRT(SessionLeft),TRUE)+1-_xlfn.NORM.S.DIST((1-O48)/SQRT(SessionLeft),TRUE)),"") -> 0 | Q48: =IF(ISNUMBER(O48),IF(SessionLeft<=0,--(ABS(O48)>2),_xlfn.NORM.S.DIST((-2-O48)/SQRT(SessionLeft),TRUE)+1-_xlfn.NORM.S.DIST((2-O48)/SQRT(SessionLeft),TRUE)),"") -> 0 | R48: =IF(ISNUMBER(O48),IF(SessionLeft<=0,--(ABS(O48)>3),_xlfn.NORM.S.DIST((-3-O48)/SQRT(SessionLeft),TRUE)+1-_xlfn.NORM.S.DIST((3-O48)/SQRT(SessionLeft),TRUE)),"") -> 0 | S48: =IFERROR(IF(INDEX(Feed!$J:$J,$AG48)="","",INDEX(Feed!$J:$J,$AG48)),"") -> 78.42535 | T48: =IFERROR(IF(N(S48)>0,(INDEX(Feed!$G:$G,$AG48)/S48-1)*10000,""),"") -> 13.3439 | U48: =IFERROR(C48*$J$49,"") -> 0.001824171 | V48: =IF(ISNUMBER(U48),IF(AND(Anchor="NAV",N(S48)>0),S48,INDEX(Feed!$G:$G,$AG48))*(1+U48),"") -> 78.673252 | W48: =IF(ISNUMBER(V48),(IF(AND(N(E48)>0,N(F48)>0),(E48+F48)/2,D48)/V48-1)*10000,"") -> -0.41337404 | X48: =IF(ISNUMBER(V48),(IF(N(E48)>0,E48,D48)/V48-1)*10000-IF($AF48="FI",CostFI,CostEq),"") -> -8.413374 | Y48: =IF(ISNUMBER(V48),(1-IF(N(F48)>0,F48,D48)/V48)*10000-IF($AF48="FI",CostFI,CostEq),"") -> -7.586626 | Z48: =IFERROR((J48-U48-INDEX(Feed!$O:$O,$AG48))/INDEX(Feed!$P:$P,$AG48),"") -> -0.12036607 | AA48: =IFERROR(IF(INDEX(Feed!$K:$K,$AG48)="","",INDEX(Feed!$K:$K,$AG48)),"") -> 0.0588 | AB48: =IFERROR(IF(INDEX(Feed!$M:$M,$AG48)="","",INDEX(Feed!$M:$M,$AG48)),"") -> 46287.671 | AD48: HYG | AE48: ETF | AF48: FI | AG48: =IFERROR(MATCH($AD48,Feed!$A:$A,0),"") -> 15
A49: JNK | D49: =IFERROR(IF(INDEX(Feed!$B:$B,$AG49)="","",INDEX(Feed!$B:$B,$AG49)),"") -> 94.72 | E49: =IFERROR(IF(INDEX(Feed!$C:$C,$AG49)="","",INDEX(Feed!$C:$C,$AG49)),"") | F49: =IFERROR(IF(INDEX(Feed!$D:$D,$AG49)="","",INDEX(Feed!$D:$D,$AG49)),"") | G49: =IFERROR(IF(INDEX(Feed!$E:$E,$AG49)="","",INDEX(Feed!$E:$E,$AG49)),"") | H49: =IFERROR(IF(INDEX(Feed!$F:$F,$AG49)="","",INDEX(Feed!$F:$F,$AG49)),"") | I49: =IF(AND(N(E49)>0,N(F49)>0),(F49-E49)/((F49+E49)/2)*10000,"") | J49: =IF(N(D49)>0,IFERROR(D49/INDEX(Feed!$G:$G,$AG49)-1,""),"") -> 0.0017979905 | K49: =IFERROR(IF(INDEX(Feed!$H:$H,$AG49)="","",INDEX(Feed!$H:$H,$AG49)),"") -> 1305555 | L49: =IFERROR(IF(INDEX(Feed!$I:$I,$AG49)="","",INDEX(Feed!$I:$I,$AG49)),"") | M49: =IF(AND(N(K49)>0,N(L49)>0),K49/L49,"") | N49: =IFERROR(IF(INDEX(Feed!$L:$L,$AG49)="","",INDEX(Feed!$L:$L,$AG49)),"") -> 0.0017315538 | O49: =IF(AND(ISNUMBER(J49),N(N49)>0),J49/N49,"") -> 1.0383682 | P49: =IF(ISNUMBER(O49),IF(SessionLeft<=0,--(ABS(O49)>1),_xlfn.NORM.S.DIST((-1-O49)/SQRT(SessionLeft),TRUE)+1-_xlfn.NORM.S.DIST((1-O49)/SQRT(SessionLeft),TRUE)),"") -> 1 | Q49: =IF(ISNUMBER(O49),IF(SessionLeft<=0,--(ABS(O49)>2),_xlfn.NORM.S.DIST((-2-O49)/SQRT(SessionLeft),TRUE)+1-_xlfn.NORM.S.DIST((2-O49)/SQRT(SessionLeft),TRUE)),"") -> 0 | R49: =IF(ISNUMBER(O49),IF(SessionLeft<=0,--(ABS(O49)>3),_xlfn.NORM.S.DIST((-3-O49)/SQRT(SessionLeft),TRUE)+1-_xlfn.NORM.S.DIST((3-O49)/SQRT(SessionLeft),TRUE)),"") -> 0 | AB49: =IFERROR(IF(INDEX(Feed!$M:$M,$AG49)="","",INDEX(Feed!$M:$M,$AG49)),"") -> 46287.671 | AD49: JNK | AE49: Underlying | AF49: FI | AG49: =IFERROR(MATCH($AD49,Feed!$A:$A,0),"") -> 291
A50: AGG | B50: =IF(NOT(ISNUMBER(V50)),"",IF((NOW()-N(AB50))*1440>StaleMin,"STALE",IF(AND($AF50="EQUITY",ABS(N(T50))>ExDivFlag),"EX-DIV?",IF(X50>IF($AF50="FI",EdgeFI,EdgeEq),"SELL ETF / BUY "&UPPER($A$51),IF(Y50>IF($AF50="FI",EdgeFI,EdgeEq),"BUY ETF / SELL "&UPPER($A$51),""))))) -> STALE | C50: =IFERROR(IF(INDEX(Feed!$N:$N,$AG50)="","",INDEX(Feed!$N:$N,$AG50)),"") -> 1.0340765 | D50: =IFERROR(IF(INDEX(Feed!$B:$B,$AG50)="","",INDEX(Feed!$B:$B,$AG50)),"") -> 96.25 | E50: =IFERROR(IF(INDEX(Feed!$C:$C,$AG50)="","",INDEX(Feed!$C:$C,$AG50)),"") -> 96 | F50: =IFERROR(IF(INDEX(Feed!$D:$D,$AG50)="","",INDEX(Feed!$D:$D,$AG50)),"") -> 97.26 | G50: =IFERROR(IF(INDEX(Feed!$E:$E,$AG50)="","",INDEX(Feed!$E:$E,$AG50)),"") -> 100 | H50: =IFERROR(IF(INDEX(Feed!$F:$F,$AG50)="","",INDEX(Feed!$F:$F,$AG50)),"") -> 50 | I50: =IF(AND(N(E50)>0,N(F50)>0),(F50-E50)/((F50+E50)/2)*10000,"") -> 130.39429 | J50: =IF(N(D50)>0,IFERROR(D50/INDEX(Feed!$G:$G,$AG50)-1,""),"") -> 0.0030220925 | K50: =IFERROR(IF(INDEX(Feed!$H:$H,$AG50)="","",INDEX(Feed!$H:$H,$AG50)),"") -> 9197633 | L50: =IFERROR(IF(INDEX(Feed!$I:$I,$AG50)="","",INDEX(Feed!$I:$I,$AG50)),"") | M50: =IF(AND(N(K50)>0,N(L50)>0),K50/L50,"") | N50: =IFERROR(IF(INDEX(Feed!$L:$L,$AG50)="","",INDEX(Feed!$L:$L,$AG50)),"") -> 0.0025338951 | O50: =IF(AND(ISNUMBER(J50),N(N50)>0),J50/N50,"") -> 1.1926668 | P50: =IF(ISNUMBER(O50),IF(SessionLeft<=0,--(ABS(O50)>1),_xlfn.NORM.S.DIST((-1-O50)/SQRT(SessionLeft),TRUE)+1-_xlfn.NORM.S.DIST((1-O50)/SQRT(SessionLeft),TRUE)),"") -> 1 | Q50: =IF(ISNUMBER(O50),IF(SessionLeft<=0,--(ABS(O50)>2),_xlfn.NORM.S.DIST((-2-O50)/SQRT(SessionLeft),TRUE)+1-_xlfn.NORM.S.DIST((2-O50)/SQRT(SessionLeft),TRUE)),"") -> 0 | R50: =IF(ISNUMBER(O50),IF(SessionLeft<=0,--(ABS(O50)>3),_xlfn.NORM.S.DIST((-3-O50)/SQRT(SessionLeft),TRUE)+1-_xlfn.NORM.S.DIST((3-O50)/SQRT(SessionLeft),TRUE)),"") -> 0 | S50: =IFERROR(IF(INDEX(Feed!$J:$J,$AG50)="","",INDEX(Feed!$J:$J,$AG50)),"") -> 95.90445 | T50: =IFERROR(IF(N(S50)>0,(INDEX(Feed!$G:$G,$AG50)/S50-1)*10000,""),"") -> 5.7922234 | U50: =IFERROR(C50*$J$51,"") -> 0.0030499446 | V50: =IF(ISNUMBER(U50),IF(AND(Anchor="NAV",N(S50)>0),S50,INDEX(Feed!$G:$G,$AG50))*(1+U50),"") -> 96.252673 | W50: =IF(ISNUMBER(V50),(IF(AND(N(E50)>0,N(F50)>0),(E50+F50)/2,D50)/V50-1)*10000,"") -> 39.201749 | X50: =IF(ISNUMBER(V50),(IF(N(E50)>0,E50,D50)/V50-1)*10000-IF($AF50="FI",CostFI,CostEq),"") -> -34.250979 | Y50: =IF(ISNUMBER(V50),(1-IF(N(F50)>0,F50,D50)/V50)*10000-IF($AF50="FI",CostFI,CostEq),"") -> -112.65448 | Z50: =IFERROR((J50-U50-INDEX(Feed!$O:$O,$AG50))/INDEX(Feed!$P:$P,$AG50),"") -> -0.11823838 | AA50: =IFERROR(IF(INDEX(Feed!$K:$K,$AG50)="","",INDEX(Feed!$K:$K,$AG50)),"") -> 0.0405 | AB50: =IFERROR(IF(INDEX(Feed!$M:$M,$AG50)="","",INDEX(Feed!$M:$M,$AG50)),"") -> 46287.673 | AD50: AGG | AE50: ETF | AF50: FI | AG50: =IFERROR(MATCH($AD50,Feed!$A:$A,0),"") -> 16
A51: BND | D51: =IFERROR(IF(INDEX(Feed!$B:$B,$AG51)="","",INDEX(Feed!$B:$B,$AG51)),"") -> 71.41 | E51: =IFERROR(IF(INDEX(Feed!$C:$C,$AG51)="","",INDEX(Feed!$C:$C,$AG51)),"") | F51: =IFERROR(IF(INDEX(Feed!$D:$D,$AG51)="","",INDEX(Feed!$D:$D,$AG51)),"") | G51: =IFERROR(IF(INDEX(Feed!$E:$E,$AG51)="","",INDEX(Feed!$E:$E,$AG51)),"") | H51: =IFERROR(IF(INDEX(Feed!$F:$F,$AG51)="","",INDEX(Feed!$F:$F,$AG51)),"") | I51: =IF(AND(N(E51)>0,N(F51)>0),(F51-E51)/((F51+E51)/2)*10000,"") | J51: =IF(N(D51)>0,IFERROR(D51/INDEX(Feed!$G:$G,$AG51)-1,""),"") -> 0.0029494382 | K51: =IFERROR(IF(INDEX(Feed!$H:$H,$AG51)="","",INDEX(Feed!$H:$H,$AG51)),"") -> 7596009 | L51: =IFERROR(IF(INDEX(Feed!$I:$I,$AG51)="","",INDEX(Feed!$I:$I,$AG51)),"") | M51: =IF(AND(N(K51)>0,N(L51)>0),K51/L51,"") | N51: =IFERROR(IF(INDEX(Feed!$L:$L,$AG51)="","",INDEX(Feed!$L:$L,$AG51)),"") -> 0.0024393467 | O51: =IF(AND(ISNUMBER(J51),N(N51)>0),J51/N51,"") -> 1.2091099 | P51: =IF(ISNUMBER(O51),IF(SessionLeft<=0,--(ABS(O51)>1),_xlfn.NORM.S.DIST((-1-O51)/SQRT(SessionLeft),TRUE)+1-_xlfn.NORM.S.DIST((1-O51)/SQRT(SessionLeft),TRUE)),"") -> 1 | Q51: =IF(ISNUMBER(O51),IF(SessionLeft<=0,--(ABS(O51)>2),_xlfn.NORM.S.DIST((-2-O51)/SQRT(SessionLeft),TRUE)+1-_xlfn.NORM.S.DIST((2-O51)/SQRT(SessionLeft),TRUE)),"") -> 0 | R51: =IF(ISNUMBER(O51),IF(SessionLeft<=0,--(ABS(O51)>3),_xlfn.NORM.S.DIST((-3-O51)/SQRT(SessionLeft),TRUE)+1-_xlfn.NORM.S.DIST((3-O51)/SQRT(SessionLeft),TRUE)),"") -> 0 | AB51: =IFERROR(IF(INDEX(Feed!$M:$M,$AG51)="","",INDEX(Feed!$M:$M,$AG51)),"") -> 46287.671 | AD51: BND | AE51: Underlying | AF51: FI | AG51: =IFERROR(MATCH($AD51,Feed!$A:$A,0),"") -> 88
A52: TIP | B52: =IF(NOT(ISNUMBER(V52)),"",IF((NOW()-N(AB52))*1440>StaleMin,"STALE",IF(AND($AF52="EQUITY",ABS(N(T52))>ExDivFlag),"EX-DIV?",IF(X52>IF($AF52="FI",EdgeFI,EdgeEq),"SELL ETF / BUY "&UPPER($A$53),IF(Y52>IF($AF52="FI",EdgeFI,EdgeEq),"BUY ETF / SELL "&UPPER($A$53),""))))) -> STALE | C52: =IFERROR(IF(INDEX(Feed!$N:$N,$AG52)="","",INDEX(Feed!$N:$N,$AG52)),"") -> 0.99680542 | D52: =IFERROR(IF(INDEX(Feed!$B:$B,$AG52)="","",INDEX(Feed!$B:$B,$AG52)),"") -> 105.55 | E52: =IFERROR(IF(INDEX(Feed!$C:$C,$AG52)="","",INDEX(Feed!$C:$C,$AG52)),"") -> 105.55 | F52: =IFERROR(IF(INDEX(Feed!$D:$D,$AG52)="","",INDEX(Feed!$D:$D,$AG52)),"") -> 105.57 | G52: =IFERROR(IF(INDEX(Feed!$E:$E,$AG52)="","",INDEX(Feed!$E:$E,$AG52)),"") -> 11506 | H52: =IFERROR(IF(INDEX(Feed!$F:$F,$AG52)="","",INDEX(Feed!$F:$F,$AG52)),"") -> 400 | I52: =IF(AND(N(E52)>0,N(F52)>0),(F52-E52)/((F52+E52)/2)*10000,"") -> 1.8946571 | J52: =IF(N(D52)>0,IFERROR(D52/INDEX(Feed!$G:$G,$AG52)-1,""),"") -> 0.0026598271 | K52: =IFERROR(IF(INDEX(Feed!$H:$H,$AG52)="","",INDEX(Feed!$H:$H,$AG52)),"") -> 1757608 | L52: =IFERROR(IF(INDEX(Feed!$I:$I,$AG52)="","",INDEX(Feed!$I:$I,$AG52)),"") | M52: =IF(AND(N(K52)>0,N(L52)>0),K52/L52,"") | N52: =IFERROR(IF(INDEX(Feed!$L:$L,$AG52)="","",INDEX(Feed!$L:$L,$AG52)),"") -> 0.0021936613 | O52: =IF(AND(ISNUMBER(J52),N(N52)>0),J52/N52,"") -> 1.2125058 | P52: =IF(ISNUMBER(O52),IF(SessionLeft<=0,--(ABS(O52)>1),_xlfn.NORM.S.DIST((-1-O52)/SQRT(SessionLeft),TRUE)+1-_xlfn.NORM.S.DIST((1-O52)/SQRT(SessionLeft),TRUE)),"") -> 1 | Q52: =IF(ISNUMBER(O52),IF(SessionLeft<=0,--(ABS(O52)>2),_xlfn.NORM.S.DIST((-2-O52)/SQRT(SessionLeft),TRUE)+1-_xlfn.NORM.S.DIST((2-O52)/SQRT(SessionLeft),TRUE)),"") -> 0 | R52: =IF(ISNUMBER(O52),IF(SessionLeft<=0,--(ABS(O52)>3),_xlfn.NORM.S.DIST((-3-O52)/SQRT(SessionLeft),TRUE)+1-_xlfn.NORM.S.DIST((3-O52)/SQRT(SessionLeft),TRUE)),"") -> 0 | S52: =IFERROR(IF(INDEX(Feed!$J:$J,$AG52)="","",INDEX(Feed!$J:$J,$AG52)),"") -> 105.26104 | T52: =IFERROR(IF(N(S52)>0,(INDEX(Feed!$G:$G,$AG52)/S52-1)*10000,""),"") -> 0.85121713 | U52: =IFERROR(C52*$J$53,"") -> 0.0031346082 | V52: =IF(ISNUMBER(U52),IF(AND(Anchor="NAV",N(S52)>0),S52,INDEX(Feed!$G:$G,$AG52))*(1+U52),"") -> 105.59998 | W52: =IF(ISNUMBER(V52),(IF(AND(N(E52)>0,N(F52)>0),(E52+F52)/2,D52)/V52-1)*10000,"") -> -3.7860054 | X52: =IF(ISNUMBER(V52),(IF(N(E52)>0,E52,D52)/V52-1)*10000-IF($AF52="FI",CostFI,CostEq),"") -> -12.732975 | Y52: =IF(ISNUMBER(V52),(1-IF(N(F52)>0,F52,D52)/V52)*10000-IF($AF52="FI",CostFI,CostEq),"") -> -5.1609645 | Z52: =IFERROR((J52-U52-INDEX(Feed!$O:$O,$AG52))/INDEX(Feed!$P:$P,$AG52),"") -> -1.2564041 | AA52: =IFERROR(IF(INDEX(Feed!$K:$K,$AG52)="","",INDEX(Feed!$K:$K,$AG52)),"") -> 0.0498 | AB52: =IFERROR(IF(INDEX(Feed!$M:$M,$AG52)="","",INDEX(Feed!$M:$M,$AG52)),"") -> 46287.672 | AD52: TIP | AE52: ETF | AF52: FI | AG52: =IFERROR(MATCH($AD52,Feed!$A:$A,0),"") -> 17
A53: SCHP | D53: =IFERROR(IF(INDEX(Feed!$B:$B,$AG53)="","",INDEX(Feed!$B:$B,$AG53)),"") -> 25.52 | E53: =IFERROR(IF(INDEX(Feed!$C:$C,$AG53)="","",INDEX(Feed!$C:$C,$AG53)),"") -> 25.51 | F53: =IFERROR(IF(INDEX(Feed!$D:$D,$AG53)="","",INDEX(Feed!$D:$D,$AG53)),"") -> 25.52 | G53: =IFERROR(IF(INDEX(Feed!$E:$E,$AG53)="","",INDEX(Feed!$E:$E,$AG53)),"") -> 1500 | H53: =IFERROR(IF(INDEX(Feed!$F:$F,$AG53)="","",INDEX(Feed!$F:$F,$AG53)),"") -> 70385 | I53: =IF(AND(N(E53)>0,N(F53)>0),(F53-E53)/((F53+E53)/2)*10000,"") -> 3.9192632 | J53: =IF(N(D53)>0,IFERROR(D53/INDEX(Feed!$G:$G,$AG53)-1,""),"") -> 0.0031446541 | K53: =IFERROR(IF(INDEX(Feed!$H:$H,$AG53)="","",INDEX(Feed!$H:$H,$AG53)),"") -> 5560989 | L53: =IFERROR(IF(INDEX(Feed!$I:$I,$AG53)="","",INDEX(Feed!$I:$I,$AG53)),"") | M53: =IF(AND(N(K53)>0,N(L53)>0),K53/L53,"") | N53: =IFERROR(IF(INDEX(Feed!$L:$L,$AG53)="","",INDEX(Feed!$L:$L,$AG53)),"") -> 0.0021269905 | O53: =IF(AND(ISNUMBER(J53),N(N53)>0),J53/N53,"") -> 1.4784524 | P53: =IF(ISNUMBER(O53),IF(SessionLeft<=0,--(ABS(O53)>1),_xlfn.NORM.S.DIST((-1-O53)/SQRT(SessionLeft),TRUE)+1-_xlfn.NORM.S.DIST((1-O53)/SQRT(SessionLeft),TRUE)),"") -> 1 | Q53: =IF(ISNUMBER(O53),IF(SessionLeft<=0,--(ABS(O53)>2),_xlfn.NORM.S.DIST((-2-O53)/SQRT(SessionLeft),TRUE)+1-_xlfn.NORM.S.DIST((2-O53)/SQRT(SessionLeft),TRUE)),"") -> 0 | R53: =IF(ISNUMBER(O53),IF(SessionLeft<=0,--(ABS(O53)>3),_xlfn.NORM.S.DIST((-3-O53)/SQRT(SessionLeft),TRUE)+1-_xlfn.NORM.S.DIST((3-O53)/SQRT(SessionLeft),TRUE)),"") -> 0 | AB53: =IFERROR(IF(INDEX(Feed!$M:$M,$AG53)="","",INDEX(Feed!$M:$M,$AG53)),"") -> 46287.683 | AD53: SCHP | AE53: Underlying | AF53: FI | AG53: =IFERROR(MATCH($AD53,Feed!$A:$A,0),"") -> 440
A54: MUB | B54: =IF(NOT(ISNUMBER(V54)),"",IF((NOW()-N(AB54))*1440>StaleMin,"STALE",IF(AND($AF54="EQUITY",ABS(N(T54))>ExDivFlag),"EX-DIV?",IF(X54>IF($AF54="FI",EdgeFI,EdgeEq),"SELL ETF / BUY "&UPPER($A$55),IF(Y54>IF($AF54="FI",EdgeFI,EdgeEq),"BUY ETF / SELL "&UPPER($A$55),""))))) -> STALE | C54: =IFERROR(IF(INDEX(Feed!$N:$N,$AG54)="","",INDEX(Feed!$N:$N,$AG54)),"") -> 1.0208871 | D54: =IFERROR(IF(INDEX(Feed!$B:$B,$AG54)="","",INDEX(Feed!$B:$B,$AG54)),"") -> 102.75 | E54: =IFERROR(IF(INDEX(Feed!$C:$C,$AG54)="","",INDEX(Feed!$C:$C,$AG54)),"") | F54: =IFERROR(IF(INDEX(Feed!$D:$D,$AG54)="","",INDEX(Feed!$D:$D,$AG54)),"") | G54: =IFERROR(IF(INDEX(Feed!$E:$E,$AG54)="","",INDEX(Feed!$E:$E,$AG54)),"") | H54: =IFERROR(IF(INDEX(Feed!$F:$F,$AG54)="","",INDEX(Feed!$F:$F,$AG54)),"") | I54: =IF(AND(N(E54)>0,N(F54)>0),(F54-E54)/((F54+E54)/2)*10000,"") | J54: =IF(N(D54)>0,IFERROR(D54/INDEX(Feed!$G:$G,$AG54)-1,""),"") -> -0.0012636081 | K54: =IFERROR(IF(INDEX(Feed!$H:$H,$AG54)="","",INDEX(Feed!$H:$H,$AG54)),"") -> 8743685 | L54: =IFERROR(IF(INDEX(Feed!$I:$I,$AG54)="","",INDEX(Feed!$I:$I,$AG54)),"") | M54: =IF(AND(N(K54)>0,N(L54)>0),K54/L54,"") | N54: =IFERROR(IF(INDEX(Feed!$L:$L,$AG54)="","",INDEX(Feed!$L:$L,$AG54)),"") -> 0.0022422134 | O54: =IF(AND(ISNUMBER(J54),N(N54)>0),J54/N54,"") -> -0.56355389 | P54: =IF(ISNUMBER(O54),IF(SessionLeft<=0,--(ABS(O54)>1),_xlfn.NORM.S.DIST((-1-O54)/SQRT(SessionLeft),TRUE)+1-_xlfn.NORM.S.DIST((1-O54)/SQRT(SessionLeft),TRUE)),"") -> 0 | Q54: =IF(ISNUMBER(O54),IF(SessionLeft<=0,--(ABS(O54)>2),_xlfn.NORM.S.DIST((-2-O54)/SQRT(SessionLeft),TRUE)+1-_xlfn.NORM.S.DIST((2-O54)/SQRT(SessionLeft),TRUE)),"") -> 0 | R54: =IF(ISNUMBER(O54),IF(SessionLeft<=0,--(ABS(O54)>3),_xlfn.NORM.S.DIST((-3-O54)/SQRT(SessionLeft),TRUE)+1-_xlfn.NORM.S.DIST((3-O54)/SQRT(SessionLeft),TRUE)),"") -> 0 | S54: =IFERROR(IF(INDEX(Feed!$J:$J,$AG54)="","",INDEX(Feed!$J:$J,$AG54)),"") -> 102.63043 | T54: =IFERROR(IF(N(S54)>0,(INDEX(Feed!$G:$G,$AG54)/S54-1)*10000,""),"") -> 24.317349 | U54: =IFERROR(C54*$J$55,"") -> 0.0050769713 | V54: =IF(ISNUMBER(U54),IF(AND(Anchor="NAV",N(S54)>0),S54,INDEX(Feed!$G:$G,$AG54))*(1+U54),"") -> 103.40232 | W54: =IF(ISNUMBER(V54),(IF(AND(N(E54)>0,N(F54)>0),(E54+F54)/2,D54)/V54-1)*10000,"") -> -63.085511 | X54: =IF(ISNUMBER(V54),(IF(N(E54)>0,E54,D54)/V54-1)*10000-IF($AF54="FI",CostFI,CostEq),"") -> -71.085511 | Y54: =IF(ISNUMBER(V54),(1-IF(N(F54)>0,F54,D54)/V54)*10000-IF($AF54="FI",CostFI,CostEq),"") -> 55.085511 | Z54: =IFERROR((J54-U54-INDEX(Feed!$O:$O,$AG54))/INDEX(Feed!$P:$P,$AG54),"") -> -13.475062 | AA54: =IFERROR(IF(INDEX(Feed!$K:$K,$AG54)="","",INDEX(Feed!$K:$K,$AG54)),"") -> 0.0325 | AB54: =IFERROR(IF(INDEX(Feed!$M:$M,$AG54)="","",INDEX(Feed!$M:$M,$AG54)),"") -> 46287.671 | AD54: MUB | AE54: ETF | AF54: FI | AG54: =IFERROR(MATCH($AD54,Feed!$A:$A,0),"") -> 18
A55: VTEB | D55: =IFERROR(IF(INDEX(Feed!$B:$B,$AG55)="","",INDEX(Feed!$B:$B,$AG55)),"") -> 48.5 | E55: =IFERROR(IF(INDEX(Feed!$C:$C,$AG55)="","",INDEX(Feed!$C:$C,$AG55)),"") -> 48.18 | F55: =IFERROR(IF(INDEX(Feed!$D:$D,$AG55)="","",INDEX(Feed!$D:$D,$AG55)),"") -> 52.64 | G55: =IFERROR(IF(INDEX(Feed!$E:$E,$AG55)="","",INDEX(Feed!$E:$E,$AG55)),"") -> 2 | H55: =IFERROR(IF(INDEX(Feed!$F:$F,$AG55)="","",INDEX(Feed!$F:$F,$AG55)),"") -> 100 | I55: =IF(AND(N(E55)>0,N(F55)>0),(F55-E55)/((F55+E55)/2)*10000,"") -> 884.74509 | J55: =IF(N(D55)>0,IFERROR(D55/INDEX(Feed!$G:$G,$AG55)-1,""),"") -> 0.0049730975 | K55: =IFERROR(IF(INDEX(Feed!$H:$H,$AG55)="","",INDEX(Feed!$H:$H,$AG55)),"") | L55: =IFERROR(IF(INDEX(Feed!$I:$I,$AG55)="","",INDEX(Feed!$I:$I,$AG55)),"") | M55: =IF(AND(N(K55)>0,N(L55)>0),K55/L55,"") | N55: =IFERROR(IF(INDEX(Feed!$L:$L,$AG55)="","",INDEX(Feed!$L:$L,$AG55)),"") -> 0.0021741427 | O55: =IF(AND(ISNUMBER(J55),N(N55)>0),J55/N55,"") -> 2.2873833 | P55: =IF(ISNUMBER(O55),IF(SessionLeft<=0,--(ABS(O55)>1),_xlfn.NORM.S.DIST((-1-O55)/SQRT(SessionLeft),TRUE)+1-_xlfn.NORM.S.DIST((1-O55)/SQRT(SessionLeft),TRUE)),"") -> 1 | Q55: =IF(ISNUMBER(O55),IF(SessionLeft<=0,--(ABS(O55)>2),_xlfn.NORM.S.DIST((-2-O55)/SQRT(SessionLeft),TRUE)+1-_xlfn.NORM.S.DIST((2-O55)/SQRT(SessionLeft),TRUE)),"") -> 1 | R55: =IF(ISNUMBER(O55),IF(SessionLeft<=0,--(ABS(O55)>3),_xlfn.NORM.S.DIST((-3-O55)/SQRT(SessionLeft),TRUE)+1-_xlfn.NORM.S.DIST((3-O55)/SQRT(SessionLeft),TRUE)),"") -> 0 | AB55: =IFERROR(IF(INDEX(Feed!$M:$M,$AG55)="","",INDEX(Feed!$M:$M,$AG55)),"") -> 46287.683 | AD55: VTEB | AE55: Underlying | AF55: FI | AG55: =IFERROR(MATCH($AD55,Feed!$A:$A,0),"") -> 529

Sheet Universe
A1: ETF | B1: Class | C1: Model | D1: Underlying | E1: Leverage | F1: Peers | G1: Holdings Source | H1: Active
A2: SPY | B2: EQUITY | C2: BASKET | F2: IVV,VOO | G2: SPDR | H2: Y
A3: QQQ | B3: EQUITY | C3: BASKET | F3: QQQM | G3: INVESCO | H3: Y
A4: XLK | B4: EQUITY | C4: BASKET | F4: VGT | G4: SPDR | H4: Y
A5: XLF | B5: EQUITY | C5: BASKET | F5: VFH | G5: SPDR | H5: Y
A6: XLE | B6: EQUITY | C6: BASKET | F6: VDE | G6: SPDR | H6: Y
A7: XLV | B7: EQUITY | C7: BASKET | F7: VHT | G7: SPDR | H7: Y
A8: IWM | B8: EQUITY | C8: PROXY | D8: VTWO | F8: VTWO | H8: Y
A9: AAPU | B9: EQUITY | C9: PROXY | D9: AAPL | E9: 2 | H9: Y
A10: TLT | B10: FI | C10: PROXY | D10: VGLT | F10: VGLT,SPTL | H10: Y
A11: IEF | B11: FI | C11: PROXY | D11: VGIT | F11: VGIT,SCHR | H11: Y
A12: SHY | B12: FI | C12: PROXY | D12: VGSH | F12: VGSH,SCHO | H12: Y
A13: LQD | B13: FI | C13: PROXY | D13: IEF | F13: VCIT,IGIB | H13: Y
A14: VCIT | B14: FI | C14: PROXY | D14: IEF | F14: IGIB | H14: Y
A15: HYG | B15: FI | C15: PROXY | D15: JNK | F15: JNK,USHY | H15: Y
A16: AGG | B16: FI | C16: PROXY | D16: BND | F16: BND,SCHZ | H16: Y
A17: TIP | B17: FI | C17: PROXY | D17: SCHP | F17: SCHP,SPIP | H17: Y
A18: MUB | B18: FI | C18: PROXY | D18: VTEB | F18: VTEB | H18: Y

Sheet Holdings
A1: ETF | B1: Symbol | C1: Name | D1: Weight | E1: Chg % | F1: Contribution | G1: Priced Wt | H1: Source | I1: As Of
A2: SPY | B2: NVDA | C2: NVIDIA CORP | D2: 0.08276795 | E2: =IFERROR(_xlfn.LET(_xlpm.m,MATCH($B2,Feed!$A:$A,0),_xlpm.p,INDEX(Feed!$B:$B,_xlpm.m),_xlpm.c,INDEX(Feed!$G:$G,_xlpm.m),IF(AND(_xlpm.p>0,_xlpm.c>0),_xlpm.p/_xlpm.c-1,"")),"") -> 0.027525982 | F2: =IF(ISNUMBER(E2),D2*E2,0) -> 0.0022782691 | G2: =IF(ISNUMBER(E2),D2,0) -> 0.08276795 | H2: SPDR | I2: 46288
A3: SPY | B3: AAPL | C3: APPLE INC | D3: 0.07409622 | E3: =IFERROR(_xlfn.LET(_xlpm.m,MATCH($B3,Feed!$A:$A,0),_xlpm.p,INDEX(Feed!$B:$B,_xlpm.m),_xlpm.c,INDEX(Feed!$G:$G,_xlpm.m),IF(AND(_xlpm.p>0,_xlpm.c>0),_xlpm.p/_xlpm.c-1,"")),"") | F3: =IF(ISNUMBER(E3),D3*E3,0) -> 0 | G3: =IF(ISNUMBER(E3),D3,0) -> 0 | H3: SPDR | I3: 46288
A4: SPY | B4: MSFT | C4: MICROSOFT CORP | D4: 0.05525998 | E4: =IFERROR(_xlfn.LET(_xlpm.m,MATCH($B4,Feed!$A:$A,0),_xlpm.p,INDEX(Feed!$B:$B,_xlpm.m),_xlpm.c,INDEX(Feed!$G:$G,_xlpm.m),IF(AND(_xlpm.p>0,_xlpm.c>0),_xlpm.p/_xlpm.c-1,"")),"") -> -0.007530751 | F4: =IF(ISNUMBER(E4),D4*E4,0) -> -0.00041614915 | G4: =IF(ISNUMBER(E4),D4,0) -> 0.05525998 | H4: SPDR | I4: 46288
A5: SPY | B5: AMZN | C5: AMAZON.COM INC | D5: 0.03740151 | E5: =IFERROR(_xlfn.LET(_xlpm.m,MATCH($B5,Feed!$A:$A,0),_xlpm.p,INDEX(Feed!$B:$B,_xlpm.m),_xlpm.c,INDEX(Feed!$G:$G,_xlpm.m),IF(AND(_xlpm.p>0,_xlpm.c>0),_xlpm.p/_xlpm.c-1,"")),"") -> 0.0051239604 | F5: =IF(ISNUMBER(E5),D5*E5,0) -> 0.00019164386 | G5: =IF(ISNUMBER(E5),D5,0) -> 0.03740151 | H5: SPDR | I5: 46288
A6: SPY | B6: GOOGL | C6: ALPHABET INC CL A | D6: 0.03079188 | E6: =IFERROR(_xlfn.LET(_xlpm.m,MATCH($B6,Feed!$A:$A,0),_xlpm.p,INDEX(Feed!$B:$B,_xlpm.m),_xlpm.c,INDEX(Feed!$G:$G,_xlpm.m),IF(AND(_xlpm.p>0,_xlpm.c>0),_xlpm.p/_xlpm.c-1,"")),"") -> 0.0051496252 | F6: =IF(ISNUMBER(E6),D6*E6,0) -> 0.00015856664 | G6: =IF(ISNUMBER(E6),D6,0) -> 0.03079188 | H6: SPDR | I6: 46288
A7: SPY | B7: AVGO | C7: BROADCOM INC | D7: 0.02591796 | E7: =IFERROR(_xlfn.LET(_xlpm.m,MATCH($B7,Feed!$A:$A,0),_xlpm.p,INDEX(Feed!$B:$B,_xlpm.m),_xlpm.c,INDEX(Feed!$G:$G,_xlpm.m),IF(AND(_xlpm.p>0,_xlpm.c>0),_xlpm.p/_xlpm.c-1,"")),"") -> 0.020170327 | F7: =IF(ISNUMBER(E7),D7*E7,0) -> 0.00052277373 | G7: =IF(ISNUMBER(E7),D7,0) -> 0.02591796 | H7: SPDR | I7: 46288
A8: SPY | B8: GOOG | C8: ALPHABET INC CL C | D8: 0.02467734 | E8: =IFERROR(_xlfn.LET(_xlpm.m,MATCH($B8,Feed!$A:$A,0),_xlpm.p,INDEX(Feed!$B:$B,_xlpm.m),_xlpm.c,INDEX(Feed!$G:$G,_xlpm.m),IF(AND(_xlpm.p>0,_xlpm.c>0),_xlpm.p/_xlpm.c-1,"")),"") -> 0.0092622165 | F8: =IF(ISNUMBER(E8),D8*E8,0) -> 0.00022856687 | G8: =IF(ISNUMBER(E8),D8,0) -> 0.02467734 | H8: SPDR | I8: 46288
A9: SPY | B9: META | C9: META PLATFORMS INC CLASS A | D9: 0.0242733 | E9: =IFERROR(_xlfn.LET(_xlpm.m,MATCH($B9,Feed!$A:$A,0),_xlpm.p,INDEX(Feed!$B:$B,_xlpm.m),_xlpm.c,INDEX(Feed!$G:$G,_xlpm.m),IF(AND(_xlpm.p>0,_xlpm.c>0),_xlpm.p/_xlpm.c-1,"")),"") -> 0.10754857 | F9: =IF(ISNUMBER(E9),D9*E9,0) -> 0.0026105588 | G9: =IF(ISNUMBER(E9),D9,0) -> 0.0242733 | H9: SPDR | I9: 46288
A10: SPY | B10: MU | C10: MICRON TECHNOLOGY INC | D10: 0.01850078 | E10: =IFERROR(_xlfn.LET(_xlpm.m,MATCH($B10,Feed!$A:$A,0),_xlpm.p,INDEX(Feed!$B:$B,_xlpm.m),_xlpm.c,INDEX(Feed!$G:$G,_xlpm.m),IF(AND(_xlpm.p>0,_xlpm.c>0),_xlpm.p/_xlpm.c-1,"")),"") -> 0.07776137 | F10: =IF(ISNUMBER(E10),D10*E10,0) -> 0.001438646 | G10: =IF(ISNUMBER(E10),D10,0) -> 0.01850078 | H10: SPDR | I10: 46288
A11: SPY | B11: TSLA | C11: TESLA INC | D11: 0.01595585 | E11: =IFERROR(_xlfn.LET(_xlpm.m,MATCH($B11,Feed!$A:$A,0),_xlpm.p,INDEX(Feed!$B:$B,_xlpm.m),_xlpm.c,INDEX(Feed!$G:$G,_xlpm.m),IF(AND(_xlpm.p>0,_xlpm.c>0),_xlpm.p/_xlpm.c-1,"")),"") | F11: =IF(ISNUMBER(E11),D11*E11,0) -> 0 | G11: =IF(ISNUMBER(E11),D11,0) -> 0 | H11: SPDR | I11: 46288
A12: SPY | B12: AMD | C12: ADVANCED MICRO DEVICES | D12: 0.01521514 | E12: =IFERROR(_xlfn.LET(_xlpm.m,MATCH($B12,Feed!$A:$A,0),_xlpm.p,INDEX(Feed!$B:$B,_xlpm.m),_xlpm.c,INDEX(Feed!$G:$G,_xlpm.m),IF(AND(_xlpm.p>0,_xlpm.c>0),_xlpm.p/_xlpm.c-1,"")),"") -> 0.11258976 | F12: =IF(ISNUMBER(E12),D12*E12,0) -> 0.001713069 | G12: =IF(ISNUMBER(E12),D12,0) -> 0.01521514 | H12: SPDR | I12: 46288
A13: SPY | B13: BRK-B | C13: BERKSHIRE HATHAWAY INC CL B | D13: 0.01401308 | E13: =IFERROR(_xlfn.LET(_xlpm.m,MATCH($B13,Feed!$A:$A,0),_xlpm.p,INDEX(Feed!$B:$B,_xlpm.m),_xlpm.c,INDEX(Feed!$G:$G,_xlpm.m),IF(AND(_xlpm.p>0,_xlpm.c>0),_xlpm.p/_xlpm.c-1,"")),"") -> -0.012162348 | F13: =IF(ISNUMBER(E13),D13*E13,0) -> -0.00017043195 | G13: =IF(ISNUMBER(E13),D13,0) -> 0.01401308 | H13: SPDR | I13: 46288
... A836: XLV | B836: DVA | C836: DAVITA INC | D836: 0.00100582 | E836: =IFERROR(_xlfn.LET(_xlpm.m,MATCH($B836,Feed!$A:$A,0),_xlpm.p,INDEX(Feed!$B:$B,_xlpm.m),_xlpm.c,INDEX(Feed!$G:$G,_xlpm.m),IF(AND(_xlpm.p>0,_xlpm.c>0),_xlpm.p/_xlpm.c-1,"")),"") -> -0.00076144893 | F836: =IF(ISNUMBER(E836),D836*E836,0) -> -7.6588056e-07 | G836: =IF(ISNUMBER(E836),D836,0) -> 0.00100582 | H836: SPDR | I836: 46288

Sheet Charts
A1: ETF | B1: AAPU
A2: Days | B2: 126

Sheet Chart Data
A1: Date | B1: ETF | C1: Underlying | D1: Spread (bps) | E1: Volume
A2: 46104 | B2: 102.6967 | C2: 102.8227 | D2: -12.5997 | E2: 2035700
A3: 46105 | B3: 102.9309 | C3: 102.9453 | D3: -1.723 | E3: 1328600
A4: 46106 | B4: 103.6372 | C4: 103.7472 | D4: -10.9957 | E4: 1247100
A5: 46107 | B5: 103.8602 | C5: 103.969 | D5: -10.8514 | E5: 2024300
A6: 46108 | B6: 100.4032 | C6: 100.606 | D6: -20.2462 | E6: 1508600
A7: 46111 | B7: 98.6189 | C7: 98.851 | D7: -23.5205 | E7: 1353600
A8: 46112 | B8: 104.3063 | C8: 104.5906 | D8: -27.4428 | E8: 1775000
A9: 46113 | B9: 105.8304 | C9: 106.1072 | D9: -26.3294 | E9: 2008300
A10: 46114 | B10: 105.9419 | C10: 106.3479 | D10: -38.4801 | E10: 1540900
A11: 46118 | B11: 108.4324 | C11: 108.7913 | D11: -33.1512 | E11: 1267300
A12: 46119 | B12: 103.8602 | C12: 104.286 | D12: -40.6939 | E12: 4435700
A13: 46120 | B13: 108.3209 | C13: 108.729 | D13: -37.2393 | E13: 1553400
... A127: 46286 | B127: 172.6351 | C127: 180.3469 | D127: -449.4161 | E127: 702700

Sheet Config
A1: Setting | B1: Value
A2: Live | B2: Y
A3: Refresh (sec) | B3: 5
A4: Equity cost (bps) | B4: 3
A5: FI cost (bps) | B5: 8
A6: Equity min edge (bps) | B6: 2
A7: FI min edge (bps) | B7: 5
A8: Anchor (CLOSE/NAV) | B8: CLOSE
A9: Stale after (min) | B9: 20
A10: Ex-div flag (bps) | B10: 30
A11: Holdings shown | B11: 3
A12: Max basket names | B12: 600
A13: History period | B13: 1y
A14: Beta lookback (days) | B14: 120
A15: Resid lookback (days) | B15: 60
A16: Vol lookback (days) | B16: 60
A17: Chart refresh (sec) | B17: 120
A18: Log intraday | B18: Y

Sheet Feed
A1: Symbol | B1: Last | C1: Bid | D1: Ask | E1: Bid Sz | F1: Ask Sz | G1: Prev Close | H1: Volume | I1: Avg Vol | J1: NAV | K1: Yield | L1: Sigma | M1: Time | N1: Beta | O1: Resid Mean | P1: Resid SD | R1: Session Left
A2: SPY | B2: 773.6197 | C2: 773.61 | D2: 773.66 | E2: 246 | F2: 1620 | G2: 761.69 | H2: 50486686 | J2: 762.0114 | K2: 0.0098 | L2: 0.0073762093 | M2: 46287.672 | N2: 1 | O2: -3.1026107e-05 | P2: 0.0010921634 | R2: 0
A3: QQQ | B3: 747.45 | C3: 747.45 | D3: 747.48 | E3: 180 | F3: 100 | G3: 720.6986 | H3: 46731300 | J3: 721.72 | K3: 0.0042 | L3: 0.01324884 | M3: 46287.672 | N3: 1 | O3: -7.6728869e-06 | P3: 0.00087942103
A4: XLK | B4: 196.229 | C4: 195.6 | D4: 196.24 | E4: 400 | F4: 100 | G4: 189.6 | H4: 9047360 | J4: 189.69778 | K4: 0.0043 | L4: 0.018249068 | M4: 46287.673 | N4: 1 | O4: -0.00016313162 | P4: 0.00083223394
A5: XLF | B5: 54.8 | G5: 55.86 | H5: 30640768 | J5: 55.90363 | K5: 0.014 | L5: 0.00816815 | M5: 46287.671 | N5: 1 | O5: -5.315486e-06 | P5: 0.00050362288
A6: XLE | B6: 61.78 | G6: 64.31 | H6: 36482216 | J6: 64.3543 | K6: 0.023699999 | L6: 0.013677719 | M6: 46287.671 | N6: 1 | O6: 8.8664632e-05 | P6: 0.00090341354
A7: XLV | B7: 170.34 | C7: 169.55 | D7: 170.35 | E7: 100 | F7: 700 | G7: 168.39 | H7: 7618319 | J7: 168.47356 | K7: 0.0149 | L7: 0.012011046 | M7: 46287.673 | N7: 1 | O7: -2.5233536e-05 | P7: 0.00046629262
A8: IWM | B8: 285.4921 | G8: 284.1 | H8: 18968224 | J8: 283.9969 | K8: 0.009 | L8: 0.008127509 | M8: 46287.672 | N8: 0.99819867 | O8: -1.2839089e-05 | P8: 0.00136385
A9: AAPU | B9: 46.14 | G9: 45.27 | H9: 706522 | J9: 45.386 | K9: 0.0186 | L9: 0.036577395 | M9: 46287.671 | N9: 2 | O9: -0.0003858289 | P9: 0.0016894243
A10: TLT | B10: 81.69 | C10: 81.7 | D10: 81.72 | E10: 1600 | F10: 1300 | G10: 81.25 | H10: 26981681 | J10: 81.15524 | K10: 0.0473 | L10: 0.0059716259 | M10: 46287.673 | N10: 1.0740028 | O10: -3.3884059e-05 | P10: 0.00051905822
A11: IEF | B11: 91.14 | G11: 90.8 | H11: 8833521 | J11: 90.75945 | K11: 0.0397 | L11: 0.0029743916 | M11: 46287.671 | N11: 1.3887398 | O11: -2.0551889e-05 | P11: 0.00054245509
A12: SHY | B12: 81.3015 | C12: 81.3 | D12: 81.31 | E12: 116049 | F12: 6100 | G12: 81.24 | H12: 3973124 | J12: 81.22375 | K12: 0.0363 | L12: 0.00086285564 | M12: 46287.673 | N12: 1.0304722 | O12: -1.2011801e-06 | P12: 0.00021328568
A13: LQD | B13: 105.09 | G13: 104.7 | H13: 23076568 | J13: 104.60595 | K13: 0.0467 | L13: 0.003448224 | M13: 46287.671 | N13: 1.0508315 | O13: 2.1715149e-05 | P13: 0.0010979121
A14: VCIT | B14: 79.95 | C14: 79.9 | D14: 80.35 | E14: 700 | F14: 31 | G14: 79.69 | H14: 10353336 | J14: 79.64 | K14: 0.048899997 | L14: 0.0027199828 | M14: 46287.673 | N14: 0.87552298 | O14: 4.016758e-05 | P14: 0.00063716917
A15: HYG | B15: 78.67 | G15: 78.53 | H15: 44495821 | J15: 78.42535 | K15: 0.0588 | L15: 0.0017903913 | M15: 46287.671 | N15: 1.014561 | O15: -6.026686e-06 | P15: 0.00029398754
A16: AGG | B16: 96.25 | C16: 96 | D16: 97.26 | E16: 100 | F16: 50 | G16: 95.96 | H16: 9197633 | J16: 95.90445 | K16: 0.0405 | L16: 0.0025338951 | M16: 46287.673 | N16: 1.0340765 | O16: -1.854961e-06 | P16: 0.00021987032
A17: TIP | B17: 105.55 | C17: 105.55 | D17: 105.57 | E17: 11506 | F17: 400 | G17: 105.27 | H17: 1757608 | J17: 105.26104 | K17: 0.0498 | L17: 0.0021936613 | M17: 46287.672 | N17: 0.99680542 | O17: -9.0342129e-06 | P17: 0.00037069835
A18: MUB | B18: 102.75 | G18: 102.88 | H18: 8743685 | J18: 102.63043 | K18: 0.0325 | L18: 0.0022422134 | M18: 46287.671 | N18: 1.0208871 | O18: 2.4440209e-05 | P18: 0.00047235551
A19: A | B19: 167.26 | G19: 156.47 | H19: 2710412 | L19: 0.017637269 | M19: 46287.671
A20: AAPL | G20: 338.98001 | L20: 0.018439339
A21: ABBV | B21: 265.21 | G21: 263.96 | H21: 3438160 | L21: 0.015757903 | M21: 46287.671
A22: ABNB | B22: 161.81 | G22: 166.22 | H22: 3301800 | L22: 0.029691324 | M22: 46287.671
A23: ABT | B23: 103.69 | G23: 102.61 | H23: 5018290 | L23: 0.02010459 | M23: 46287.671
A24: ACGL | B24: 96.406 | G24: 96.89 | H24: 4102033 | L24: 0.014502499 | M24: 46287.671
A25: ACN | B25: 182.15 | G25: 181.29 | H25: 7419162 | L25: 0.029911926 | M25: 46287.671
A26: ADBE | B26: 238.43 | G26: 248.92 | H26: 5186640 | L26: 0.030712659 | M26: 46287.671
A27: ADI | B27: 390.37 | G27: 375.72 | H27: 4050448 | L27: 0.022678063 | M27: 46287.671
A28: ADM | B28: 83.11 | G28: 85.18 | H28: 2565830 | L28: 0.01800999 | M28: 46287.671
A29: ADP | B29: 269.64 | G29: 271.22 | H29: 2307379 | L29: 0.018988042 | M29: 46287.671
A30: ADSK | B30: 219.62 | G30: 216.95 | H30: 1528518 | L30: 0.029806324 | M30: 46287.671
A31: AEE | B31: 101.66 | G31: 102.23 | H31: 1852613 | L31: 0.011739343 | M31: 46287.671
A32: AEP | B32: 120.27 | G32: 120 | H32: 6986209 | L32: 0.011102305 | M32: 46287.671
... A80: BEN | B80: 33.13 | G80: 33.01 | H80: 4988971 | L80: 0.015104783 | M80: 46287.671
A81: BF-B | B81: 26.56 | G81: 26.15 | L81: 0.022256688 | M81: 46287.671
A82: BG | B82: 110 | G82: 115.58 | H82: 1583079 | L82: 0.022488652 | M82: 46287.671
A83: BIIB | B83: 225.36 | G83: 215.5 | H83: 928563 | L83: 0.02474604 | M83: 46287.671
A84: BKNG | B84: 164.22 | G84: 167.9 | H84: 6994688 | L84: 0.024952237 | M84: 46287.671
A85: BKR | B85: 57.26 | G85: 57.25 | H85: 7974891 | L85: 0.019991182 | M85: 46287.671
A86: BLK | B86: 1066.66 | G86: 1069.78 | H86: 512501 | L86: 0.017290826 | M86: 46287.671
A87: BMY | B87: 62.25 | G87: 63.06 | H87: 6839128 | L87: 0.017654678 | M87: 46287.671
A88: BND | B88: 71.41 | G88: 71.2 | H88: 7596009 | L88: 0.0024393467 | M88: 46287.671
A89: BNY | B89: 150.17 | G89: 153.79 | H89: 3645745 | L89: 0.013802664 | M89: 46287.671
A90: BR | B90: 160 | G90: 163.13 | H90: 1078766 | L90: 0.021680911 | M90: 46287.671
A91: BRK-B | B91: 503.57 | G91: 509.77 | H91: 4807459 | L91: 0.0096126656 | M91: 46287.671
A92: BRO | B92: 62.44 | G92: 65.02 | H92: 2328331 | L92: 0.022563751 | M92: 46287.671
A93: BSX | B93: 44.59 | G93: 43.34 | H93: 24998926 | L93: 0.023054515 | M93: 46287.671
... A401: PKG | B401: 238.23 | G401: 232.77 | H401: 720261 | L401: 0.017996399 | M401: 46287.671
A402: PLD | G402: 135.82001 | L402: 0.013432074
A403: PLTR | G403: 183.09 | L403: 0.049655693
A404: PM | G404: 187.48 | L404: 0.017027301
A405: PNC | G405: 233.25 | L405: 0.011249474
A406: PNR | G406: 55.779999 | L406: 0.025950325
A407: PNW | G407: 93.309998 | L407: 0.010222202
A408: PODD | G408: 140.53 | L408: 0.034612084
A409: PPG | G409: 106.625 | L409: 0.018388115
A410: PPL | G410: 33.049999 | L410: 0.011572117
A411: PRU | G411: 118.53 | L411: 0.012920512
A412: PSA | G412: 296.67001 | L412: 0.013692049
A413: PSKY | G413: 9.9099998 | L413: 0.025294364
... A421: RCL | G421: 250.25 | L421: 0.019188702
A422: RDDT | B422: 155.67 | G422: 150.85 | H422: 5464344 | L422: 0.052335758 | M422: 46287.671
A423: REG | B423: 73.13 | G423: 72.95 | H423: 1346042 | L423: 0.0097697252 | M423: 46287.671
A424: REGN | B424: 803.9 | G424: 784.85 | H424: 704529 | L424: 0.019518228 | M424: 46287.671
A425: RF | B425: 27.91 | G425: 28.5 | H425: 6634025 | L425: 0.01332489 | M425: 46287.671
A426: RJF | B426: 159.39 | G426: 165.19 | H426: 2122223 | L426: 0.014686977 | M426: 46287.671
A427: RKLB | B427: 71.904 | G427: 64.57 | H427: 26038799 | L427: 0.049921503 | M427: 46287.671
A428: RL | B428: 346.06 | G428: 335.1 | H428: 666337 | L428: 0.018893261 | M428: 46287.671
A429: RMD | B429: 221.97 | G429: 224.99 | H429: 1072146 | L429: 0.023049145 | M429: 46287.671
A430: ROK | B430: 428.75 | G430: 415.62 | H430: 755318 | L430: 0.017914011 | M430: 46287.671
A431: ROL | B431: 32.86 | G431: 32.43 | H431: 6589851 | L431: 0.019033208 | M431: 46287.671
A432: ROP | B432: 363.85 | G432: 372.74 | H432: 1030938 | L432: 0.022017297 | M432: 46287.671
A433: ROST | B433: 232.51 | G433: 226.61 | H433: 2228670 | L433: 0.015918964 | M433: 46287.671
... A439: SCHO | B439: 23.9 | G439: 23.89 | H439: 4113380 | L439: 0.0008085611 | M439: 46287.671
A440: SCHP | B440: 25.52 | C440: 25.51 | D440: 25.52 | E440: 1500 | F440: 70385 | G440: 25.44 | H440: 5560989 | L440: 0.0021269905 | M440: 46287.683
A441: SCHR | B441: 23.99 | G441: 23.93 | H441: 2749449 | L441: 0.0020755871 | M441: 46287.671
A442: SCHW | B442: 100.8 | G442: 105.25 | H442: 5444867 | L442: 0.013679853 | M442: 46287.671
A443: SCHZ | B443: 22.49 | G443: 22.42 | H443: 1569205 | L443: 0.0024568744 | M443: 46287.671
A444: SHOP | B444: 147.69 | G444: 128.5 | H444: 16650102 | L444: 0.040328055 | M444: 46287.671
A445: SHW | B445: 328.35 | G445: 320.73 | H445: 1511664 | L445: 0.019421171 | M445: 46287.671
A446: SJM | B446: 121.11 | G446: 122.95 | H446: 1364576 | L446: 0.018700438 | M446: 46287.671
A447: SLB | B447: 52.12 | G447: 51.12 | H447: 11322082 | L447: 0.025103963 | M447: 46287.671
A448: SMCI | B448: 41.39 | G448: 39.09 | H448: 48218370 | L448: 0.057824485 | M448: 46287.671
A449: SNA | B449: 371.8 | G449: 372.15 | H449: 326473 | L449: 0.010828264 | M449: 46287.671
A450: SNDK | B450: 1881.155 | G450: 1791.82 | H450: 10442863 | L450: 0.079073153 | M450: 46287.671
A451: SNPS | B451: 409.24 | G451: 384.97 | H451: 1669226 | L451: 0.030250067 | M451: 46287.671
A452: SO | B452: 85.15 | G452: 85.52 | H452: 7828975 | L452: 0.010218183 | M452: 46287.671
... A481: TMO | B481: 658.52 | G481: 651.45 | H481: 2303878 | L481: 0.018413046 | M481: 46287.671
A482: TMUS | G482: 165.27 | L482: 0.026340043
A483: TPL | G483: 366.79999 | L483: 0.02853183
A484: TPR | G484: 113.07 | L484: 0.028806705
A485: TRGP | G485: 289.35999 | L485: 0.02015976
A486: TRI | G486: 95.43 | L486: 0.038488762
A487: TRMB | G487: 57.75 | L487: 0.020923543
A488: TROW | G488: 104.63 | L488: 0.01684528
A489: TRV | G489: 371.13 | L489: 0.017787953
A490: TSCO | G490: 32.330002 | L490: 0.019343654
A491: TSLA | G491: 375.29999 | L491: 0.035527393
A492: TSN | G492: 52.505001 | L492: 0.0173976
A493: TT | G493: 433.32001 | L493: 0.016432043
... A512: VFH | G512: 136.75999 | L512: 0.0081557245
...
